Workbook
Name Indoor: OFFSET([1]Indoor!$A$2,MATCH(Total_Москва!#REF!,[1]Indoor!$A$2:$A$996,0)-1,1,COUNTIF([1]Indoor!$A$2:$A$996,Total_Москва!#REF!),1)
Name Indoor: OFFSET([1]Indoor!$A$2,MATCH('Медиа факторы'!#REF!,[1]Indoor!$A$2:$A$996,0)-1,1,COUNTIF([1]Indoor!$A$2:$A$996,'Медиа факторы'!#REF!),1)
Name Indoor: OFFSET([2]Indoor!$A$2,MATCH(Москва!$E$4,[2]Indoor!$A$2:$A$996,0)-1,1,COUNTIF([2]Indoor!$A$2:$A$996,Москва!$E$4),1)
Name Indoor: OFFSET([1]Indoor!$A$2,MATCH(Фильтры!#REF!,[1]Indoor!$A$2:$A$996,0)-1,1,COUNTIF([1]Indoor!$A$2:$A$996,Фильтры!#REF!),1)
Name Indoor: OFFSET([1]Indoor!$A$2,MATCH(#REF!,[1]Indoor!$A$2:$A$996,0)-1,1,COUNTIF([1]Indoor!$A$2:$A$996,#REF!),1)
Name OTSРадио: OFFSET([1]Радиостанции!$B$1,MATCH(Total_Москва!#REF!,[1]Радиостанции!$B:$B,0)-1,3,COUNTIF([1]Радиостанции!$B:$B,Total_Москва!#REF!),1)
Name OTSРадио: OFFSET([1]Радиостанции!$B$1,MATCH('Медиа факторы'!$C1,[1]Радиостанции!$B:$B,0)-1,3,COUNTIF([1]Радиостанции!$B:$B,'Медиа факторы'!$C1),1)
Name OTSРадио: OFFSET([2]Радиостанции!$B$1,MATCH(Москва!$E1,[2]Радиостанции!$B:$B,0)-1,3,COUNTIF([2]Радиостанции!$B:$B,Москва!$E1),1)
Name OTSРадио: OFFSET([1]Радиостанции!$B$1,MATCH(Фильтры!$B1,[1]Радиостанции!$B:$B,0)-1,3,COUNTIF([1]Радиостанции!$B:$B,Фильтры!$B1),1)
Name OTSРадио: OFFSET([1]Радиостанции!$B$1,MATCH(#REF!,[1]Радиостанции!$B:$B,0)-1,3,COUNTIF([1]Радиостанции!$B:$B,#REF!),1)
Name OTSРадиоМосква: OFFSET([1]Радиостанции!$C$1,MATCH(Total_Москва!$E1,[1]Радиостанции!$C:$C,0)-1,3,COUNTIF([1]Радиостанции!$C:$C,Total_Москва!$E1),1)
Name OTSРадиоМосква: OFFSET([1]Радиостанции!$C$1,MATCH('Медиа факторы'!$N1,[1]Радиостанции!$C:$C,0)-1,3,COUNTIF([1]Радиостанции!$C:$C,'Медиа факторы'!$N1),1)
Name OTSРадиоМосква: OFFSET([2]Радиостанции!$C$1,MATCH(Москва!$P1,[2]Радиостанции!$C:$C,0)-1,3,COUNTIF([2]Радиостанции!$C:$C,Москва!$P1),1)
Name OTSРадиоМосква: OFFSET([1]Радиостанции!$C$1,MATCH(Фильтры!#REF!,[1]Радиостанции!$C:$C,0)-1,3,COUNTIF([1]Радиостанции!$C:$C,Фильтры!#REF!),1)
Name OTSРадиоМосква: OFFSET([1]Радиостанции!$C$1,MATCH(#REF!,[1]Радиостанции!$C:$C,0)-1,3,COUNTIF([1]Радиостанции!$C:$C,#REF!),1)
Name OTSТВ: OFFSET('[1]ТВ Каналы'!$B$1,MATCH(Total_Москва!#REF!,'[1]ТВ Каналы'!$B:$B,0)-1,4,COUNTIF('[1]ТВ Каналы'!$B:$B,Total_Москва!#REF!),1)
Name OTSТВ: OFFSET('[1]ТВ Каналы'!$B$1,MATCH('Медиа факторы'!$C1,'[1]ТВ Каналы'!$B:$B,0)-1,4,COUNTIF('[1]ТВ Каналы'!$B:$B,'Медиа факторы'!$C1),1)
Name OTSТВ: OFFSET('[2]ТВ Каналы'!$B$1,MATCH(Москва!$E1,'[2]ТВ Каналы'!$B:$B,0)-1,4,COUNTIF('[2]ТВ Каналы'!$B:$B,Москва!$E1),1)
Name OTSТВ: OFFSET('[1]ТВ Каналы'!$B$1,MATCH(Фильтры!$B1,'[1]ТВ Каналы'!$B:$B,0)-1,4,COUNTIF('[1]ТВ Каналы'!$B:$B,Фильтры!$B1),1)
Name OTSТВ: OFFSET('[1]ТВ Каналы'!$B$1,MATCH(#REF!,'[1]ТВ Каналы'!$B:$B,0)-1,4,COUNTIF('[1]ТВ Каналы'!$B:$B,#REF!),1)
Name OTSТВМосква: OFFSET('[1]ТВ Каналы'!$C$1,MATCH(Total_Москва!$E1,'[1]ТВ Каналы'!$C:$C,0)-1,3,COUNTIF('[1]ТВ Каналы'!$C:$C,Total_Москва!$E1),1)
Name OTSТВМосква: OFFSET('[1]ТВ Каналы'!$C$1,MATCH('Медиа факторы'!$N1,'[1]ТВ Каналы'!$C:$C,0)-1,3,COUNTIF('[1]ТВ Каналы'!$C:$C,'Медиа факторы'!$N1),1)
Name OTSТВМосква: OFFSET('[2]ТВ Каналы'!$C$1,MATCH(Москва!$P1,'[2]ТВ Каналы'!$C:$C,0)-1,3,COUNTIF('[2]ТВ Каналы'!$C:$C,Москва!$P1),1)
Name OTSТВМосква: OFFSET('[1]ТВ Каналы'!$C$1,MATCH(Фильтры!#REF!,'[1]ТВ Каналы'!$C:$C,0)-1,3,COUNTIF('[1]ТВ Каналы'!$C:$C,Фильтры!#REF!),1)
Name OTSТВМосква: OFFSET('[1]ТВ Каналы'!$C$1,MATCH(#REF!,'[1]ТВ Каналы'!$C:$C,0)-1,3,COUNTIF('[1]ТВ Каналы'!$C:$C,#REF!),1)
Name OTSТВСумм: SUM(Total_Москва!OTSТВ)
Name OTSТВСумм: SUM('Медиа факторы'!OTSТВ)
Name OTSТВСумм: SUM(Москва!OTSТВ)
Name OTSТВСумм: SUM(Фильтры!OTSТВ)
Name OTSТВСумм: SUM(OTSТВ)
Name Канал: OFFSET([1]ТВ!$A$1,MATCH(Total_Москва!#REF!,[1]ТВ!$A:$A,0)-1,1,COUNTIF([1]ТВ!$A:$A,Total_Москва!#REF!),1)
Name Канал: OFFSET([1]ТВ!$A$1,MATCH('Медиа факторы'!#REF!,[1]ТВ!$A:$A,0)-1,1,COUNTIF([1]ТВ!$A:$A,'Медиа факторы'!#REF!),1)
Name Канал: OFFSET([2]ТВ!$A$1,MATCH(Москва!$E$4,[2]ТВ!$A:$A,0)-1,1,COUNTIF([2]ТВ!$A:$A,Москва!$E$4),1)
Name Канал: OFFSET([1]ТВ!$A$1,MATCH(Фильтры!#REF!,[1]ТВ!$A:$A,0)-1,1,COUNTIF([1]ТВ!$A:$A,Фильтры!#REF!),1)
Name Канал: OFFSET([1]ТВ!$A$1,MATCH(#REF!,[1]ТВ!$A:$A,0)-1,1,COUNTIF([1]ТВ!$A:$A,#REF!),1)
Name МинутыРадио: OFFSET([1]Радиостанции!$B$1,MATCH(Total_Москва!#REF!,[1]Радиостанции!$B:$B,0)-1,2,COUNTIF([1]Радиостанции!$B:$B,Total_Москва!#REF!),1)
Name МинутыРадио: OFFSET([1]Радиостанции!$B$1,MATCH('Медиа факторы'!$C1,[1]Радиостанции!$B:$B,0)-1,2,COUNTIF([1]Радиостанции!$B:$B,'Медиа факторы'!$C1),1)
Name МинутыРадио: OFFSET([2]Радиостанции!$B$1,MATCH(Москва!$E1,[2]Радиостанции!$B:$B,0)-1,2,COUNTIF([2]Радиостанции!$B:$B,Москва!$E1),1)
Name МинутыРадио: OFFSET([1]Радиостанции!$B$1,MATCH(Фильтры!$B1,[1]Радиостанции!$B:$B,0)-1,2,COUNTIF([1]Радиостанции!$B:$B,Фильтры!$B1),1)
Name МинутыРадио: OFFSET([1]Радиостанции!$B$1,MATCH(#REF!,[1]Радиостанции!$B:$B,0)-1,2,COUNTIF([1]Радиостанции!$B:$B,#REF!),1)
Name МинутыРадиоМосква: OFFSET([1]Радиостанции!$C$1,MATCH(Total_Москва!$E1,[1]Радиостанции!$C:$C,0)-1,2,COUNTIF([1]Радиостанции!$C:$C,Total_Москва!$E1),1)
Name МинутыРадиоМосква: OFFSET([1]Радиостанции!$C$1,MATCH('Медиа факторы'!$N1,[1]Радиостанции!$C:$C,0)-1,2,COUNTIF([1]Радиостанции!$C:$C,'Медиа факторы'!$N1),1)
Name МинутыРадиоМосква: OFFSET([2]Радиостанции!$C$1,MATCH(Москва!$P1,[2]Радиостанции!$C:$C,0)-1,2,COUNTIF([2]Радиостанции!$C:$C,Москва!$P1),1)
Name МинутыРадиоМосква: OFFSET([1]Радиостанции!$C$1,MATCH(Фильтры!#REF!,[1]Радиостанции!$C:$C,0)-1,2,COUNTIF([1]Радиостанции!$C:$C,Фильтры!#REF!),1)
Name МинутыРадиоМосква: OFFSET([1]Радиостанции!$C$1,MATCH(#REF!,[1]Радиостанции!$C:$C,0)-1,2,COUNTIF([1]Радиостанции!$C:$C,#REF!),1)
Name МинутыТВ: OFFSET('[1]ТВ Каналы'!$B$1,MATCH(Total_Москва!#REF!,'[1]ТВ Каналы'!$B:$B,0)-1,2,COUNTIF('[1]ТВ Каналы'!$B:$B,Total_Москва!#REF!),1)
Name МинутыТВ: OFFSET('[1]ТВ Каналы'!$B$1,MATCH('Медиа факторы'!$C1,'[1]ТВ Каналы'!$B:$B,0)-1,2,COUNTIF('[1]ТВ Каналы'!$B:$B,'Медиа факторы'!$C1),1)
Name МинутыТВ: OFFSET('[2]ТВ Каналы'!$B$1,MATCH(Москва!$E1,'[2]ТВ Каналы'!$B:$B,0)-1,2,COUNTIF('[2]ТВ Каналы'!$B:$B,Москва!$E1),1)
Name МинутыТВ: OFFSET('[1]ТВ Каналы'!$B$1,MATCH(Фильтры!$B1,'[1]ТВ Каналы'!$B:$B,0)-1,2,COUNTIF('[1]ТВ Каналы'!$B:$B,Фильтры!$B1),1)
Name МинутыТВ: OFFSET('[1]ТВ Каналы'!$B$1,MATCH(#REF!,'[1]ТВ Каналы'!$B:$B,0)-1,2,COUNTIF('[1]ТВ Каналы'!$B:$B,#REF!),1)
Name МинутыТВМосква: OFFSET('[1]ТВ Каналы'!$C$1,MATCH(Total_Москва!$E1,'[1]ТВ Каналы'!$C:$C,0)-1,2,COUNTIF('[1]ТВ Каналы'!$C:$C,Total_Москва!$E1),1)
Name МинутыТВМосква: OFFSET('[1]ТВ Каналы'!$C$1,MATCH('Медиа факторы'!$N1,'[1]ТВ Каналы'!$C:$C,0)-1,2,COUNTIF('[1]ТВ Каналы'!$C:$C,'Медиа факторы'!$N1),1)
Name МинутыТВМосква: OFFSET('[2]ТВ Каналы'!$C$1,MATCH(Москва!$P1,'[2]ТВ Каналы'!$C:$C,0)-1,2,COUNTIF('[2]ТВ Каналы'!$C:$C,Москва!$P1),1)
Name МинутыТВМосква: OFFSET('[1]ТВ Каналы'!$C$1,MATCH(Фильтры!#REF!,'[1]ТВ Каналы'!$C:$C,0)-1,2,COUNTIF('[1]ТВ Каналы'!$C:$C,Фильтры!#REF!),1)
Name МинутыТВМосква: OFFSET('[1]ТВ Каналы'!$C$1,MATCH(#REF!,'[1]ТВ Каналы'!$C:$C,0)-1,2,COUNTIF('[1]ТВ Каналы'!$C:$C,#REF!),1)
Name Радио: OFFSET([1]Radio!$A$1,MATCH(Total_Москва!#REF!,[1]Radio!$A:$A,0)-1,1,COUNTIF([1]Radio!$A:$A,Total_Москва!#REF!),1)
Name Радио: OFFSET([1]Radio!$A$1,MATCH('Медиа факторы'!#REF!,[1]Radio!$A:$A,0)-1,1,COUNTIF([1]Radio!$A:$A,'Медиа факторы'!#REF!),1)
Name Радио: OFFSET([2]Radio!$A$1,MATCH(Москва!$E$4,[2]Radio!$A:$A,0)-1,1,COUNTIF([2]Radio!$A:$A,Москва!$E$4),1)
Name Радио: OFFSET([1]Radio!$A$1,MATCH(Фильтры!#REF!,[1]Radio!$A:$A,0)-1,1,COUNTIF([1]Radio!$A:$A,Фильтры!#REF!),1)
Name Радио: OFFSET([1]Radio!$A$1,MATCH(#REF!,[1]Radio!$A:$A,0)-1,1,COUNTIF([1]Radio!$A:$A,#REF!),1)

Sheet Медиа факторы
A1: Медиа факторы | B1: Описание | C1: Форматы | D1: Период размещения, дни | E1: Доля брендирования | F1: OTS 16+ ('000) | G1: Охват 16+* ('000) | H1: OTS 16+ ('000) (с учетом доли брендирования) | I1: Взаимодействие с контентом | J1: Характеристики инвентаря и аудитории | K1: Хронометраж | L1: Время взаимодействия с креативом | M1: Охват 16+ ('000) (с учетом доли брендирования)
A2: Тип активации: ДО МЕРОПРИЯТИЯ (медиа продвижение и PR) | B2: ООН | C2: BB | D2: 120 | E2: 0.3 | F2: 50000 | H2: 15000 | L2: 0 | M2: 1000
A3: Тип активации: ДО МЕРОПРИЯТИЯ (медиа продвижение и PR) | B3: Indoor | C3: Авиапарк | D3: 120 | E3: 0.3 | F3: 5000 | H3: 1500 | L3: 0 | M3: 300
A4: Тип активации: ДО МЕРОПРИЯТИЯ (медиа продвижение и PR) | B4: Радио | C4: Прямая Реклама | D4: 120 | E4: 0.2 | H4: 196668.21 | I4: 1076 | K4: 30 | L4: 15.84 | M4: 8304 | N4: =_xlfn.CONCAT(#REF!,C4) -> #REF!
A5: Тип активации: ДО МЕРОПРИЯТИЯ (медиа продвижение и PR) | B5: Digital | C5: Баннеры | D5: 120 | E5: 0.3 | F5: 24000 | H5: 7200 | L5: 0 | M5: 1440
A6: Тип активации: ДО МЕРОПРИЯТИЯ (медиа продвижение и PR) | B6: Digital | C6: Промо-пост | D6: 120 | E6: 0.3 | F6: 4000 | H6: 1200 | L6: 0 | M6: 240
A7: Тип активации: ДО МЕРОПРИЯТИЯ (медиа продвижение и PR) | B7: Айдентика Бренда партнера на сайте | C7: Billboard в шапке сайта | D7: 120 | E7: 1 | G7: 1100 | H7: 1100 | M7: 1100
A8: Тип активации: ДО МЕРОПРИЯТИЯ (медиа продвижение и PR) | B8: PR | C8: Статьи о событии | D8: 120 | E8: 0.5 | F8: 10000 | H8: 5000 | J8: 300 тыс | K8: 1 | M8: 3333.3333
A9: Тип активации: ПРОДВИЖЕНИЕ НА МЕРОПРИЯТИИ | B9: Видео | C9: Экраны на сцене | D9: 28 | E9: 1 | F9: 90 | H9: 90 | K9: 0 | M9: 30
A10: Тип активации: ПРОДВИЖЕНИЕ НА МЕРОПРИЯТИИ | B10: Брендирование | C10: брендинг вип-зоны | D10: 28 | E10: 1 | F10: 90 | H10: 90 | M10: 30
A11: Тип активации: ПРОДВИЖЕНИЕ НА МЕРОПРИЯТИИ | B11: Брендирование | C11: размещение арт-объекта | D11: 28 | E11: 1 | F11: 90 | H11: 90 | M11: 90
A12: Тип активации: ПРОДВИЖЕНИЕ НА МЕРОПРИЯТИИ | B12: Брендирование | C12: бренд-зона/лаундж-зона | D12: 28 | E12: 1 | F12: 90 | H12: 90 | M12: 60
A13: Тип активации: ПРОДВИЖЕНИЕ НА МЕРОПРИЯТИИ | B13: Брендирование | C13: брендинг браслетов | D13: 28 | E13: 1 | F13: 90 | H13: 90 | M13: 15
A14: Тип активации: ПРОДВИЖЕНИЕ НА МЕРОПРИЯТИИ | B14: Брендирование | C14: брендинг одежды персонала (бармены, гардеробщики) | D14: 28 | E14: 1 | F14: 90 | H14: 90 | M14: 45
A15: Тип активации: ПРОДВИЖЕНИЕ НА МЕРОПРИЯТИИ | B15: Брендирование | C15: брендированная раздатка (например, флешмоб с брендированными масками с лицом артиста) | D15: 28 | E15: 1 | F15: 90 | H15: 90 | M15: 30
A16: Тип активации: ПРОДВИЖЕНИЕ НА МЕРОПРИЯТИИ | B16: Брендирование | C16: брендированная зона раздачи мерча | D16: 28 | E16: 1 | F16: 90 | H16: 90 | M16: 90
A17: Тип активации: ПРОДВИЖЕНИЕ НА МЕРОПРИЯТИИ | B17: Брендирование | C17: AR-фотозона (с интерактивом) | D17: 28 | E17: 1 | F17: 90 | H17: 90 | M17: 45
A18: Тип активации: ПРОДВИЖЕНИЕ НА МЕРОПРИЯТИИ | B18: Брендирование | C18: флаги/штендеры/лайтбоксы/расклеенные печатные лого/тейбл-тенты на локации мероприятия | D18: 28 | E18: 1 | F18: 90 | H18: 90 | M18: 60
A19: Тип активации: ПРОДВИЖЕНИЕ НА МЕРОПРИЯТИИ | B19: Брендирование | C19: раздача/продажа брендированного мерча на площадке | D19: 28 | E19: 1 | F19: 90 | H19: 90 | M19: 90
A20: Тип активации: ПРОДВИЖЕНИЕ НА МЕРОПРИЯТИИ | B20: Промо-акции | C20: Различные акции с участием промо-персонала | D20: 28 | E20: 1 | F20: 90 | H20: 90 | M20: 60
A21: Тип активации: ДОПОЛНИТЕЛЬНЫЕ АКТИВАЦИИ ПОСЛЕ МЕРОПРИЯТИЯ | B21: Лого партнера | C21: Интеграция в фото и видео отчеты | H21: - | I21: 6 | K21: 1 | M21: 0
A22: Тип активации: ДОПОЛНИТЕЛЬНЫЕ АКТИВАЦИИ ПОСЛЕ МЕРОПРИЯТИЯ | B22: Лого партнера | C22: PR публикации | H22: - | I22: 8 | K22: 1 | M22: 0
A23: Тип активации: ДОПОЛНИТЕЛЬНЫЕ АКТИВАЦИИ ПОСЛЕ МЕРОПРИЯТИЯ | B23: Лого партнера | C23: Интеграция в посты у артиста | H23: - | I23: 7 | K23: 1 | M23: 0

Sheet Фильтры
A1: Блок | B1: Название | C1: Данные
A2: ПЛАНОВЫЙ РЕЗУЛЬТАТ МЕРОПРИЯТИЯ | B2: Кол-во посетителей всего, тыс. | C2: 90
A3: ПЛАНОВЫЙ РЕЗУЛЬТАТ МЕРОПРИЯТИЯ | B3: Средняя цена билета
A4: ПЛАНОВЫЙ РЕЗУЛЬТАТ МЕРОПРИЯТИЯ | B4: GMV
A5: ПЛАНОВЫЙ РЕЗУЛЬТАТ МЕРОПРИЯТИЯ | B5: Агентская комиссия
A6: ПЛАНОВЫЙ РЕЗУЛЬТАТ МЕРОПРИЯТИЯ | B6: Количество проданных билетов через виджит/витрину
A7: БЮДЖЕТ | B7: Интеграционный платеж (организатору) | C7: 5000000
A8: БЮДЖЕТ | B8: Продакшен фото-зоны и лайтбокса, букингсекретных артистов | C8: 19763161
A9: БЮДЖЕТ | B9: Общий бюджет | C9: =SUM(C7:C8) -> 24763161
A10: ЭФФЕКТИВНОСТЬ | B10: Стоимость привлеченного клиента
A11: ЭФФЕКТИВНОСТЬ | B11: Стоимость за контакт | C11: 0.1082551
A12: ЭФФЕКТИВНОСТЬ | B12: Стоимость за охваченного пользователя | C12: 3.9999062
A13: ЭФФЕКТИВНОСТЬ | B13: Стоимость за посетителя мероприятия | C13: 275.14623
A14: ПАРАМЕТРЫ | B14: ЦА (унифицированная аудитория для всех медиа, тыс. 16+) | C14: 11062.57
A15: ПАРАМЕТРЫ | B15: количество дней на фестивале/площадке | C15: 28
A16: ПАРАМЕТРЫ | B16: Общий период размещения | C16: 120
A17: ПАРАМЕТРЫ | B17: План посетителей (в тыс. человек) | C17: 90

Sheet Total_Москва
A1: Медиа факторы | B1: Описание | C1: OTS 16+ ('000) (с учетом доли брендирования) | D1: Охват 16+ ('000) (с учетом доли брендирования)
A2: Тип активации: ДО МЕРОПРИЯТИЯ (медиа продвижение и PR) | B2: ООН | C2: 15000 | D2: 1000
A3: Тип активации: ДО МЕРОПРИЯТИЯ (медиа продвижение и PR) | B3: Indoor | C3: 1500 | D3: 300
A4: Тип активации: ДО МЕРОПРИЯТИЯ (медиа продвижение и PR) | B4: Радио | C4: 196668.21 | D4: 8303.7687
A5: Тип активации: ДО МЕРОПРИЯТИЯ (медиа продвижение и PR) | B5: Digital | C5: 8400 | D5: 1440
A6: Тип активации: ДО МЕРОПРИЯТИЯ (медиа продвижение и PR) | B6: Айдентика Бренда партнера на сайте | C6: 1100 | D6: 1100
A7: Тип активации: ДО МЕРОПРИЯТИЯ (медиа продвижение и PR) | B7: PR | C7: 5000 | D7: 3333.3333
A8: Тип активации: ПРОДВИЖЕНИЕ НА МЕРОПРИЯТИИ | B8: Видео | C8: 90 | D8: 30
A9: Тип активации: ПРОДВИЖЕНИЕ НА МЕРОПРИЯТИИ | B9: Брендирование | C9: 900 | D9: 90
A10: Тип активации: ПРОДВИЖЕНИЕ НА МЕРОПРИЯТИИ | B10: Промо-акции | C10: 90 | D10: 60
A11: Тип активации: ПРОДВИЖЕНИЕ НА МЕРОПРИЯТИИ | B11: Взаимодействие с артистом во время мероприятия
A12: Тип активации: ПРОДВИЖЕНИЕ НА МЕРОПРИЯТИИ | B12: UGC
A13: Тип активации: ДОПОЛНИТЕЛЬНЫЕ АКТИВАЦИИ ПОСЛЕ МЕРОПРИЯТИЯ | B13: Лого партнера
A14: Итог | C14: 228748.21 | D14: 6190.9354

Sheet Москва
C2: Параметры | D2: Описание
C3: ЦА | D3: Унифицированная аудитория для всех медиа, тыс. 16+ | E3: 11062.57
B4: 1 | C4: Гео | D4: 15 городов | E4: Москва
C5: Тип площадки | D5: концерт/фестиваль/площадка | E5: Площадка
D6: количество дней на фестивале/площадке | E6: 28
B7: 2 | C7: Общий период размещения | D7: в днях | E7: 120
B8: 3 | C8: План посетителей | D8: в тысячах человек | E8: 90
B9: # | C9: Медиа факторы | D9: Описание | E9: Форматы | F9: Период размещения, дни | G9: Доля брендирования | H9: OTS 16+ ('000) | I9: Охват 16+* ('000) | J9: OTS 16+ ('000) (с учетом доли брендирования) | K9: Как оцениваем OTS медиа, в случае отсутствия данных по OTS и Охватам у поставщика | M9: Индекс качества (для медиа) | O9: Охват 16+ ('000) (с учетом доли брендирования)
B10: 4 | C10: Тип активации: ДО МЕРОПРИЯТИЯ (медиа продвижение и PR) | D10: ТВ | J10: =SUM(J11:J12) -> 0 | K10: Количество минут в день | L10: Каналы | M10: Хронометраж | N10: Время взаимодействия с креативом | O10: =IFERROR(IF(J10>0,J10/VLOOKUP(D10,'[2]Коэфы качество контакта'!$A$2:$G$22,7,FALSE),(1-(1-(O11/$E$3*0.5))*(1-(O12/$E$3*0.5)))*$E$3),0) -> 0
D11: ТВ | E11: Спонсорство | J11: {=IFERROR(IF(H11>0,H11*G11,IF(K11>0,SUM(OTSТВМосква)*G11*F11*(K11/200),IF(I11>0,G11*I11*SUMPRODUCT(('[2]Коэфы качество контакта'!$A$2:$A$50=D11)*'[2]Коэфы качество контакта'!$G$2:$G$50),""))),"")} | K11: =IFERROR(SUM(МинутыТВМосква),0) -> 0 | L11: Каналы из списка | N11: =M11*VLOOKUP(D11,'[2]Коэфы качество контакта'!$A$2:$E$22,3,FALSE)*VLOOKUP(D11,'[2]Коэфы качество контакта'!$A$2:$E$22,5,FALSE) -> 0 | O11: =IFERROR(IF(I11>0,I11*G11,J11/VLOOKUP(D11,'[2]Коэфы качество контакта'!$A$2:$G$22,7,FALSE)),"") | P11: =_xlfn.CONCAT($E$4,E11) -> МоскваСпонсорство
D12: ТВ | E12: Прямая Реклама | J12: {=IFERROR(IF(H12>0,H12*G12,IF(K12>0,SUM(OTSТВМосква)*G12*F12*(K12/200),IF(I12>0,G12*I12*SUMPRODUCT(('[2]Коэфы качество контакта'!$A$2:$A$50=D12)*'[2]Коэфы качество контакта'!$G$2:$G$50),""))),"")} | K12: =IFERROR(SUM(МинутыТВМосква),0) -> 0 | L12: Каналы из списка | N12: =M12*VLOOKUP(D12,'[2]Коэфы качество контакта'!$A$2:$E$22,3,FALSE)*VLOOKUP(D12,'[2]Коэфы качество контакта'!$A$2:$E$22,5,FALSE) -> 0 | O12: =IFERROR(IF(I12>0,I12*G12,J12/VLOOKUP(D12,'[2]Коэфы качество контакта'!$A$2:$G$22,7,FALSE)),"") | P12: =_xlfn.CONCAT($E$4,E12) -> МоскваПрямая Реклама
D13: ООН | J13: =SUM(J14:J21) -> 15000 | K13: Количество сторон | M13: Хронометраж | N13: Время взаимодействия с креативом | O13: =IFERROR(IF(J13>0,J13/VLOOKUP(D13,'[2]Коэфы качество контакта'!$A$2:$G$22,7,FALSE),(1-(1-(O14/$E$3*0.5))*(1-(O15/$E$3*0.5))*(1-(O16/$E$3*0.5))*(1-(O17/$E$3*0.5))*(1-(O18/$E$3*0.5))*(1-(O19/$E$3*0.5))*(1-(O20/$E$3*0.5))*(1-(O21/$E$3*0.5)))*$E$3),) -> 1000
D14: ООН | E14: BB | F14: 120 | G14: 0.3 | H14: 50000 | J14: {=IF(H14>0,H14*G14,IF(K14>0,SUMPRODUCT(([2]OOH!$A$2:$A$1000=Москва!$E$4)*([2]OOH!$B$2:$B$1000=Москва!$E14)*[2]OOH!$C$2:$C$1000)*F14*K14*G14,IF(I14>0,G14*I14*SUMPRODUCT(('[2]Коэфы качество контакта'!$A$2:$A$50=D14)*'[2]Коэфы качество контакта'!$G$2:$G$50),"")))} -> 15000 | N14: =M14*VLOOKUP(D14,'[2]Коэфы качество контакта'!$A$2:$E$22,3,FALSE)*VLOOKUP(D14,'[2]Коэфы качество контакта'!$A$2:$E$22,5,FALSE) -> 0 | O14: =IFERROR(IF(I14>0,I14*G14,J14/VLOOKUP(D14,'[2]Коэфы качество контакта'!$A$2:$G$22,7,FALSE)),"") -> 1000
D15: ООН | E15: DBB | J15: {=IF(H15>0,H15*G15,IF(K15>0,SUMPRODUCT(([2]OOH!$A$2:$A$1000=Москва!$E$4)*([2]OOH!$B$2:$B$1000=Москва!$E15)*[2]OOH!$C$2:$C$1000)*F15*K15*G15,IF(I15>0,G15*I15*SUMPRODUCT(('[2]Коэфы качество контакта'!$A$2:$A$50=D15)*'[2]Коэфы качество контакта'!$G$2:$G$50),"")))} | N15: =M15*VLOOKUP(D15,'[2]Коэфы качество контакта'!$A$2:$E$22,3,FALSE)*VLOOKUP(D15,'[2]Коэфы качество контакта'!$A$2:$E$22,5,FALSE) -> 0 | O15: =IFERROR(IF(I15>0,I15*G15,J15/VLOOKUP(D15,'[2]Коэфы качество контакта'!$A$2:$G$22,7,FALSE)),"")
D16: ООН | E16: PL | J16: {=IF(H16>0,H16*G16,IF(K16>0,SUMPRODUCT(([2]OOH!$A$2:$A$1000=Москва!$E$4)*([2]OOH!$B$2:$B$1000=Москва!$E16)*[2]OOH!$C$2:$C$1000)*F16*K16*G16,IF(I16>0,G16*I16*SUMPRODUCT(('[2]Коэфы качество контакта'!$A$2:$A$50=D16)*'[2]Коэфы качество контакта'!$G$2:$G$50),"")))} | N16: =M16*VLOOKUP(D16,'[2]Коэфы качество контакта'!$A$2:$E$22,3,FALSE)*VLOOKUP(D16,'[2]Коэфы качество контакта'!$A$2:$E$22,5,FALSE) -> 0 | O16: =IFERROR(IF(I16>0,I16*G16,J16/VLOOKUP(D16,'[2]Коэфы качество контакта'!$A$2:$G$22,7,FALSE)),"")
D17: ООН | E17: SS | J17: {=IF(H17>0,H17*G17,IF(K17>0,SUMPRODUCT(([2]OOH!$A$2:$A$1000=Москва!$E$4)*([2]OOH!$B$2:$B$1000=Москва!$E17)*[2]OOH!$C$2:$C$1000)*F17*K17*G17,IF(I17>0,G17*I17*SUMPRODUCT(('[2]Коэфы качество контакта'!$A$2:$A$50=D17)*'[2]Коэфы качество контакта'!$G$2:$G$50),"")))} | N17: =M17*VLOOKUP(D17,'[2]Коэфы качество контакта'!$A$2:$E$22,3,FALSE)*VLOOKUP(D17,'[2]Коэфы качество контакта'!$A$2:$E$22,5,FALSE) -> 0 | O17: =IFERROR(IF(I17>0,I17*G17,J17/VLOOKUP(D17,'[2]Коэфы качество контакта'!$A$2:$G$22,7,FALSE)),"")
D18: ООН | E18: CF | J18: {=IF(H18>0,H18*G18,IF(K18>0,SUMPRODUCT(([2]OOH!$A$2:$A$1000=Москва!$E$4)*([2]OOH!$B$2:$B$1000=Москва!$E18)*[2]OOH!$C$2:$C$1000)*F18*K18*G18,IF(I18>0,G18*I18*SUMPRODUCT(('[2]Коэфы качество контакта'!$A$2:$A$50=D18)*'[2]Коэфы качество контакта'!$G$2:$G$50),"")))} | N18: =M18*VLOOKUP(D18,'[2]Коэфы качество контакта'!$A$2:$E$22,3,FALSE)*VLOOKUP(D18,'[2]Коэфы качество контакта'!$A$2:$E$22,5,FALSE) -> 0 | O18: =IFERROR(IF(I18>0,I18*G18,J18/VLOOKUP(D18,'[2]Коэфы качество контакта'!$A$2:$G$22,7,FALSE)),"")
D19: ООН | J19: {=IF(H19>0,H19*G19,IF(K19>0,SUMPRODUCT(([2]OOH!$A$2:$A$1000=Москва!$E$4)*([2]OOH!$B$2:$B$1000=Москва!$E19)*[2]OOH!$C$2:$C$1000)*F19*K19*G19,IF(I19>0,G19*I19*SUMPRODUCT(('[2]Коэфы качество контакта'!$A$2:$A$50=D19)*'[2]Коэфы качество контакта'!$G$2:$G$50),"")))} | N19: =M19*VLOOKUP(D19,'[2]Коэфы качество контакта'!$A$2:$E$22,3,FALSE)*VLOOKUP(D19,'[2]Коэфы качество контакта'!$A$2:$E$22,5,FALSE) -> 0 | O19: =IFERROR(IF(I19>0,I19*G19,J19/VLOOKUP(D19,'[2]Коэфы качество контакта'!$A$2:$G$22,7,FALSE)),"")
D20: ООН | J20: {=IF(H20>0,H20*G20,IF(K20>0,SUMPRODUCT(([2]OOH!$A$2:$A$1000=Москва!$E$4)*([2]OOH!$B$2:$B$1000=Москва!$E20)*[2]OOH!$C$2:$C$1000)*F20*K20*G20,IF(I20>0,G20*I20*SUMPRODUCT(('[2]Коэфы качество контакта'!$A$2:$A$50=D20)*'[2]Коэфы качество контакта'!$G$2:$G$50),"")))} | N20: =M20*VLOOKUP(D20,'[2]Коэфы качество контакта'!$A$2:$E$22,3,FALSE)*VLOOKUP(D20,'[2]Коэфы качество контакта'!$A$2:$E$22,5,FALSE) -> 0 | O20: =IFERROR(IF(I20>0,I20*G20,J20/VLOOKUP(D20,'[2]Коэфы качество контакта'!$A$2:$G$22,7,FALSE)),"")
D21: ООН | J21: {=IF(H21>0,H21*G21,IF(K21>0,SUMPRODUCT(([2]OOH!$A$2:$A$1000=Москва!$E$4)*([2]OOH!$B$2:$B$1000=Москва!$E21)*[2]OOH!$C$2:$C$1000)*F21*K21*G21,IF(I21>0,G21*I21*SUMPRODUCT(('[2]Коэфы качество контакта'!$A$2:$A$50=D21)*'[2]Коэфы качество контакта'!$G$2:$G$50),"")))} | L21: - | N21: =M21*VLOOKUP(D21,'[2]Коэфы качество контакта'!$A$2:$E$22,3,FALSE)*VLOOKUP(D21,'[2]Коэфы качество контакта'!$A$2:$E$22,5,FALSE) -> 0 | O21: =IFERROR(IF(I21>0,I21*G21,J21/VLOOKUP(D21,'[2]Коэфы качество контакта'!$A$2:$G$22,7,FALSE)),"")
D22: Indoor | J22: =SUM(J23:J42) -> 1500 | M22: Хронометраж | N22: Время взаимодействия с креативом | O22: =IF(J22>0,J22/VLOOKUP(D22,'[2]Коэфы качество контакта'!$A$2:$G$22,7,FALSE),(1-(1-(O23/$E$3*0.5))*(1-(O24/$E$3*0.5))*(1-(O25/$E$3*0.5))*(1-(O26/$E$3*0.5))*(1-(O27/$E$3*0.5))*(1-(O28/$E$3*0.5))*(1-(O29/$E$3*0.5))*(1-(O30/$E$3*0.5))*(1-(O31/$E$3*0.5))*(1-(O32/$E$3*0.5))*(1-(O33/$E$3*0.5))*(1-(O34/$E$3*0.5))*(1-(O35/$E$3*0.5))*(1-(O36/$E$3*0.5))*(1-(O37/$E$3*0.5))*(1-(O38/$E$3*0.5))*(1-(O39/$E$3*0.5))*(1-(O40/$E$3*0.5))*(1-(O41/$E$3*0.5))*(1-(O42/$E$3*0.5)))*$E$3) -> 300
D23: Indoor | E23: Авиапарк | F23: 120 | G23: 0.3 | H23: 5000 | J23: {=IF(H23>0,H23*G23,IF(I23>0,G23*I23*SUMPRODUCT(('[2]Коэфы качество контакта'!$A$2:$A$50=D23)*'[2]Коэфы качество контакта'!$G$2:$G$50),SUMPRODUCT(([2]Indoor!$A$2:$A$996=Москва!$E$4)*([2]Indoor!$B$2:$B$996=Москва!$E23)*[2]Indoor!$F$2:$F$996)*F23*G23))} -> 1500 | N23: =M23*VLOOKUP(D23,'[2]Коэфы качество контакта'!$A$2:$E$22,3,FALSE)*VLOOKUP(D23,'[2]Коэфы качество контакта'!$A$2:$E$22,5,FALSE) -> 0 | O23: {=IFERROR(IF(I23>0,I23*G23,J23/SUMPRODUCT(([2]Indoor!$A$2:$A$996=Москва!$E$4)*([2]Indoor!$B$2:$B$996=Москва!$E23)*[2]Indoor!$G$2:$G$996)),0)} -> 300
D24: Indoor | E24: ТЦ Атриум | J24: {=IF(H24>0,H24*G24,IF(I24>0,G24*I24*SUMPRODUCT(('[2]Коэфы качество контакта'!$A$2:$A$50=D24)*'[2]Коэфы качество контакта'!$G$2:$G$50),SUMPRODUCT(([2]Indoor!$A$2:$A$996=Москва!$E$4)*([2]Indoor!$B$2:$B$996=Москва!$E24)*[2]Indoor!$F$2:$F$996)*F24*G24))} -> 0 | N24: =M24*VLOOKUP(D24,'[2]Коэфы качество контакта'!$A$2:$E$22,3,FALSE)*VLOOKUP(D24,'[2]Коэфы качество контакта'!$A$2:$E$22,5,FALSE) -> 0 | O24: {=IFERROR(IF(I24>0,I24*G24,J24/SUMPRODUCT(([2]Indoor!$A$2:$A$996=Москва!$E$4)*([2]Indoor!$B$2:$B$996=Москва!$E24)*[2]Indoor!$G$2:$G$996)),0)} -> 0
D25: Indoor | E25: ПВЗ | J25: {=IF(H25>0,H25*G25,IF(I25>0,G25*I25*SUMPRODUCT(('[2]Коэфы качество контакта'!$A$2:$A$50=D25)*'[2]Коэфы качество контакта'!$G$2:$G$50),SUMPRODUCT(([2]Indoor!$A$2:$A$996=Москва!$E$4)*([2]Indoor!$B$2:$B$996=Москва!$E25)*[2]Indoor!$F$2:$F$996)*F25*G25))} -> 0 | N25: =M25*VLOOKUP(D25,'[2]Коэфы качество контакта'!$A$2:$E$22,3,FALSE)*VLOOKUP(D25,'[2]Коэфы качество контакта'!$A$2:$E$22,5,FALSE) -> 0 | O25: {=IFERROR(IF(I25>0,I25*G25,J25/SUMPRODUCT(([2]Indoor!$A$2:$A$996=Москва!$E$4)*([2]Indoor!$B$2:$B$996=Москва!$E25)*[2]Indoor!$G$2:$G$996)),0)} -> 0
D26: Indoor | E26: ТЦ Коламбус | J26: {=IF(H26>0,H26*G26,IF(I26>0,G26*I26*SUMPRODUCT(('[2]Коэфы качество контакта'!$A$2:$A$50=D26)*'[2]Коэфы качество контакта'!$G$2:$G$50),SUMPRODUCT(([2]Indoor!$A$2:$A$996=Москва!$E$4)*([2]Indoor!$B$2:$B$996=Москва!$E26)*[2]Indoor!$F$2:$F$996)*F26*G26))} -> 0 | N26: =M26*VLOOKUP(D26,'[2]Коэфы качество контакта'!$A$2:$E$22,3,FALSE)*VLOOKUP(D26,'[2]Коэфы качество контакта'!$A$2:$E$22,5,FALSE) -> 0 | O26: {=IFERROR(IF(I26>0,I26*G26,J26/SUMPRODUCT(([2]Indoor!$A$2:$A$996=Москва!$E$4)*([2]Indoor!$B$2:$B$996=Москва!$E26)*[2]Indoor!$G$2:$G$996)),0)} -> 0
D27: Indoor | J27: {=IF(H27>0,H27*G27,IF(I27>0,G27*I27*SUMPRODUCT(('[2]Коэфы качество контакта'!$A$2:$A$50=D27)*'[2]Коэфы качество контакта'!$G$2:$G$50),SUMPRODUCT(([2]Indoor!$A$2:$A$996=Москва!$E$4)*([2]Indoor!$B$2:$B$996=Москва!$E27)*[2]Indoor!$F$2:$F$996)*F27*G27))} -> 0 | N27: =M27*VLOOKUP(D27,'[2]Коэфы качество контакта'!$A$2:$E$22,3,FALSE)*VLOOKUP(D27,'[2]Коэфы качество контакта'!$A$2:$E$22,5,FALSE) -> 0 | O27: {=IFERROR(IF(I27>0,I27*G27,J27/SUMPRODUCT(([2]Indoor!$A$2:$A$996=Москва!$E$4)*([2]Indoor!$B$2:$B$996=Москва!$E27)*[2]Indoor!$G$2:$G$996)),0)} -> 0
D28: Indoor | J28: {=IF(H28>0,H28*G28,IF(I28>0,G28*I28*SUMPRODUCT(('[2]Коэфы качество контакта'!$A$2:$A$50=D28)*'[2]Коэфы качество контакта'!$G$2:$G$50),SUMPRODUCT(([2]Indoor!$A$2:$A$996=Москва!$E$4)*([2]Indoor!$B$2:$B$996=Москва!$E28)*[2]Indoor!$F$2:$F$996)*F28*G28))} -> 0 | N28: =M28*VLOOKUP(D28,'[2]Коэфы качество контакта'!$A$2:$E$22,3,FALSE)*VLOOKUP(D28,'[2]Коэфы качество контакта'!$A$2:$E$22,5,FALSE) -> 0 | O28: {=IFERROR(IF(I28>0,I28*G28,J28/SUMPRODUCT(([2]Indoor!$A$2:$A$996=Москва!$E$4)*([2]Indoor!$B$2:$B$996=Москва!$E28)*[2]Indoor!$G$2:$G$996)),0)} -> 0
D29: Indoor | J29: {=IF(H29>0,H29*G29,IF(I29>0,G29*I29*SUMPRODUCT(('[2]Коэфы качество контакта'!$A$2:$A$50=D29)*'[2]Коэфы качество контакта'!$G$2:$G$50),SUMPRODUCT(([2]Indoor!$A$2:$A$996=Москва!$E$4)*([2]Indoor!$B$2:$B$996=Москва!$E29)*[2]Indoor!$F$2:$F$996)*F29*G29))} -> 0 | N29: =M29*VLOOKUP(D29,'[2]Коэфы качество контакта'!$A$2:$E$22,3,FALSE)*VLOOKUP(D29,'[2]Коэфы качество контакта'!$A$2:$E$22,5,FALSE) -> 0 | O29: {=IFERROR(IF(I29>0,I29*G29,J29/SUMPRODUCT(([2]Indoor!$A$2:$A$996=Москва!$E$4)*([2]Indoor!$B$2:$B$996=Москва!$E29)*[2]Indoor!$G$2:$G$996)),0)} -> 0
D30: Indoor | J30: {=IF(H30>0,H30*G30,IF(I30>0,G30*I30*SUMPRODUCT(('[2]Коэфы качество контакта'!$A$2:$A$50=D30)*'[2]Коэфы качество контакта'!$G$2:$G$50),SUMPRODUCT(([2]Indoor!$A$2:$A$996=Москва!$E$4)*([2]Indoor!$B$2:$B$996=Москва!$E30)*[2]Indoor!$F$2:$F$996)*F30*G30))} -> 0 | N30: =M30*VLOOKUP(D30,'[2]Коэфы качество контакта'!$A$2:$E$22,3,FALSE)*VLOOKUP(D30,'[2]Коэфы качество контакта'!$A$2:$E$22,5,FALSE) -> 0 | O30: {=IFERROR(IF(I30>0,I30*G30,J30/SUMPRODUCT(([2]Indoor!$A$2:$A$996=Москва!$E$4)*([2]Indoor!$B$2:$B$996=Москва!$E30)*[2]Indoor!$G$2:$G$996)),0)} -> 0
D31: Indoor | J31: {=IF(H31>0,H31*G31,IF(I31>0,G31*I31*SUMPRODUCT(('[2]Коэфы качество контакта'!$A$2:$A$50=D31)*'[2]Коэфы качество контакта'!$G$2:$G$50),SUMPRODUCT(([2]Indoor!$A$2:$A$996=Москва!$E$4)*([2]Indoor!$B$2:$B$996=Москва!$E31)*[2]Indoor!$F$2:$F$996)*F31*G31))} -> 0 | N31: =M31*VLOOKUP(D31,'[2]Коэфы качество контакта'!$A$2:$E$22,3,FALSE)*VLOOKUP(D31,'[2]Коэфы качество контакта'!$A$2:$E$22,5,FALSE) -> 0 | O31: {=IFERROR(IF(I31>0,I31*G31,J31/SUMPRODUCT(([2]Indoor!$A$2:$A$996=Москва!$E$4)*([2]Indoor!$B$2:$B$996=Москва!$E31)*[2]Indoor!$G$2:$G$996)),0)} -> 0
D32: Indoor | J32: {=IF(H32>0,H32*G32,IF(I32>0,G32*I32*SUMPRODUCT(('[2]Коэфы качество контакта'!$A$2:$A$50=D32)*'[2]Коэфы качество контакта'!$G$2:$G$50),SUMPRODUCT(([2]Indoor!$A$2:$A$996=Москва!$E$4)*([2]Indoor!$B$2:$B$996=Москва!$E32)*[2]Indoor!$F$2:$F$996)*F32*G32))} -> 0 | N32: =M32*VLOOKUP(D32,'[2]Коэфы качество контакта'!$A$2:$E$22,3,FALSE)*VLOOKUP(D32,'[2]Коэфы качество контакта'!$A$2:$E$22,5,FALSE) -> 0 | O32: {=IFERROR(IF(I32>0,I32*G32,J32/SUMPRODUCT(([2]Indoor!$A$2:$A$996=Москва!$E$4)*([2]Indoor!$B$2:$B$996=Москва!$E32)*[2]Indoor!$G$2:$G$996)),0)} -> 0
D33: Indoor | J33: {=IF(H33>0,H33*G33,IF(I33>0,G33*I33*SUMPRODUCT(('[2]Коэфы качество контакта'!$A$2:$A$50=D33)*'[2]Коэфы качество контакта'!$G$2:$G$50),SUMPRODUCT(([2]Indoor!$A$2:$A$996=Москва!$E$4)*([2]Indoor!$B$2:$B$996=Москва!$E33)*[2]Indoor!$F$2:$F$996)*F33*G33))} -> 0 | N33: =M33*VLOOKUP(D33,'[2]Коэфы качество контакта'!$A$2:$E$22,3,FALSE)*VLOOKUP(D33,'[2]Коэфы качество контакта'!$A$2:$E$22,5,FALSE) -> 0 | O33: {=IFERROR(IF(I33>0,I33*G33,J33/SUMPRODUCT(([2]Indoor!$A$2:$A$996=Москва!$E$4)*([2]Indoor!$B$2:$B$996=Москва!$E33)*[2]Indoor!$G$2:$G$996)),0)} -> 0
D34: Indoor | J34: {=IF(H34>0,H34*G34,IF(I34>0,G34*I34*SUMPRODUCT(('[2]Коэфы качество контакта'!$A$2:$A$50=D34)*'[2]Коэфы качество контакта'!$G$2:$G$50),SUMPRODUCT(([2]Indoor!$A$2:$A$996=Москва!$E$4)*([2]Indoor!$B$2:$B$996=Москва!$E34)*[2]Indoor!$F$2:$F$996)*F34*G34))} -> 0 | N34: =M34*VLOOKUP(D34,'[2]Коэфы качество контакта'!$A$2:$E$22,3,FALSE)*VLOOKUP(D34,'[2]Коэфы качество контакта'!$A$2:$E$22,5,FALSE) -> 0 | O34: {=IFERROR(IF(I34>0,I34*G34,J34/SUMPRODUCT(([2]Indoor!$A$2:$A$996=Москва!$E$4)*([2]Indoor!$B$2:$B$996=Москва!$E34)*[2]Indoor!$G$2:$G$996)),0)} -> 0
D35: Indoor | J35: {=IF(H35>0,H35*G35,IF(I35>0,G35*I35*SUMPRODUCT(('[2]Коэфы качество контакта'!$A$2:$A$50=D35)*'[2]Коэфы качество контакта'!$G$2:$G$50),SUMPRODUCT(([2]Indoor!$A$2:$A$996=Москва!$E$4)*([2]Indoor!$B$2:$B$996=Москва!$E35)*[2]Indoor!$F$2:$F$996)*F35*G35))} -> 0 | N35: =M35*VLOOKUP(D35,'[2]Коэфы качество контакта'!$A$2:$E$22,3,FALSE)*VLOOKUP(D35,'[2]Коэфы качество контакта'!$A$2:$E$22,5,FALSE) -> 0 | O35: {=IFERROR(IF(I35>0,I35*G35,J35/SUMPRODUCT(([2]Indoor!$A$2:$A$996=Москва!$E$4)*([2]Indoor!$B$2:$B$996=Москва!$E35)*[2]Indoor!$G$2:$G$996)),0)} -> 0
D36: Indoor | J36: {=IF(H36>0,H36*G36,IF(I36>0,G36*I36*SUMPRODUCT(('[2]Коэфы качество контакта'!$A$2:$A$50=D36)*'[2]Коэфы качество контакта'!$G$2:$G$50),SUMPRODUCT(([2]Indoor!$A$2:$A$996=Москва!$E$4)*([2]Indoor!$B$2:$B$996=Москва!$E36)*[2]Indoor!$F$2:$F$996)*F36*G36))} -> 0 | N36: =M36*VLOOKUP(D36,'[2]Коэфы качество контакта'!$A$2:$E$22,3,FALSE)*VLOOKUP(D36,'[2]Коэфы качество контакта'!$A$2:$E$22,5,FALSE) -> 0 | O36: {=IFERROR(IF(I36>0,I36*G36,J36/SUMPRODUCT(([2]Indoor!$A$2:$A$996=Москва!$E$4)*([2]Indoor!$B$2:$B$996=Москва!$E36)*[2]Indoor!$G$2:$G$996)),0)} -> 0
D37: Indoor | J37: {=IF(H37>0,H37*G37,IF(I37>0,G37*I37*SUMPRODUCT(('[2]Коэфы качество контакта'!$A$2:$A$50=D37)*'[2]Коэфы качество контакта'!$G$2:$G$50),SUMPRODUCT(([2]Indoor!$A$2:$A$996=Москва!$E$4)*([2]Indoor!$B$2:$B$996=Москва!$E37)*[2]Indoor!$F$2:$F$996)*F37*G37))} -> 0 | N37: =M37*VLOOKUP(D37,'[2]Коэфы качество контакта'!$A$2:$E$22,3,FALSE)*VLOOKUP(D37,'[2]Коэфы качество контакта'!$A$2:$E$22,5,FALSE) -> 0 | O37: {=IFERROR(IF(I37>0,I37*G37,J37/SUMPRODUCT(([2]Indoor!$A$2:$A$996=Москва!$E$4)*([2]Indoor!$B$2:$B$996=Москва!$E37)*[2]Indoor!$G$2:$G$996)),0)} -> 0
D38: Indoor | J38: {=IF(H38>0,H38*G38,IF(I38>0,G38*I38*SUMPRODUCT(('[2]Коэфы качество контакта'!$A$2:$A$50=D38)*'[2]Коэфы качество контакта'!$G$2:$G$50),SUMPRODUCT(([2]Indoor!$A$2:$A$996=Москва!$E$4)*([2]Indoor!$B$2:$B$996=Москва!$E38)*[2]Indoor!$F$2:$F$996)*F38*G38))} -> 0 | N38: =M38*VLOOKUP(D38,'[2]Коэфы качество контакта'!$A$2:$E$22,3,FALSE)*VLOOKUP(D38,'[2]Коэфы качество контакта'!$A$2:$E$22,5,FALSE) -> 0 | O38: {=IFERROR(IF(I38>0,I38*G38,J38/SUMPRODUCT(([2]Indoor!$A$2:$A$996=Москва!$E$4)*([2]Indoor!$B$2:$B$996=Москва!$E38)*[2]Indoor!$G$2:$G$996)),0)} -> 0
... D42: Indoor | J42: {=IF(H42>0,H42*G42,IF(I42>0,G42*I42*SUMPRODUCT(('[2]Коэфы качество контакта'!$A$2:$A$50=D42)*'[2]Коэфы качество контакта'!$G$2:$G$50),SUMPRODUCT(([2]Indoor!$A$2:$A$996=Москва!$E$4)*([2]Indoor!$B$2:$B$996=Москва!$E42)*[2]Indoor!$F$2:$F$996)*F42*G42))} -> 0 | N42: =M42*VLOOKUP(D42,'[2]Коэфы качество контакта'!$A$2:$E$22,3,FALSE)*VLOOKUP(D42,'[2]Коэфы качество контакта'!$A$2:$E$22,5,FALSE) -> 0 | O42: {=IFERROR(IF(I42>0,I42*G42,J42/SUMPRODUCT(([2]Indoor!$A$2:$A$996=Москва!$E$4)*([2]Indoor!$B$2:$B$996=Москва!$E42)*[2]Indoor!$G$2:$G$996)),0)} -> 0
D43: Метро | J43: =SUM(J44:J48) -> 0 | K43: Количество выходов в день | L43: Количество веток | M43: Хронометраж | N43: Время взаимодействия с креативом | O43: =IF(J43>0,J43/VLOOKUP(D43,'[2]Коэфы качество контакта'!$A$2:$G$22,7,FALSE),(1-(1-(O44/$E$3*0.5))*(1-(O45/$E$3*0.5))*(1-(O46/$E$3*0.5))*(1-(O47/$E$3*0.5))*(1-(O48/$E$3*0.5)))*$E$3) -> 0
D44: Метро | E44: Digital Screen в вагонах | J44: {=IF(H44>0,H44*G44,IF(K44>0,SUMPRODUCT((([2]Метро!$A$2:$A$1000=Москва!$E$4)*[2]Метро!$E$2:$E$1000)/1000)*L44*F44*G44*SUMPRODUCT(([2]Метро!$F$2:$F$6=Москва!$E44)*[2]Метро!$G$2:$G$6)*K44,IF(I44>0,G44*I44*SUMPRODUCT(('[2]Коэфы качество контакта'!$A$2:$A$50=D44)*'[2]Коэфы качество контакта'!$G$2:$G$50),"")))} | N44: =M44*VLOOKUP(D44,'[2]Коэфы качество контакта'!$A$2:$E$22,3,FALSE)*VLOOKUP(D44,'[2]Коэфы качество контакта'!$A$2:$E$22,5,FALSE) -> 0 | O44: =IFERROR(IF(I44>0,I44*G44,J44/VLOOKUP(D44,'[2]Коэфы качество контакта'!$A$2:$G$22,7,FALSE)),) -> 0
D45: Метро | E45: DCF на ст.метро | J45: {=IF(H45>0,H45*G45,IF(K45>0,SUMPRODUCT((([2]Метро!$A$2:$A$1000=Москва!$E$4)*[2]Метро!$E$2:$E$1000)/1000)*L45*F45*G45*SUMPRODUCT(([2]Метро!$F$2:$F$6=Москва!$E45)*[2]Метро!$G$2:$G$6)*K45,IF(I45>0,G45*I45*SUMPRODUCT(('[2]Коэфы качество контакта'!$A$2:$A$50=D45)*'[2]Коэфы качество контакта'!$G$2:$G$50),"")))} | N45: =M45*VLOOKUP(D45,'[2]Коэфы качество контакта'!$A$2:$E$22,3,FALSE)*VLOOKUP(D45,'[2]Коэфы качество контакта'!$A$2:$E$22,5,FALSE) -> 0 | O45: =IFERROR(IF(I45>0,I45*G45,J45/VLOOKUP(D45,'[2]Коэфы качество контакта'!$A$2:$G$22,7,FALSE)),) -> 0
D46: Метро | E46: Digital Screen на ст.Савеловская | J46: {=IF(H46>0,H46*G46,IF(K46>0,SUMPRODUCT((([2]Метро!$A$2:$A$1000=Москва!$E$4)*[2]Метро!$E$2:$E$1000)/1000)*L46*F46*G46*SUMPRODUCT(([2]Метро!$F$2:$F$6=Москва!$E46)*[2]Метро!$G$2:$G$6)*K46,IF(I46>0,G46*I46*SUMPRODUCT(('[2]Коэфы качество контакта'!$A$2:$A$50=D46)*'[2]Коэфы качество контакта'!$G$2:$G$50),"")))} | N46: =M46*VLOOKUP(D46,'[2]Коэфы качество контакта'!$A$2:$E$22,3,FALSE)*VLOOKUP(D46,'[2]Коэфы качество контакта'!$A$2:$E$22,5,FALSE) -> 0 | O46: =IFERROR(IF(I46>0,I46*G46,J46/VLOOKUP(D46,'[2]Коэфы качество контакта'!$A$2:$G$22,7,FALSE)),) -> 0
D47: Метро | E47: Стикеры в вагонах А2 | J47: {=IF(H47>0,H47*G47,IF(K47>0,SUMPRODUCT((([2]Метро!$A$2:$A$1000=Москва!$E$4)*[2]Метро!$E$2:$E$1000)/1000)*L47*F47*G47*SUMPRODUCT(([2]Метро!$F$2:$F$6=Москва!$E47)*[2]Метро!$G$2:$G$6)*K47,IF(I47>0,G47*I47*SUMPRODUCT(('[2]Коэфы качество контакта'!$A$2:$A$50=D47)*'[2]Коэфы качество контакта'!$G$2:$G$50),"")))} | N47: =M47*VLOOKUP(D47,'[2]Коэфы качество контакта'!$A$2:$E$22,3,FALSE)*VLOOKUP(D47,'[2]Коэфы качество контакта'!$A$2:$E$22,5,FALSE) -> 0 | O47: =IFERROR(IF(I47>0,I47*G47,J47/VLOOKUP(D47,'[2]Коэфы качество контакта'!$A$2:$G$22,7,FALSE)),) -> 0
D48: Метро | E48: Стикеры в вагонах над дверью | J48: {=IF(H48>0,H48*G48,IF(K48>0,SUMPRODUCT((([2]Метро!$A$2:$A$1000=Москва!$E$4)*[2]Метро!$E$2:$E$1000)/1000)*L48*F48*G48*SUMPRODUCT(([2]Метро!$F$2:$F$6=Москва!$E48)*[2]Метро!$G$2:$G$6)*K48,IF(I48>0,G48*I48*SUMPRODUCT(('[2]Коэфы качество контакта'!$A$2:$A$50=D48)*'[2]Коэфы качество контакта'!$G$2:$G$50),"")))} | N48: =M48*VLOOKUP(D48,'[2]Коэфы качество контакта'!$A$2:$E$22,3,FALSE)*VLOOKUP(D48,'[2]Коэфы качество контакта'!$A$2:$E$22,5,FALSE) -> 0 | O48: =IFERROR(IF(I48>0,I48*G48,J48/VLOOKUP(D48,'[2]Коэфы качество контакта'!$A$2:$G$22,7,FALSE)),) -> 0
D49: Радио | J49: =SUM(J50:J51) -> 0 | K49: Количество выходов за весь период | L49: Радиостанции | M49: Хронометраж | N49: Время взаимодействия с креативом | O49: =IFERROR(IF(J49>0,J49/(VLOOKUP(D49,'[2]Коэфы качество контакта'!$A$2:$G$22,7,FALSE)*(MAX(F50:F51)/30.4)),(1-(1-(O50/$E$3*0.5))*(1-(O51/$E$3*0.5)))*$E$3),0) -> 0
D50: Радио | E50: Спонсорство | J50: {=IFERROR(IF(H50>0,H50*G50,IF(K50>0,SUM(OTSРадиоМосква)*G50*K50,IF(I50>0,G50*I50*SUMPRODUCT(('[2]Коэфы качество контакта'!$A$2:$A$50=D50)*'[2]Коэфы качество контакта'!$G$2:$G$50),""))),"")} | K50: =IFERROR(SUM(МинутыРадиоМосква),0) -> 0 | L50: Радиостанции из списка | N50: =M50*VLOOKUP(D50,'[2]Коэфы качество контакта'!$A$2:$E$22,3,FALSE)*VLOOKUP(D50,'[2]Коэфы качество контакта'!$A$2:$E$22,5,FALSE) -> 0 | O50: =IFERROR(IF(I50>0,I50*G50,J50/(VLOOKUP(D50,'[2]Коэфы качество контакта'!$A$2:$G$22,7,FALSE)*F50/30.4)),"") | P50: =_xlfn.CONCAT($E$4,E50) -> МоскваСпонсорство
D51: Радио | E51: Прямая Реклама | F51: 120 | G51: 0.2 | J51: {=IFERROR(IF(H51>0,H51*G51,IF(K51>0,SUM(OTSРадиоМосква)*G51*K51,IF(I51>0,G51*I51*SUMPRODUCT(('[2]Коэфы качество контакта'!$A$2:$A$50=D51)*'[2]Коэфы качество контакта'!$G$2:$G$50),""))),"")} | K51: =IFERROR(SUM(МинутыРадиоМосква),0) -> 0 | L51: Радиостанции из списка | M51: 30 | N51: =M51*VLOOKUP(D51,'[2]Коэфы качество контакта'!$A$2:$E$22,3,FALSE)*VLOOKUP(D51,'[2]Коэфы качество контакта'!$A$2:$E$22,5,FALSE) -> 15.84 | O51: =IFERROR(IF(I51>0,I51*G51,J51/(VLOOKUP(D51,'[2]Коэфы качество контакта'!$A$2:$G$22,7,FALSE)*F51/30.4)),"") | P51: =_xlfn.CONCAT($E$4,E51) -> МоскваПрямая Реклама
D52: Digital | J52: =SUM(J53:J60) -> 8400 | K52: Количество показов за весь период, тыс. | L52: Размер аудитории ресурса в тыс. (без продвижения) | M52: Хронометраж | N52: Время взаимодействия с креативом | O52: =IF((SUM(O53:O60)*0.6)<MAX(O53:O60),MAX(O53:O60),(SUM(O53:O60)*0.6)) -> 1440
D53: Digital | E53: Баннеры | F53: 120 | G53: 0.3 | H53: 24000 | J53: {=IFERROR(IF(H53>0,H53*G53,IF(K53>0,G53*K53,IF(L53>0,L53*G53*(1-SUMPRODUCT(([2]Списки!$F$2:$F$20=E53)*[2]Списки!$G$2:$G$20)),G53*I53*SUMPRODUCT(('[2]Коэфы качество контакта'!$A$2:$A$50=E53)*'[2]Коэфы качество контакта'!$G$2:$G$50)))),"")} -> 7200 | N53: =IFERROR(M53*VLOOKUP(E53,'[2]Коэфы качество контакта'!$A$2:$E$50,3,FALSE)*VLOOKUP(E53,'[2]Коэфы качество контакта'!$A$2:$E$50,5,FALSE),"") -> 0 | O53: =IF(I52>0,I53*G53,IFERROR(J53/VLOOKUP(E53,'[2]Коэфы качество контакта'!$A$2:$G$50,7,FALSE),"")) -> 1440
D54: Digital | E54: Промо-пост | F54: 120 | G54: 0.3 | H54: 4000 | J54: {=IFERROR(IF(H54>0,H54*G54,IF(K54>0,G54*K54,IF(L54>0,L54*G54*(1-SUMPRODUCT(([2]Списки!$F$2:$F$20=E54)*[2]Списки!$G$2:$G$20)),G54*I54*SUMPRODUCT(('[2]Коэфы качество контакта'!$A$2:$A$50=E54)*'[2]Коэфы качество контакта'!$G$2:$G$50)))),"")} -> 1200 | N54: =IFERROR(M54*VLOOKUP(E54,'[2]Коэфы качество контакта'!$A$2:$E$50,3,FALSE)*VLOOKUP(E54,'[2]Коэфы качество контакта'!$A$2:$E$50,5,FALSE),"") -> 0 | O54: =IF(I54>0,I54*G54,IFERROR(J54/VLOOKUP(E54,'[2]Коэфы качество контакта'!$A$2:$G$50,7,FALSE),"")) -> 240
D55: Digital | E55: Аудио | J55: {=IFERROR(IF(H55>0,H55*G55,IF(K55>0,G55*K55,IF(L55>0,L55*G55*(1-SUMPRODUCT(([2]Списки!$F$2:$F$20=E55)*[2]Списки!$G$2:$G$20)),G55*I55*SUMPRODUCT(('[2]Коэфы качество контакта'!$A$2:$A$50=E55)*'[2]Коэфы качество контакта'!$G$2:$G$50)))),"")} -> 0 | N55: =IFERROR(M55*VLOOKUP(E55,'[2]Коэфы качество контакта'!$A$2:$E$50,3,FALSE)*VLOOKUP(E55,'[2]Коэфы качество контакта'!$A$2:$E$50,5,FALSE),"") -> 0 | O55: =IF(I55>0,I55*G55,IFERROR(J55/VLOOKUP(E55,'[2]Коэфы качество контакта'!$A$2:$G$50,7,FALSE),"")) -> 0
D56: Digital | E56: Промо-пост | J56: {=IFERROR(IF(H56>0,H56*G56,IF(K56>0,G56*K56,IF(L56>0,L56*G56*(1-SUMPRODUCT(([2]Списки!$F$2:$F$20=E56)*[2]Списки!$G$2:$G$20)),G56*I56*SUMPRODUCT(('[2]Коэфы качество контакта'!$A$2:$A$50=E56)*'[2]Коэфы качество контакта'!$G$2:$G$50)))),"")} -> 0 | N56: =IFERROR(M56*VLOOKUP(E56,'[2]Коэфы качество контакта'!$A$2:$E$50,3,FALSE)*VLOOKUP(E56,'[2]Коэфы качество контакта'!$A$2:$E$50,5,FALSE),"") -> 0 | O56: =IF(I56>0,I56*G56,IFERROR(J56/VLOOKUP(E56,'[2]Коэфы качество контакта'!$A$2:$G$50,7,FALSE),"")) -> 0
D57: Digital | J57: {=IFERROR(IF(H57>0,H57*G57,IF(K57>0,G57*K57,IF(L57>0,L57*G57*(1-SUMPRODUCT(([2]Списки!$F$2:$F$20=E57)*[2]Списки!$G$2:$G$20)),G57*I57*SUMPRODUCT(('[2]Коэфы качество контакта'!$A$2:$A$50=E57)*'[2]Коэфы качество контакта'!$G$2:$G$50)))),"")} -> 0 | N57: =IFERROR(M57*VLOOKUP(E57,'[2]Коэфы качество контакта'!$A$2:$E$50,3,FALSE)*VLOOKUP(E57,'[2]Коэфы качество контакта'!$A$2:$E$50,5,FALSE),"") | O57: =IF(I57>0,I57*G57,IFERROR(J57/VLOOKUP(E57,'[2]Коэфы качество контакта'!$A$2:$G$50,7,FALSE),""))
D58: Digital | J58: {=IFERROR(IF(H58>0,H58*G58,IF(K58>0,G58*K58,IF(L58>0,L58*G58*(1-SUMPRODUCT(([2]Списки!$F$2:$F$20=E58)*[2]Списки!$G$2:$G$20)),G58*I58*SUMPRODUCT(('[2]Коэфы качество контакта'!$A$2:$A$50=E58)*'[2]Коэфы качество контакта'!$G$2:$G$50)))),"")} -> 0 | N58: =IFERROR(M58*VLOOKUP(E58,'[2]Коэфы качество контакта'!$A$2:$E$50,3,FALSE)*VLOOKUP(E58,'[2]Коэфы качество контакта'!$A$2:$E$50,5,FALSE),"") | O58: =IF(I58>0,I58*G58,IFERROR(J58/VLOOKUP(E58,'[2]Коэфы качество контакта'!$A$2:$G$50,7,FALSE),""))
D59: Digital | J59: {=IFERROR(IF(H59>0,H59*G59,IF(K59>0,G59*K59,IF(L59>0,L59*G59*(1-SUMPRODUCT(([2]Списки!$F$2:$F$20=E59)*[2]Списки!$G$2:$G$20)),G59*I59*SUMPRODUCT(('[2]Коэфы качество контакта'!$A$2:$A$50=E59)*'[2]Коэфы качество контакта'!$G$2:$G$50)))),"")} -> 0 | N59: =IFERROR(M59*VLOOKUP(E59,'[2]Коэфы качество контакта'!$A$2:$E$50,3,FALSE)*VLOOKUP(E59,'[2]Коэфы качество контакта'!$A$2:$E$50,5,FALSE),"") | O59: =IF(I59>0,I59*G59,IFERROR(J59/VLOOKUP(E59,'[2]Коэфы качество контакта'!$A$2:$G$50,7,FALSE),""))
D60: Digital | J60: {=IFERROR(IF(H60>0,H60*G60,IF(K60>0,G60*K60,IF(L60>0,L60*G60*(1-SUMPRODUCT(([2]Списки!$F$2:$F$20=E60)*[2]Списки!$G$2:$G$20)),G60*I60*SUMPRODUCT(('[2]Коэфы качество контакта'!$A$2:$A$50=E60)*'[2]Коэфы качество контакта'!$G$2:$G$50)))),"")} -> 0 | N60: =IFERROR(M60*VLOOKUP(E60,'[2]Коэфы качество контакта'!$A$2:$E$50,3,FALSE)*VLOOKUP(E60,'[2]Коэфы качество контакта'!$A$2:$E$50,5,FALSE),"") | O60: =IF(I60>0,I60*G60,IFERROR(J60/VLOOKUP(E60,'[2]Коэфы качество контакта'!$A$2:$G$50,7,FALSE),""))
D61: Айдентика Бренда партнера на сайте | J61: =SUM(J62:J67) -> 1100 | K61: Посешаемость сайта за весь период, тыс. или заполнить сайт | L61: Сайт / размер аудитории | M61: Хронометраж | O61: =IF(J61>0,J61/1,IF((SUM(O62:O67)*0.6)>MAX(O62:O67),MAX(O62:O67),(SUM(O62:O67)*0.6))) -> 1100
D62: Айдентика Бренда партнера на сайте | E62: Billboard в шапке сайта | F62: 120 | G62: 1 | I62: 1100 | J62: {=IF(I62>0,I62,IF(H62>0,H62*G62,IF(K62<>"",K62*G62,G62*SUMPRODUCT(([2]Списки!$S$2:$S$17=Москва!L62)*[2]Списки!$T$2:$T$17)/1000)))} -> 1100 | O62: =IF(I62>0,I62*G62,J62/1) -> 1100
D63: Айдентика Бренда партнера на сайте | E63: Баннер боковой в 1 экране | J63: {=IF(I63>0,I63,IF(H63>0,H63*G63,IF(K63<>"",K63*G63,G63*SUMPRODUCT(([2]Списки!$S$2:$S$17=Москва!L63)*[2]Списки!$T$2:$T$17)/1000)))} -> 0 | O63: =IF(I63>0,I63*G63,J63/1) -> 0
D64: Айдентика Бренда партнера на сайте | E64: Баннер боковой во 2м экране | J64: {=IF(I64>0,I64,IF(H64>0,H64*G64,IF(K64<>"",K64*G64,G64*SUMPRODUCT(([2]Списки!$S$2:$S$17=Москва!L64)*[2]Списки!$T$2:$T$17)/1000)))} -> 0 | O64: =IF(I64>0,I64*G64,J64/1) -> 0
D65: Айдентика Бренда партнера на сайте | J65: {=IF(I65>0,I65,IF(H65>0,H65*G65,IF(K65<>"",K65*G65,G65*SUMPRODUCT(([2]Списки!$S$2:$S$17=Москва!L65)*[2]Списки!$T$2:$T$17)/1000)))} -> 0 | O65: =IF(I65>0,I65*G65,J65/1) -> 0
D66: Айдентика Бренда партнера на сайте | J66: {=IF(I66>0,I66,IF(H66>0,H66*G66,IF(K66<>"",K66*G66,G66*SUMPRODUCT(([2]Списки!$S$2:$S$17=Москва!L66)*[2]Списки!$T$2:$T$17)/1000)))} -> 0 | O66: =IF(I66>0,I66*G66,J66/1) -> 0
D67: Айдентика Бренда партнера на сайте | J67: {=IF(I67>0,I67,IF(H67>0,H67*G67,IF(K67<>"",K67*G67,G67*SUMPRODUCT(([2]Списки!$S$2:$S$17=Москва!L67)*[2]Списки!$T$2:$T$17)/1000)))} -> 0 | O67: =IF(I67>0,I67*G67,J67/1) -> 0
D68: PR | J68: =SUM(J69:J74) -> 5000 | K68: Количество просмотров статьи, тыс. или заполнить сайт | L68: Сайт / размер аудитории | M68: Хронометраж | O68: =IF(J68>0,J68/1.5,(1-(1-(O69/$E$3*0.5))*(1-(O70/$E$3*0.5))*(1-(O71/$E$3*0.5))*(1-(O72/$E$3*0.5))*(1-(O73/$E$3*0.5))*(1-(O74/$E$3*0.5)))*$E$3) -> 3333.3333
D69: PR | E69: Статьи о событии | F69: 120 | G69: 0.5 | H69: 10000 | J69: {=IF(I69>0,I69*1.5,IF(H69>0,H69*G69,IF(K69<>"",K69*G69,G69*SUMPRODUCT(([2]Списки!$S$2:$S$17=Москва!L69)*[2]Списки!$T$2:$T$17)/1000)*(1-SUMPRODUCT(([2]Списки!$I$2:$I$7=Москва!E69)*[2]Списки!$J$2:$J$7))))} -> 5000 | L69: 300 тыс | M69: 1 | O69: =IF(I69>0,I69*G69,J69/1.5) -> 3333.3333
D70: PR | E70: Статьи с упоминанием события | J70: {=IF(I70>0,I70*1.5,IF(H70>0,H70*G70,IF(K70<>"",K70*G70,G70*SUMPRODUCT(([2]Списки!$S$2:$S$17=Москва!L70)*[2]Списки!$T$2:$T$17)/1000)*(1-SUMPRODUCT(([2]Списки!$I$2:$I$7=Москва!E70)*[2]Списки!$J$2:$J$7))))} -> 0 | M70: 1 | O70: =IF(I70>0,I70*G70,J70/1.5) -> 0
D71: PR | E71: Посев в TG | J71: {=IF(I71>0,I71*1.5,IF(H71>0,H71*G71,IF(K71<>"",K71*G71,G71*SUMPRODUCT(([2]Списки!$S$2:$S$17=Москва!L71)*[2]Списки!$T$2:$T$17)/1000)*(1-SUMPRODUCT(([2]Списки!$I$2:$I$7=Москва!E71)*[2]Списки!$J$2:$J$7))))} -> 0 | M71: 1 | O71: =IF(I71>0,I71*G71,J71/1.5) -> 0
D72: PR | E72: Блогеры в TG | J72: {=IF(I72>0,I72*1.5,IF(H72>0,H72*G72,IF(K72<>"",K72*G72,G72*SUMPRODUCT(([2]Списки!$S$2:$S$17=Москва!L72)*[2]Списки!$T$2:$T$17)/1000)*(1-SUMPRODUCT(([2]Списки!$I$2:$I$7=Москва!E72)*[2]Списки!$J$2:$J$7))))} -> 0 | M72: 1 | O72: =IF(I72>0,I72*G72,J72/1.5) -> 0
D73: PR | E73: Блогеры в VK | J73: {=IF(I73>0,I73*1.5,IF(H73>0,H73*G73,IF(K73<>"",K73*G73,G73*SUMPRODUCT(([2]Списки!$S$2:$S$17=Москва!L73)*[2]Списки!$T$2:$T$17)/1000)*(1-SUMPRODUCT(([2]Списки!$I$2:$I$7=Москва!E73)*[2]Списки!$J$2:$J$7))))} -> 0 | M73: 1 | O73: =IF(I73>0,I73*G73,J73/1.5) -> 0
D74: PR | E74: Посев в VK | J74: {=IF(I74>0,I74*1.5,IF(H74>0,H74*G74,IF(K74<>"",K74*G74,G74*SUMPRODUCT(([2]Списки!$S$2:$S$17=Москва!L74)*[2]Списки!$T$2:$T$17)/1000)*(1-SUMPRODUCT(([2]Списки!$I$2:$I$7=Москва!E74)*[2]Списки!$J$2:$J$7))))} -> 0 | M74: 1 | O74: =IF(I74>0,I74*G74,J74/1.5) -> 0
B75: 5 | C75: Тип активации: ПРОДВИЖЕНИЕ НА МЕРОПРИЯТИИ | D75: Видео | J75: =SUM(J76:J79) -> 90 | O75: =IF(IF(COUNTIF($O$76:$O$79,">0")>1,(1-(1-($O$76/$E$8))*(1-($O$77/$E$8))*(1-($O$78/$E$8))*(1-($O$79/$E$8)))*$E$8,SUM($O$76:$O$79))>$E$8,E8,IF(COUNTIF($O$76:$O$79,">0")>1,(1-(1-($O$76/$E$8))*(1-($O$77/$E$8))*(1-($O$78/$E$8))*(1-($O$79/$E$8)))*$E$8,SUM($O$76:$O$79))) -> 30
D76: Видео | E76: Экраны на сцене | F76: 28 | G76: 1 | H76: 90 | J76: {=IF(H76>0,H76*G76,G76*SUMPRODUCT(('[2]Коэфы брендирование'!$P$2:$P$5=Москва!E76)*'[2]Коэфы брендирование'!$Q$2:$Q$5)*$E$8)} -> 90 | M76: 0 | O76: {=IFERROR(IF(I76>0,I76*G76,J76/SUMPRODUCT(('[2]Коэфы брендирование'!$P$2:$P$996=Москва!$E76)*'[2]Коэфы брендирование'!$R$2:$R$996)),"-")} -> 30
D77: Видео | E77: Экраны в чаше локации/стадиона | J77: {=IF(H77>0,H77*G77,G77*SUMPRODUCT(('[2]Коэфы брендирование'!$P$2:$P$5=Москва!E77)*'[2]Коэфы брендирование'!$Q$2:$Q$5)*$E$8)} -> 0 | O77: {=IFERROR(IF(I77>0,I77*G77,J77/SUMPRODUCT(('[2]Коэфы брендирование'!$P$2:$P$996=Москва!$E77)*'[2]Коэфы брендирование'!$R$2:$R$996)),"-")} -> 0
D78: Видео | E78: Плазменные панели на територии локации/стадиона | J78: {=IF(H78>0,H78*G78,G78*SUMPRODUCT(('[2]Коэфы брендирование'!$P$2:$P$5=Москва!E78)*'[2]Коэфы брендирование'!$Q$2:$Q$5)*$E$8)} -> 0 | O78: {=IFERROR(IF(I78>0,I78*G78,J78/SUMPRODUCT(('[2]Коэфы брендирование'!$P$2:$P$996=Москва!$E78)*'[2]Коэфы брендирование'!$R$2:$R$996)),"-")} -> 0
D79: Видео | E79: Лого на входе | J79: {=IF(H79>0,H79*G79,G79*SUMPRODUCT(('[2]Коэфы брендирование'!$P$2:$P$5=Москва!E79)*'[2]Коэфы брендирование'!$Q$2:$Q$5)*$E$8)} -> 0 | O79: {=IFERROR(IF(I79>0,I79*G79,J79/SUMPRODUCT(('[2]Коэфы брендирование'!$P$2:$P$996=Москва!$E79)*'[2]Коэфы брендирование'!$R$2:$R$996)),"-")} -> 0
D80: Аудио | J80: =SUM(J81:J82) -> 0 | O80: =IF(IF(COUNTIF($O$81:$O$82,">0")>1,(1-(1-($O$81/$E$8))*(1-($O$82/$E$8)))*$E$8,SUM($O$81:$O$82))>$E$8,E8,IF(COUNTIF($O$81:$O$82,">0")>1,(1-(1-($O$81/$E$8))*(1-($O$82/$E$8))*(1-($O$81/$E$8))*(1-($O$82/$E$8)))*$E$8,SUM($O$81:$O$82))) -> 0
D81: Аудио | E81: Голосовое сообщение до старта мероприятия | J81: {=IF(H81>0,H81*G81,G81*SUMPRODUCT(('[2]Коэфы брендирование'!$A$2:$A$3=Москва!E81)*'[2]Коэфы брендирование'!$B$2:$B$3)*$E$8)} -> 0 | O81: {=IFERROR(IF(I81>0,I81*G81,J81/SUMPRODUCT(('[2]Коэфы брендирование'!$A$2:$A$996=Москва!$E81)*'[2]Коэфы брендирование'!$C$2:$C$996)),"-")} -> 0
D82: Аудио | E82: Голосовое сообщение во время мероприятия | J82: {=IF(H82>0,H82*G82,G82*SUMPRODUCT(('[2]Коэфы брендирование'!$A$2:$A$3=Москва!E82)*'[2]Коэфы брендирование'!$B$2:$B$3)*$E$8)} -> 0 | O82: {=IFERROR(IF(I82>0,I82*G82,J82/SUMPRODUCT(('[2]Коэфы брендирование'!$A$2:$A$996=Москва!$E82)*'[2]Коэфы брендирование'!$C$2:$C$996)),"-")} -> 0
D83: Брендирование | J83: =SUM(J84:J105) -> 900 | O83: =IF(IF(COUNTIF($O$84:$O$105,">0")>1,(1-(1-($O$84/$E$8))*(1-($O$85/$E$8))*(1-($O$86/$E$8))*(1-($O$87/$E$8))*(1-($O$88/$E$8))*(1-($O$89/$E$8))*(1-($O$90/$E$8))*(1-($O$91/$E$8))*(1-($O$92/$E$8))*(1-($O$93/$E$8))*(1-($O$94/$E$8))*(1-($O$95/$E$8))*(1-($O$96/$E$8))*(1-($O$97/$E$8))*(1-($O$98/$E$8))*(1-($O$99/$E$8))*(1-($O$100/$E$8))*(1-($O$101/$E$8))*(1-($O$102/$E$8))*(1-($O$103/$E$8))*(1-($O$104/$E$8))*(1-($O$105/$E$8)))*$E$8,SUM($O$84:$O$105))>$E$8,E8,IF(COUNTIF($O$84:$O$105,">0")>1,(1-(1-($O$84/$E$8))*(1-($O$85/$E$8))*(1-($O$86/$E$8))*(1-($O$87/$E$8))*(1-($O$88/$E$8))*(1-($O$89/$E$8))*(1-($O$90/$E$8))*(1-($O$91/$E$8))*(1-($O$92/$E$8))*(1-($O$93/$E$8))*(1-($O$94/$E$8))*(1-($O$95/$E$8))*(1-($O$96/$E$8))*(1-($O$97/$E$8))*(1-($O$98/$E$8))*(1-($O$99/$E$8))*(1-($O$100/$E$8))*(1-($O$101/$E$8))*(1-($O$102/$E$8))*(1-($O$103/$E$8))*(1-($O$104/$E$8))*(1-($O$105/$E$8)))*$E$8,SUM($O$84:$O$105))) -> 90
D84: Брендирование | E84: брендинг вип-зоны | F84: 28 | G84: 1 | H84: 90 | J84: {=IF(H84>0,H84*G84,G84*SUMPRODUCT(('[2]Коэфы брендирование'!$D$2:$D$23=Москва!E84)*'[2]Коэфы брендирование'!$E$2:$E$23)*$E$8*(1-SUMPRODUCT(([2]Списки!$W$2:$W$5=Москва!$E$5)*[2]Списки!$X$2:$X$5)))} -> 90 | O84: {=IFERROR(IF(I84>0,I84*G84,J84/SUMPRODUCT(('[2]Коэфы брендирование'!$D$2:$D$993=Москва!$E84)*'[2]Коэфы брендирование'!$F$2:$F$993)),0)} -> 30
D85: Брендирование | E85: размещение арт-объекта | F85: 28 | G85: 1 | H85: 90 | J85: {=IF(H85>0,H85*G85,G85*SUMPRODUCT(('[2]Коэфы брендирование'!$D$2:$D$23=Москва!E85)*'[2]Коэфы брендирование'!$E$2:$E$23)*$E$8*(1-SUMPRODUCT(([2]Списки!$W$2:$W$5=Москва!$E$5)*[2]Списки!$X$2:$X$5)))} -> 90 | O85: {=IFERROR(IF(I85>0,I85*G85,J85/SUMPRODUCT(('[2]Коэфы брендирование'!$D$2:$D$993=Москва!$E85)*'[2]Коэфы брендирование'!$F$2:$F$993)),0)} -> 90
D86: Брендирование | E86: бренд-зона/лаундж-зона | F86: 28 | G86: 1 | H86: 90 | J86: {=IF(H86>0,H86*G86,G86*SUMPRODUCT(('[2]Коэфы брендирование'!$D$2:$D$23=Москва!E86)*'[2]Коэфы брендирование'!$E$2:$E$23)*$E$8*(1-SUMPRODUCT(([2]Списки!$W$2:$W$5=Москва!$E$5)*[2]Списки!$X$2:$X$5)))} -> 90 | O86: {=IFERROR(IF(I86>0,I86*G86,J86/SUMPRODUCT(('[2]Коэфы брендирование'!$D$2:$D$993=Москва!$E86)*'[2]Коэфы брендирование'!$F$2:$F$993)),0)} -> 60
D87: Брендирование | E87: брендинг браслетов | F87: 28 | G87: 1 | H87: 90 | J87: {=IF(H87>0,H87*G87,G87*SUMPRODUCT(('[2]Коэфы брендирование'!$D$2:$D$23=Москва!E87)*'[2]Коэфы брендирование'!$E$2:$E$23)*$E$8*(1-SUMPRODUCT(([2]Списки!$W$2:$W$5=Москва!$E$5)*[2]Списки!$X$2:$X$5)))} -> 90 | O87: {=IFERROR(IF(I87>0,I87*G87,J87/SUMPRODUCT(('[2]Коэфы брендирование'!$D$2:$D$993=Москва!$E87)*'[2]Коэфы брендирование'!$F$2:$F$993)),0)} -> 15
D88: Брендирование | E88: брендинг одежды персонала (бармены, гардеробщики) | F88: 28 | G88: 1 | H88: 90 | J88: {=IF(H88>0,H88*G88,G88*SUMPRODUCT(('[2]Коэфы брендирование'!$D$2:$D$23=Москва!E88)*'[2]Коэфы брендирование'!$E$2:$E$23)*$E$8*(1-SUMPRODUCT(([2]Списки!$W$2:$W$5=Москва!$E$5)*[2]Списки!$X$2:$X$5)))} -> 90 | O88: {=IFERROR(IF(I88>0,I88*G88,J88/SUMPRODUCT(('[2]Коэфы брендирование'!$D$2:$D$993=Москва!$E88)*'[2]Коэфы брендирование'!$F$2:$F$993)),0)} -> 45
D89: Брендирование | E89: брендированная раздатка (например, флешмоб с брендированными масками с лицом артиста) | F89: 28 | G89: 1 | H89: 90 | J89: {=IF(H89>0,H89*G89,G89*SUMPRODUCT(('[2]Коэфы брендирование'!$D$2:$D$23=Москва!E89)*'[2]Коэфы брендирование'!$E$2:$E$23)*$E$8*(1-SUMPRODUCT(([2]Списки!$W$2:$W$5=Москва!$E$5)*[2]Списки!$X$2:$X$5)))} -> 90 | O89: {=IFERROR(IF(I89>0,I89*G89,J89/SUMPRODUCT(('[2]Коэфы брендирование'!$D$2:$D$993=Москва!$E89)*'[2]Коэфы брендирование'!$F$2:$F$993)),0)} -> 30
D90: Брендирование | E90: брендированная зона раздачи мерча | F90: 28 | G90: 1 | H90: 90 | J90: {=IF(H90>0,H90*G90,G90*SUMPRODUCT(('[2]Коэфы брендирование'!$D$2:$D$23=Москва!E90)*'[2]Коэфы брендирование'!$E$2:$E$23)*$E$8*(1-SUMPRODUCT(([2]Списки!$W$2:$W$5=Москва!$E$5)*[2]Списки!$X$2:$X$5)))} -> 90 | O90: {=IFERROR(IF(I90>0,I90*G90,J90/SUMPRODUCT(('[2]Коэфы брендирование'!$D$2:$D$993=Москва!$E90)*'[2]Коэфы брендирование'!$F$2:$F$993)),0)} -> 90
D91: Брендирование | E91: AR-фотозона (с интерактивом) | F91: 28 | G91: 1 | H91: 90 | J91: {=IF(H91>0,H91*G91,G91*SUMPRODUCT(('[2]Коэфы брендирование'!$D$2:$D$23=Москва!E91)*'[2]Коэфы брендирование'!$E$2:$E$23)*$E$8*(1-SUMPRODUCT(([2]Списки!$W$2:$W$5=Москва!$E$5)*[2]Списки!$X$2:$X$5)))} -> 90 | O91: {=IFERROR(IF(I91>0,I91*G91,J91/SUMPRODUCT(('[2]Коэфы брендирование'!$D$2:$D$993=Москва!$E91)*'[2]Коэфы брендирование'!$F$2:$F$993)),0)} -> 45
D92: Брендирование | E92: флаги/штендеры/лайтбоксы/расклеенные печатные лого/тейбл-тенты на локации мероприятия | F92: 28 | G92: 1 | H92: 90 | J92: {=IF(H92>0,H92*G92,G92*SUMPRODUCT(('[2]Коэфы брендирование'!$D$2:$D$23=Москва!E92)*'[2]Коэфы брендирование'!$E$2:$E$23)*$E$8*(1-SUMPRODUCT(([2]Списки!$W$2:$W$5=Москва!$E$5)*[2]Списки!$X$2:$X$5)))} -> 90 | O92: {=IFERROR(IF(I92>0,I92*G92,J92/SUMPRODUCT(('[2]Коэфы брендирование'!$D$2:$D$993=Москва!$E92)*'[2]Коэфы брендирование'!$F$2:$F$993)),0)} -> 60
D93: Брендирование | E93: раздача/продажа брендированного мерча на площадке | F93: 28 | G93: 1 | H93: 90 | J93: {=IF(H93>0,H93*G93,G93*SUMPRODUCT(('[2]Коэфы брендирование'!$D$2:$D$23=Москва!E93)*'[2]Коэфы брендирование'!$E$2:$E$23)*$E$8*(1-SUMPRODUCT(([2]Списки!$W$2:$W$5=Москва!$E$5)*[2]Списки!$X$2:$X$5)))} -> 90 | O93: {=IFERROR(IF(I93>0,I93*G93,J93/SUMPRODUCT(('[2]Коэфы брендирование'!$D$2:$D$993=Москва!$E93)*'[2]Коэфы брендирование'!$F$2:$F$993)),0)} -> 90
D94: Брендирование | J94: {=IF(H94>0,H94*G94,G94*SUMPRODUCT(('[2]Коэфы брендирование'!$D$2:$D$23=Москва!E94)*'[2]Коэфы брендирование'!$E$2:$E$23)*$E$8*(1-SUMPRODUCT(([2]Списки!$W$2:$W$5=Москва!$E$5)*[2]Списки!$X$2:$X$5)))} -> 0 | O94: {=IFERROR(IF(I94>0,I94*G94,J94/SUMPRODUCT(('[2]Коэфы брендирование'!$D$2:$D$993=Москва!$E94)*'[2]Коэфы брендирование'!$F$2:$F$993)),0)} -> 0
D95: Брендирование | J95: {=IF(H95>0,H95*G95,G95*SUMPRODUCT(('[2]Коэфы брендирование'!$D$2:$D$23=Москва!E95)*'[2]Коэфы брендирование'!$E$2:$E$23)*$E$8*(1-SUMPRODUCT(([2]Списки!$W$2:$W$5=Москва!$E$5)*[2]Списки!$X$2:$X$5)))} -> 0 | O95: {=IFERROR(IF(I95>0,I95*G95,J95/SUMPRODUCT(('[2]Коэфы брендирование'!$D$2:$D$993=Москва!$E95)*'[2]Коэфы брендирование'!$F$2:$F$993)),0)} -> 0
D96: Брендирование | J96: {=IF(H96>0,H96*G96,G96*SUMPRODUCT(('[2]Коэфы брендирование'!$D$2:$D$23=Москва!E96)*'[2]Коэфы брендирование'!$E$2:$E$23)*$E$8*(1-SUMPRODUCT(([2]Списки!$W$2:$W$5=Москва!$E$5)*[2]Списки!$X$2:$X$5)))} -> 0 | O96: {=IFERROR(IF(I96>0,I96*G96,J96/SUMPRODUCT(('[2]Коэфы брендирование'!$D$2:$D$993=Москва!$E96)*'[2]Коэфы брендирование'!$F$2:$F$993)),0)} -> 0
D97: Брендирование | J97: {=IF(H97>0,H97*G97,G97*SUMPRODUCT(('[2]Коэфы брендирование'!$D$2:$D$23=Москва!E97)*'[2]Коэфы брендирование'!$E$2:$E$23)*$E$8*(1-SUMPRODUCT(([2]Списки!$W$2:$W$5=Москва!$E$5)*[2]Списки!$X$2:$X$5)))} -> 0 | O97: {=IFERROR(IF(I97>0,I97*G97,J97/SUMPRODUCT(('[2]Коэфы брендирование'!$D$2:$D$993=Москва!$E97)*'[2]Коэфы брендирование'!$F$2:$F$993)),0)} -> 0
D98: Брендирование | J98: {=IF(H98>0,H98*G98,G98*SUMPRODUCT(('[2]Коэфы брендирование'!$D$2:$D$23=Москва!E98)*'[2]Коэфы брендирование'!$E$2:$E$23)*$E$8*(1-SUMPRODUCT(([2]Списки!$W$2:$W$5=Москва!$E$5)*[2]Списки!$X$2:$X$5)))} -> 0 | O98: {=IFERROR(IF(I98>0,I98*G98,J98/SUMPRODUCT(('[2]Коэфы брендирование'!$D$2:$D$993=Москва!$E98)*'[2]Коэфы брендирование'!$F$2:$F$993)),0)} -> 0
D99: Брендирование | J99: {=IF(H99>0,H99*G99,G99*SUMPRODUCT(('[2]Коэфы брендирование'!$D$2:$D$23=Москва!E99)*'[2]Коэфы брендирование'!$E$2:$E$23)*$E$8*(1-SUMPRODUCT(([2]Списки!$W$2:$W$5=Москва!$E$5)*[2]Списки!$X$2:$X$5)))} -> 0 | O99: {=IFERROR(IF(I99>0,I99*G99,J99/SUMPRODUCT(('[2]Коэфы брендирование'!$D$2:$D$993=Москва!$E99)*'[2]Коэфы брендирование'!$F$2:$F$993)),0)} -> 0
D100: Брендирование | J100: {=IF(H100>0,H100*G100,G100*SUMPRODUCT(('[2]Коэфы брендирование'!$D$2:$D$23=Москва!E100)*'[2]Коэфы брендирование'!$E$2:$E$23)*$E$8*(1-SUMPRODUCT(([2]Списки!$W$2:$W$5=Москва!$E$5)*[2]Списки!$X$2:$X$5)))} -> 0 | O100: {=IFERROR(IF(I100>0,I100*G100,J100/SUMPRODUCT(('[2]Коэфы брендирование'!$D$2:$D$993=Москва!$E100)*'[2]Коэфы брендирование'!$F$2:$F$993)),0)} -> 0
D101: Брендирование | J101: {=IF(H101>0,H101*G101,G101*SUMPRODUCT(('[2]Коэфы брендирование'!$D$2:$D$23=Москва!E101)*'[2]Коэфы брендирование'!$E$2:$E$23)*$E$8*(1-SUMPRODUCT(([2]Списки!$W$2:$W$5=Москва!$E$5)*[2]Списки!$X$2:$X$5)))} -> 0 | O101: {=IFERROR(IF(I101>0,I101*G101,J101/SUMPRODUCT(('[2]Коэфы брендирование'!$D$2:$D$993=Москва!$E101)*'[2]Коэфы брендирование'!$F$2:$F$993)),0)} -> 0
D102: Брендирование | J102: {=IF(H102>0,H102*G102,G102*SUMPRODUCT(('[2]Коэфы брендирование'!$D$2:$D$23=Москва!E102)*'[2]Коэфы брендирование'!$E$2:$E$23)*$E$8*(1-SUMPRODUCT(([2]Списки!$W$2:$W$5=Москва!$E$5)*[2]Списки!$X$2:$X$5)))} -> 0 | O102: {=IFERROR(IF(I102>0,I102*G102,J102/SUMPRODUCT(('[2]Коэфы брендирование'!$D$2:$D$993=Москва!$E102)*'[2]Коэфы брендирование'!$F$2:$F$993)),0)} -> 0
D103: Брендирование | J103: {=IF(H103>0,H103*G103,G103*SUMPRODUCT(('[2]Коэфы брендирование'!$D$2:$D$23=Москва!E103)*'[2]Коэфы брендирование'!$E$2:$E$23)*$E$8*(1-SUMPRODUCT(([2]Списки!$W$2:$W$5=Москва!$E$5)*[2]Списки!$X$2:$X$5)))} -> 0 | O103: {=IFERROR(IF(I103>0,I103*G103,J103/SUMPRODUCT(('[2]Коэфы брендирование'!$D$2:$D$993=Москва!$E103)*'[2]Коэфы брендирование'!$F$2:$F$993)),0)} -> 0
D104: Брендирование | J104: {=IF(H104>0,H104*G104,G104*SUMPRODUCT(('[2]Коэфы брендирование'!$D$2:$D$23=Москва!E104)*'[2]Коэфы брендирование'!$E$2:$E$23)*$E$8*(1-SUMPRODUCT(([2]Списки!$W$2:$W$5=Москва!$E$5)*[2]Списки!$X$2:$X$5)))} -> 0 | O104: {=IFERROR(IF(I104>0,I104*G104,J104/SUMPRODUCT(('[2]Коэфы брендирование'!$D$2:$D$993=Москва!$E104)*'[2]Коэфы брендирование'!$F$2:$F$993)),0)} -> 0
...

Sheet Списки
A1: Фильтр | B1: Список
A2: ГЕО | B2: Москва
A3: ГЕО | B3: Санкт-Петербург
A4: ГЕО | B4: Екатеринбург
A5: ГЕО | B5: Томск
A6: ГЕО | B6: Кемерово
A7: ГЕО | B7: Казань
A8: ГЕО | B8: Новосибирск
A9: ГЕО | B9: Краснодар
A10: ГЕО | B10: Сочи
A11: ГЕО | B11: Чебоксары
A12: ГЕО | B12: Нижний Новгород
... A19: Тип площадки | B19: Площадка

Sheet Описание
A1: Описание
A2: ООН
A3: Indoor
A4: Радио
A5: Digital
A6: Айдентика Бренда партнера на сайте
A7: PR
A8: Видео
A9: Брендирование
A10: Промо-акции
A11: Лого партнера
A12: BB
... A75: Блогеры в VK

Sheet Форматы
A1: Описание | B1: Форматы
A2: ООН | B2: BB
A3: ООН | B3: DBB
A4: ООН | B4: SS
A5: ООН | B5: DSS
A6: ООН | B6: CF
A7: ООН | B7: DCF
A8: ООН | B8: Медиафасады
A9: ООН | B9: PL
A10: Digital | B10: Видео
A11: Digital | B11: Баннеры
A12: Digital | B12: Аудио
... A65: PR | B65: Блогеры в VK

Sheet PR
A1: Sostav
A2: Marie Claire
A3: НСН
A4: Woman.ru
A5: Thegirl.ru
A6: The Blueprint
A7: AdIndex
A8: РБК
A9: Коммерсант
A10: Известия
A11: 100 тыс
A12: 200 тыс
... A16: 1 млн
