Workbook
Name Indoor: OFFSET([1]Indoor!$A$2,MATCH(TEMPLATE!$E$22,[1]Indoor!$A$2:$A$996,0)-1,1,COUNTIF([1]Indoor!$A$2:$A$996,TEMPLATE!$E$22),1)
Name Indoor: OFFSET(Indoor!$A$2,MATCH(#REF!,Indoor!$A$2:$A$996,0)-1,1,COUNTIF(Indoor!$A$2:$A$996,#REF!),1)
Name OTSРадио: OFFSET([1]Радиостанции!$B$1,MATCH(TEMPLATE!$E1,[1]Радиостанции!$B:$B,0)-1,3,COUNTIF([1]Радиостанции!$B:$B,TEMPLATE!$E1),1)
Name OTSРадио: OFFSET(Радиостанции!$B$1,MATCH(#REF!,Радиостанции!$B:$B,0)-1,3,COUNTIF(Радиостанции!$B:$B,#REF!),1)
Name OTSРадиоМосква: OFFSET([1]Радиостанции!$C$1,MATCH(TEMPLATE!$P1,[1]Радиостанции!$C:$C,0)-1,3,COUNTIF([1]Радиостанции!$C:$C,TEMPLATE!$P1),1)
Name OTSРадиоМосква: OFFSET(Радиостанции!$C$1,MATCH(#REF!,Радиостанции!$C:$C,0)-1,3,COUNTIF(Радиостанции!$C:$C,#REF!),1)
Name OTSТВ: OFFSET('[1]ТВ Каналы'!$B$1,MATCH(TEMPLATE!$E1,'[1]ТВ Каналы'!$B:$B,0)-1,4,COUNTIF('[1]ТВ Каналы'!$B:$B,TEMPLATE!$E1),1)
Name OTSТВ: OFFSET('ТВ Каналы'!$B$1,MATCH(#REF!,'ТВ Каналы'!$B:$B,0)-1,4,COUNTIF('ТВ Каналы'!$B:$B,#REF!),1)
Name OTSТВМосква: OFFSET('[1]ТВ Каналы'!$C$1,MATCH(TEMPLATE!$P1,'[1]ТВ Каналы'!$C:$C,0)-1,3,COUNTIF('[1]ТВ Каналы'!$C:$C,TEMPLATE!$P1),1)
Name OTSТВМосква: OFFSET('ТВ Каналы'!$C$1,MATCH(#REF!,'ТВ Каналы'!$C:$C,0)-1,3,COUNTIF('ТВ Каналы'!$C:$C,#REF!),1)
Name OTSТВСумм: SUM(TEMPLATE!OTSТВ)
Name OTSТВСумм: SUM(OTSТВ)
Name Канал: OFFSET([1]ТВ!$A$1,MATCH(TEMPLATE!$E$22,[1]ТВ!$A:$A,0)-1,1,COUNTIF([1]ТВ!$A:$A,TEMPLATE!$E$22),1)
Name Канал: OFFSET(ТВ!$A$1,MATCH(#REF!,ТВ!$A:$A,0)-1,1,COUNTIF(ТВ!$A:$A,#REF!),1)
Name МинутыРадио: OFFSET([1]Радиостанции!$B$1,MATCH(TEMPLATE!$E1,[1]Радиостанции!$B:$B,0)-1,2,COUNTIF([1]Радиостанции!$B:$B,TEMPLATE!$E1),1)
Name МинутыРадио: OFFSET(Радиостанции!$B$1,MATCH(#REF!,Радиостанции!$B:$B,0)-1,2,COUNTIF(Радиостанции!$B:$B,#REF!),1)
Name МинутыРадиоМосква: OFFSET([1]Радиостанции!$C$1,MATCH(TEMPLATE!$P1,[1]Радиостанции!$C:$C,0)-1,2,COUNTIF([1]Радиостанции!$C:$C,TEMPLATE!$P1),1)
Name МинутыРадиоМосква: OFFSET(Радиостанции!$C$1,MATCH(#REF!,Радиостанции!$C:$C,0)-1,2,COUNTIF(Радиостанции!$C:$C,#REF!),1)
Name МинутыТВ: OFFSET('[1]ТВ Каналы'!$B$1,MATCH(TEMPLATE!$E1,'[1]ТВ Каналы'!$B:$B,0)-1,2,COUNTIF('[1]ТВ Каналы'!$B:$B,TEMPLATE!$E1),1)
Name МинутыТВ: OFFSET('ТВ Каналы'!$B$1,MATCH(#REF!,'ТВ Каналы'!$B:$B,0)-1,2,COUNTIF('ТВ Каналы'!$B:$B,#REF!),1)
Name МинутыТВМосква: OFFSET('[1]ТВ Каналы'!$C$1,MATCH(TEMPLATE!$P1,'[1]ТВ Каналы'!$C:$C,0)-1,2,COUNTIF('[1]ТВ Каналы'!$C:$C,TEMPLATE!$P1),1)
Name МинутыТВМосква: OFFSET('ТВ Каналы'!$C$1,MATCH(#REF!,'ТВ Каналы'!$C:$C,0)-1,2,COUNTIF('ТВ Каналы'!$C:$C,#REF!),1)
Name Радио: OFFSET([1]Radio!$A$1,MATCH(TEMPLATE!$E$22,[1]Radio!$A:$A,0)-1,1,COUNTIF([1]Radio!$A:$A,TEMPLATE!$E$22),1)
Name Радио: OFFSET(Radio!$A$1,MATCH(#REF!,Radio!$A:$A,0)-1,1,COUNTIF(Radio!$A:$A,#REF!),1)

Sheet TEMPLATE
C2: Коммерческое предложение
C3: Результат | D3: Содержание | E3: Этапы подготовки
C4: 1. Калькулятор для оценки эффективности комплексных проектов, нацеленных на продвижение бренда | D4: Оценка эффективности согласно брифу учитывает: - список городов (всего 15) - ЦА Все 18+ - разбивку по типам/этапам активации (до мероприятия, во время мероприятия, дополнительные активации по итогам мероприятия) - список медиа каналов 360 и PR - детализацию по форматам - параметры качества по каналам, форматам - оценку Охвата/OTS, стоимости размещения, стоимость за Контакт и стоимость за Посетителя | E4: 1) Формирование и согласование детального брифа на подготовку Калькулятора 2) Сбор, обработка и валидация аналитических и статистических данных для имплементации расчетов Калькулятора 3) Написание методологии для расчетов Калькулятора 4) Техническая реализация - производство Калькулятора 5) Обсуждение разработанного Калькулятора 6) Доработка Калькулятора в соответствии с полученными комментариями
C5: 2. Универсальная/единая форма отчетности (УФО) по итогам размещения/активности для комплексных проектов | D5: УФО учитывает: - возможность выбора типа/этапа активации (до мероприятия, во время мероприятия, дополнительные активации по итогам мероприятия), медиа каналов 360 и PR, форматы размещения - внесение фактических данных, на базе которых будет произведена оценка эффективности комплексного проекта | E5: 1) Формирование и согласование детального брифа на подготовку УФО 2) Написание методологии для формирования УФО 3) Техническая реализация - производство УФО 4) Обсуждение разработанной УФО 5) Доработка УФО в соответствии с полученными комментариями
E6: ИТОГО:
C8: Последующие изменения и дополнения Калькулятора и УФО не учтены в расчете и будут оценены отдельно при необходимости доработки
C10: в сопроводительном письме говорим, что сроки обусловлены сезоном отпусков и необходимости участия как аналитиков, так и департамента стратегического планирования медиа, про ЦА
C11: Предлагаем делать оценку на ЦА 18+
D16: Вводится пользователем
D17: Счиатется автоматически на основе данных внутри калькулятора
C20: Параметры | D20: Описание
C21: ЦА | D21: Унифицированная аудитория для всех медиа, тыс. 16+ | E21: =VLOOKUP($E$22,'[1]ЦА по городам'!$A$2:$B$16,2,FALSE)/1000 -> #N/A
B22: 1 | C22: Гео | D22: 15 городов
C23: Тип площадки | D23: концерт/фестиваль/площадка
D24: количество дней на фестивале/площадке
B25: 2 | C25: Общий период размещения | D25: в днях
B26: 3 | C26: План посетителей | D26: в тысячах человек
B27: # | C27: Медиа факторы | D27: Описание | E27: Форматы | F27: Период размещения, дни | G27: Доля брендирования | H27: OTS 16+ ('000) | I27: Охват 16+* ('000) | J27: OTS 16+ ('000) (с учетом доли брендирования) | K27: Как оцениваем OTS медиа, в случае отсутствия данных по OTS и Охватам у поставщика | M27: Индекс качества (для медиа) | O27: Охват 16+ ('000) (с учетом доли брендирования)
B28: 4 | C28: Тип активации: ДО МЕРОПРИЯТИЯ (медиа продвижение и PR) | D28: ТВ | J28: =SUM(J29:J30) -> 0 | K28: Количество минут в день | L28: Каналы | M28: Хронометраж | N28: Время взаимодействия с креативом | O28: =IFERROR(IF(J28>0,J28/VLOOKUP(D28,'[1]Коэфы качество контакта'!$A$2:$G$22,7,FALSE),(1-(1-(O29/$E$21*0.5))*(1-(O30/$E$21*0.5)))*$E$21),0) -> 0
D29: ТВ | E29: Спонсорство | J29: {=IFERROR(IF(H29>0,H29*G29,IF(K29>0,SUM(OTSТВМосква)*G29*F29*(K29/200),IF(I29>0,G29*I29*SUMPRODUCT(('[1]Коэфы качество контакта'!$A$2:$A$50=D29)*'[1]Коэфы качество контакта'!$G$2:$G$50),""))),"")} | K29: =IFERROR(SUM(МинутыТВМосква),0) -> 0 | L29: Каналы из списка | N29: =M29*VLOOKUP(D29,'[1]Коэфы качество контакта'!$A$2:$E$22,3,FALSE)*VLOOKUP(D29,'[1]Коэфы качество контакта'!$A$2:$E$22,5,FALSE) -> 0 | O29: =IFERROR(IF(I29>0,I29*G29,J29/VLOOKUP(D29,'[1]Коэфы качество контакта'!$A$2:$G$22,7,FALSE)),"") | P29: =_xlfn.CONCAT($E$22,E29) -> Спонсорство
D30: ТВ | E30: Прямая Реклама | J30: {=IFERROR(IF(H30>0,H30*G30,IF(K30>0,SUM(OTSТВМосква)*G30*F30*(K30/200),IF(I30>0,G30*I30*SUMPRODUCT(('[1]Коэфы качество контакта'!$A$2:$A$50=D30)*'[1]Коэфы качество контакта'!$G$2:$G$50),""))),"")} | K30: =IFERROR(SUM(МинутыТВМосква),0) -> 0 | L30: Каналы из списка | N30: =M30*VLOOKUP(D30,'[1]Коэфы качество контакта'!$A$2:$E$22,3,FALSE)*VLOOKUP(D30,'[1]Коэфы качество контакта'!$A$2:$E$22,5,FALSE) -> 0 | O30: =IFERROR(IF(I30>0,I30*G30,J30/VLOOKUP(D30,'[1]Коэфы качество контакта'!$A$2:$G$22,7,FALSE)),"") | P30: =_xlfn.CONCAT($E$22,E30) -> Прямая Реклама
D31: ООН | J31: =SUM(J32:J39) -> 0 | K31: Количество сторон | M31: Хронометраж | N31: Время взаимодействия с креативом | O31: =IF(J31>0,J31/VLOOKUP(D31,'[1]Коэфы качество контакта'!$A$2:$G$22,7,FALSE),(1-(1-(O32/$E$21*0.5))*(1-(O33/$E$21*0.5))*(1-(O34/$E$21*0.5))*(1-(O35/$E$21*0.5))*(1-(O36/$E$21*0.5))*(1-(O37/$E$21*0.5))*(1-(O38/$E$21*0.5))*(1-(O39/$E$21*0.5)))*$E$21) -> #VALUE!
D32: ООН | E32: BB | J32: {=IF(H32>0,H32*G32,IF(K32>0,SUMPRODUCT(([1]OOH!$A$2:$A$1000=TEMPLATE!$E$22)*([1]OOH!$B$2:$B$1000=TEMPLATE!$E32)*[1]OOH!$C$2:$C$1000)*F32*K32*G32,IF(I32>0,G32*I32*SUMPRODUCT(('[1]Коэфы качество контакта'!$A$2:$A$50=D32)*'[1]Коэфы качество контакта'!$G$2:$G$50),"")))} | L32: - | N32: =M32*VLOOKUP(D32,'[1]Коэфы качество контакта'!$A$2:$E$22,3,FALSE)*VLOOKUP(D32,'[1]Коэфы качество контакта'!$A$2:$E$22,5,FALSE) -> 0 | O32: =IFERROR(IF(I32>0,I32*G32,J32/VLOOKUP(D32,'[1]Коэфы качество контакта'!$A$2:$G$22,7,FALSE)),"")
D33: ООН | E33: DBB | J33: {=IF(H33>0,H33*G33,IF(K33>0,SUMPRODUCT(([1]OOH!$A$2:$A$1000=TEMPLATE!$E$22)*([1]OOH!$B$2:$B$1000=TEMPLATE!$E33)*[1]OOH!$C$2:$C$1000)*F33*K33*G33,IF(I33>0,G33*I33*SUMPRODUCT(('[1]Коэфы качество контакта'!$A$2:$A$50=D33)*'[1]Коэфы качество контакта'!$G$2:$G$50),"")))} | L33: - | N33: =M33*VLOOKUP(D33,'[1]Коэфы качество контакта'!$A$2:$E$22,3,FALSE)*VLOOKUP(D33,'[1]Коэфы качество контакта'!$A$2:$E$22,5,FALSE) -> 0 | O33: =IFERROR(IF(I33>0,I33*G33,J33/VLOOKUP(D33,'[1]Коэфы качество контакта'!$A$2:$G$22,7,FALSE)),"")
D34: ООН | E34: PL | J34: {=IF(H34>0,H34*G34,IF(K34>0,SUMPRODUCT(([1]OOH!$A$2:$A$1000=TEMPLATE!$E$22)*([1]OOH!$B$2:$B$1000=TEMPLATE!$E34)*[1]OOH!$C$2:$C$1000)*F34*K34*G34,IF(I34>0,G34*I34*SUMPRODUCT(('[1]Коэфы качество контакта'!$A$2:$A$50=D34)*'[1]Коэфы качество контакта'!$G$2:$G$50),"")))} | L34: - | N34: =M34*VLOOKUP(D34,'[1]Коэфы качество контакта'!$A$2:$E$22,3,FALSE)*VLOOKUP(D34,'[1]Коэфы качество контакта'!$A$2:$E$22,5,FALSE) -> 0 | O34: =IFERROR(IF(I34>0,I34*G34,J34/VLOOKUP(D34,'[1]Коэфы качество контакта'!$A$2:$G$22,7,FALSE)),"")
D35: ООН | E35: SS | J35: {=IF(H35>0,H35*G35,IF(K35>0,SUMPRODUCT(([1]OOH!$A$2:$A$1000=TEMPLATE!$E$22)*([1]OOH!$B$2:$B$1000=TEMPLATE!$E35)*[1]OOH!$C$2:$C$1000)*F35*K35*G35,IF(I35>0,G35*I35*SUMPRODUCT(('[1]Коэфы качество контакта'!$A$2:$A$50=D35)*'[1]Коэфы качество контакта'!$G$2:$G$50),"")))} | L35: - | N35: =M35*VLOOKUP(D35,'[1]Коэфы качество контакта'!$A$2:$E$22,3,FALSE)*VLOOKUP(D35,'[1]Коэфы качество контакта'!$A$2:$E$22,5,FALSE) -> 0 | O35: =IFERROR(IF(I35>0,I35*G35,J35/VLOOKUP(D35,'[1]Коэфы качество контакта'!$A$2:$G$22,7,FALSE)),"")
D36: ООН | E36: CF | J36: {=IF(H36>0,H36*G36,IF(K36>0,SUMPRODUCT(([1]OOH!$A$2:$A$1000=TEMPLATE!$E$22)*([1]OOH!$B$2:$B$1000=TEMPLATE!$E36)*[1]OOH!$C$2:$C$1000)*F36*K36*G36,IF(I36>0,G36*I36*SUMPRODUCT(('[1]Коэфы качество контакта'!$A$2:$A$50=D36)*'[1]Коэфы качество контакта'!$G$2:$G$50),"")))} | L36: - | N36: =M36*VLOOKUP(D36,'[1]Коэфы качество контакта'!$A$2:$E$22,3,FALSE)*VLOOKUP(D36,'[1]Коэфы качество контакта'!$A$2:$E$22,5,FALSE) -> 0 | O36: =IFERROR(IF(I36>0,I36*G36,J36/VLOOKUP(D36,'[1]Коэфы качество контакта'!$A$2:$G$22,7,FALSE)),"")
D37: ООН | J37: {=IF(H37>0,H37*G37,IF(K37>0,SUMPRODUCT(([1]OOH!$A$2:$A$1000=TEMPLATE!$E$22)*([1]OOH!$B$2:$B$1000=TEMPLATE!$E37)*[1]OOH!$C$2:$C$1000)*F37*K37*G37,IF(I37>0,G37*I37*SUMPRODUCT(('[1]Коэфы качество контакта'!$A$2:$A$50=D37)*'[1]Коэфы качество контакта'!$G$2:$G$50),"")))} | L37: - | N37: =M37*VLOOKUP(D37,'[1]Коэфы качество контакта'!$A$2:$E$22,3,FALSE)*VLOOKUP(D37,'[1]Коэфы качество контакта'!$A$2:$E$22,5,FALSE) -> 0 | O37: =IFERROR(IF(I37>0,I37*G37,J37/VLOOKUP(D37,'[1]Коэфы качество контакта'!$A$2:$G$22,7,FALSE)),"")
D38: ООН | J38: {=IF(H38>0,H38*G38,IF(K38>0,SUMPRODUCT(([1]OOH!$A$2:$A$1000=TEMPLATE!$E$22)*([1]OOH!$B$2:$B$1000=TEMPLATE!$E38)*[1]OOH!$C$2:$C$1000)*F38*K38*G38,IF(I38>0,G38*I38*SUMPRODUCT(('[1]Коэфы качество контакта'!$A$2:$A$50=D38)*'[1]Коэфы качество контакта'!$G$2:$G$50),"")))} | N38: =M38*VLOOKUP(D38,'[1]Коэфы качество контакта'!$A$2:$E$22,3,FALSE)*VLOOKUP(D38,'[1]Коэфы качество контакта'!$A$2:$E$22,5,FALSE) -> 0 | O38: =IFERROR(IF(I38>0,I38*G38,J38/VLOOKUP(D38,'[1]Коэфы качество контакта'!$A$2:$G$22,7,FALSE)),"")
D39: ООН | J39: {=IF(H39>0,H39*G39,IF(K39>0,SUMPRODUCT(([1]OOH!$A$2:$A$1000=TEMPLATE!$E$22)*([1]OOH!$B$2:$B$1000=TEMPLATE!$E39)*[1]OOH!$C$2:$C$1000)*F39*K39*G39,IF(I39>0,G39*I39*SUMPRODUCT(('[1]Коэфы качество контакта'!$A$2:$A$50=D39)*'[1]Коэфы качество контакта'!$G$2:$G$50),"")))} | L39: - | N39: =M39*VLOOKUP(D39,'[1]Коэфы качество контакта'!$A$2:$E$22,3,FALSE)*VLOOKUP(D39,'[1]Коэфы качество контакта'!$A$2:$E$22,5,FALSE) -> 0 | O39: =IFERROR(IF(I39>0,I39*G39,J39/VLOOKUP(D39,'[1]Коэфы качество контакта'!$A$2:$G$22,7,FALSE)),"")
D40: Indoor | J40: =SUM(J41:J60) -> 0 | M40: Хронометраж | N40: Время взаимодействия с креативом | O40: =IF(J40>0,J40/VLOOKUP(D40,'[1]Коэфы качество контакта'!$A$2:$G$22,7,FALSE),(1-(1-(O41/$E$21*0.5))*(1-(O42/$E$21*0.5))*(1-(O43/$E$21*0.5))*(1-(O44/$E$21*0.5))*(1-(O45/$E$21*0.5))*(1-(O46/$E$21*0.5))*(1-(O47/$E$21*0.5))*(1-(O48/$E$21*0.5))*(1-(O49/$E$21*0.5))*(1-(O50/$E$21*0.5))*(1-(O51/$E$21*0.5))*(1-(O52/$E$21*0.5))*(1-(O53/$E$21*0.5))*(1-(O54/$E$21*0.5))*(1-(O55/$E$21*0.5))*(1-(O56/$E$21*0.5))*(1-(O57/$E$21*0.5))*(1-(O58/$E$21*0.5))*(1-(O59/$E$21*0.5))*(1-(O60/$E$21*0.5)))*$E$21) -> #N/A
D41: Indoor | E41: Авиапарк | J41: {=IF(H41>0,H41*G41,IF(I41>0,G41*I41*SUMPRODUCT(('[1]Коэфы качество контакта'!$A$2:$A$50=D41)*'[1]Коэфы качество контакта'!$G$2:$G$50),SUMPRODUCT(([1]Indoor!$A$2:$A$996=TEMPLATE!$E$22)*([1]Indoor!$B$2:$B$996=TEMPLATE!$E41)*[1]Indoor!$F$2:$F$996)*F41*G41))} -> 0 | N41: =M41*VLOOKUP(D41,'[1]Коэфы качество контакта'!$A$2:$E$22,3,FALSE)*VLOOKUP(D41,'[1]Коэфы качество контакта'!$A$2:$E$22,5,FALSE) -> 0 | O41: {=IFERROR(IF(I41>0,I41*G41,J41/SUMPRODUCT(([1]Indoor!$A$2:$A$996=TEMPLATE!$E$22)*([1]Indoor!$B$2:$B$996=TEMPLATE!$E41)*[1]Indoor!$G$2:$G$996)),0)} -> 0
D42: Indoor | E42: ТЦ Атриум | J42: {=IF(H42>0,H42*G42,IF(I42>0,G42*I42*SUMPRODUCT(('[1]Коэфы качество контакта'!$A$2:$A$50=D42)*'[1]Коэфы качество контакта'!$G$2:$G$50),SUMPRODUCT(([1]Indoor!$A$2:$A$996=TEMPLATE!$E$22)*([1]Indoor!$B$2:$B$996=TEMPLATE!$E42)*[1]Indoor!$F$2:$F$996)*F42*G42))} -> 0 | N42: =M42*VLOOKUP(D42,'[1]Коэфы качество контакта'!$A$2:$E$22,3,FALSE)*VLOOKUP(D42,'[1]Коэфы качество контакта'!$A$2:$E$22,5,FALSE) -> 0 | O42: {=IFERROR(IF(I42>0,I42*G42,J42/SUMPRODUCT(([1]Indoor!$A$2:$A$996=TEMPLATE!$E$22)*([1]Indoor!$B$2:$B$996=TEMPLATE!$E42)*[1]Indoor!$G$2:$G$996)),0)} -> 0
D43: Indoor | E43: ПВЗ | J43: {=IF(H43>0,H43*G43,IF(I43>0,G43*I43*SUMPRODUCT(('[1]Коэфы качество контакта'!$A$2:$A$50=D43)*'[1]Коэфы качество контакта'!$G$2:$G$50),SUMPRODUCT(([1]Indoor!$A$2:$A$996=TEMPLATE!$E$22)*([1]Indoor!$B$2:$B$996=TEMPLATE!$E43)*[1]Indoor!$F$2:$F$996)*F43*G43))} -> 0 | N43: =M43*VLOOKUP(D43,'[1]Коэфы качество контакта'!$A$2:$E$22,3,FALSE)*VLOOKUP(D43,'[1]Коэфы качество контакта'!$A$2:$E$22,5,FALSE) -> 0 | O43: {=IFERROR(IF(I43>0,I43*G43,J43/SUMPRODUCT(([1]Indoor!$A$2:$A$996=TEMPLATE!$E$22)*([1]Indoor!$B$2:$B$996=TEMPLATE!$E43)*[1]Indoor!$G$2:$G$996)),0)} -> 0
D44: Indoor | E44: ТЦ Коламбус | J44: {=IF(H44>0,H44*G44,IF(I44>0,G44*I44*SUMPRODUCT(('[1]Коэфы качество контакта'!$A$2:$A$50=D44)*'[1]Коэфы качество контакта'!$G$2:$G$50),SUMPRODUCT(([1]Indoor!$A$2:$A$996=TEMPLATE!$E$22)*([1]Indoor!$B$2:$B$996=TEMPLATE!$E44)*[1]Indoor!$F$2:$F$996)*F44*G44))} -> 0 | N44: =M44*VLOOKUP(D44,'[1]Коэфы качество контакта'!$A$2:$E$22,3,FALSE)*VLOOKUP(D44,'[1]Коэфы качество контакта'!$A$2:$E$22,5,FALSE) -> 0 | O44: {=IFERROR(IF(I44>0,I44*G44,J44/SUMPRODUCT(([1]Indoor!$A$2:$A$996=TEMPLATE!$E$22)*([1]Indoor!$B$2:$B$996=TEMPLATE!$E44)*[1]Indoor!$G$2:$G$996)),0)} -> 0
D45: Indoor | J45: {=IF(H45>0,H45*G45,IF(I45>0,G45*I45*SUMPRODUCT(('[1]Коэфы качество контакта'!$A$2:$A$50=D45)*'[1]Коэфы качество контакта'!$G$2:$G$50),SUMPRODUCT(([1]Indoor!$A$2:$A$996=TEMPLATE!$E$22)*([1]Indoor!$B$2:$B$996=TEMPLATE!$E45)*[1]Indoor!$F$2:$F$996)*F45*G45))} -> 0 | N45: =M45*VLOOKUP(D45,'[1]Коэфы качество контакта'!$A$2:$E$22,3,FALSE)*VLOOKUP(D45,'[1]Коэфы качество контакта'!$A$2:$E$22,5,FALSE) -> 0 | O45: {=IFERROR(IF(I45>0,I45*G45,J45/SUMPRODUCT(([1]Indoor!$A$2:$A$996=TEMPLATE!$E$22)*([1]Indoor!$B$2:$B$996=TEMPLATE!$E45)*[1]Indoor!$G$2:$G$996)),0)} -> 0
D46: Indoor | J46: {=IF(H46>0,H46*G46,IF(I46>0,G46*I46*SUMPRODUCT(('[1]Коэфы качество контакта'!$A$2:$A$50=D46)*'[1]Коэфы качество контакта'!$G$2:$G$50),SUMPRODUCT(([1]Indoor!$A$2:$A$996=TEMPLATE!$E$22)*([1]Indoor!$B$2:$B$996=TEMPLATE!$E46)*[1]Indoor!$F$2:$F$996)*F46*G46))} -> 0 | N46: =M46*VLOOKUP(D46,'[1]Коэфы качество контакта'!$A$2:$E$22,3,FALSE)*VLOOKUP(D46,'[1]Коэфы качество контакта'!$A$2:$E$22,5,FALSE) -> 0 | O46: {=IFERROR(IF(I46>0,I46*G46,J46/SUMPRODUCT(([1]Indoor!$A$2:$A$996=TEMPLATE!$E$22)*([1]Indoor!$B$2:$B$996=TEMPLATE!$E46)*[1]Indoor!$G$2:$G$996)),0)} -> 0
D47: Indoor | J47: {=IF(H47>0,H47*G47,IF(I47>0,G47*I47*SUMPRODUCT(('[1]Коэфы качество контакта'!$A$2:$A$50=D47)*'[1]Коэфы качество контакта'!$G$2:$G$50),SUMPRODUCT(([1]Indoor!$A$2:$A$996=TEMPLATE!$E$22)*([1]Indoor!$B$2:$B$996=TEMPLATE!$E47)*[1]Indoor!$F$2:$F$996)*F47*G47))} -> 0 | N47: =M47*VLOOKUP(D47,'[1]Коэфы качество контакта'!$A$2:$E$22,3,FALSE)*VLOOKUP(D47,'[1]Коэфы качество контакта'!$A$2:$E$22,5,FALSE) -> 0 | O47: {=IFERROR(IF(I47>0,I47*G47,J47/SUMPRODUCT(([1]Indoor!$A$2:$A$996=TEMPLATE!$E$22)*([1]Indoor!$B$2:$B$996=TEMPLATE!$E47)*[1]Indoor!$G$2:$G$996)),0)} -> 0
D48: Indoor | J48: {=IF(H48>0,H48*G48,IF(I48>0,G48*I48*SUMPRODUCT(('[1]Коэфы качество контакта'!$A$2:$A$50=D48)*'[1]Коэфы качество контакта'!$G$2:$G$50),SUMPRODUCT(([1]Indoor!$A$2:$A$996=TEMPLATE!$E$22)*([1]Indoor!$B$2:$B$996=TEMPLATE!$E48)*[1]Indoor!$F$2:$F$996)*F48*G48))} -> 0 | N48: =M48*VLOOKUP(D48,'[1]Коэфы качество контакта'!$A$2:$E$22,3,FALSE)*VLOOKUP(D48,'[1]Коэфы качество контакта'!$A$2:$E$22,5,FALSE) -> 0 | O48: {=IFERROR(IF(I48>0,I48*G48,J48/SUMPRODUCT(([1]Indoor!$A$2:$A$996=TEMPLATE!$E$22)*([1]Indoor!$B$2:$B$996=TEMPLATE!$E48)*[1]Indoor!$G$2:$G$996)),0)} -> 0
D49: Indoor | J49: {=IF(H49>0,H49*G49,IF(I49>0,G49*I49*SUMPRODUCT(('[1]Коэфы качество контакта'!$A$2:$A$50=D49)*'[1]Коэфы качество контакта'!$G$2:$G$50),SUMPRODUCT(([1]Indoor!$A$2:$A$996=TEMPLATE!$E$22)*([1]Indoor!$B$2:$B$996=TEMPLATE!$E49)*[1]Indoor!$F$2:$F$996)*F49*G49))} -> 0 | N49: =M49*VLOOKUP(D49,'[1]Коэфы качество контакта'!$A$2:$E$22,3,FALSE)*VLOOKUP(D49,'[1]Коэфы качество контакта'!$A$2:$E$22,5,FALSE) -> 0 | O49: {=IFERROR(IF(I49>0,I49*G49,J49/SUMPRODUCT(([1]Indoor!$A$2:$A$996=TEMPLATE!$E$22)*([1]Indoor!$B$2:$B$996=TEMPLATE!$E49)*[1]Indoor!$G$2:$G$996)),0)} -> 0
D50: Indoor | J50: {=IF(H50>0,H50*G50,IF(I50>0,G50*I50*SUMPRODUCT(('[1]Коэфы качество контакта'!$A$2:$A$50=D50)*'[1]Коэфы качество контакта'!$G$2:$G$50),SUMPRODUCT(([1]Indoor!$A$2:$A$996=TEMPLATE!$E$22)*([1]Indoor!$B$2:$B$996=TEMPLATE!$E50)*[1]Indoor!$F$2:$F$996)*F50*G50))} -> 0 | N50: =M50*VLOOKUP(D50,'[1]Коэфы качество контакта'!$A$2:$E$22,3,FALSE)*VLOOKUP(D50,'[1]Коэфы качество контакта'!$A$2:$E$22,5,FALSE) -> 0 | O50: {=IFERROR(IF(I50>0,I50*G50,J50/SUMPRODUCT(([1]Indoor!$A$2:$A$996=TEMPLATE!$E$22)*([1]Indoor!$B$2:$B$996=TEMPLATE!$E50)*[1]Indoor!$G$2:$G$996)),0)} -> 0
D51: Indoor | J51: {=IF(H51>0,H51*G51,IF(I51>0,G51*I51*SUMPRODUCT(('[1]Коэфы качество контакта'!$A$2:$A$50=D51)*'[1]Коэфы качество контакта'!$G$2:$G$50),SUMPRODUCT(([1]Indoor!$A$2:$A$996=TEMPLATE!$E$22)*([1]Indoor!$B$2:$B$996=TEMPLATE!$E51)*[1]Indoor!$F$2:$F$996)*F51*G51))} -> 0 | N51: =M51*VLOOKUP(D51,'[1]Коэфы качество контакта'!$A$2:$E$22,3,FALSE)*VLOOKUP(D51,'[1]Коэфы качество контакта'!$A$2:$E$22,5,FALSE) -> 0 | O51: {=IFERROR(IF(I51>0,I51*G51,J51/SUMPRODUCT(([1]Indoor!$A$2:$A$996=TEMPLATE!$E$22)*([1]Indoor!$B$2:$B$996=TEMPLATE!$E51)*[1]Indoor!$G$2:$G$996)),0)} -> 0
D52: Indoor | J52: {=IF(H52>0,H52*G52,IF(I52>0,G52*I52*SUMPRODUCT(('[1]Коэфы качество контакта'!$A$2:$A$50=D52)*'[1]Коэфы качество контакта'!$G$2:$G$50),SUMPRODUCT(([1]Indoor!$A$2:$A$996=TEMPLATE!$E$22)*([1]Indoor!$B$2:$B$996=TEMPLATE!$E52)*[1]Indoor!$F$2:$F$996)*F52*G52))} -> 0 | N52: =M52*VLOOKUP(D52,'[1]Коэфы качество контакта'!$A$2:$E$22,3,FALSE)*VLOOKUP(D52,'[1]Коэфы качество контакта'!$A$2:$E$22,5,FALSE) -> 0 | O52: {=IFERROR(IF(I52>0,I52*G52,J52/SUMPRODUCT(([1]Indoor!$A$2:$A$996=TEMPLATE!$E$22)*([1]Indoor!$B$2:$B$996=TEMPLATE!$E52)*[1]Indoor!$G$2:$G$996)),0)} -> 0
D53: Indoor | J53: {=IF(H53>0,H53*G53,IF(I53>0,G53*I53*SUMPRODUCT(('[1]Коэфы качество контакта'!$A$2:$A$50=D53)*'[1]Коэфы качество контакта'!$G$2:$G$50),SUMPRODUCT(([1]Indoor!$A$2:$A$996=TEMPLATE!$E$22)*([1]Indoor!$B$2:$B$996=TEMPLATE!$E53)*[1]Indoor!$F$2:$F$996)*F53*G53))} -> 0 | N53: =M53*VLOOKUP(D53,'[1]Коэфы качество контакта'!$A$2:$E$22,3,FALSE)*VLOOKUP(D53,'[1]Коэфы качество контакта'!$A$2:$E$22,5,FALSE) -> 0 | O53: {=IFERROR(IF(I53>0,I53*G53,J53/SUMPRODUCT(([1]Indoor!$A$2:$A$996=TEMPLATE!$E$22)*([1]Indoor!$B$2:$B$996=TEMPLATE!$E53)*[1]Indoor!$G$2:$G$996)),0)} -> 0
D54: Indoor | J54: {=IF(H54>0,H54*G54,IF(I54>0,G54*I54*SUMPRODUCT(('[1]Коэфы качество контакта'!$A$2:$A$50=D54)*'[1]Коэфы качество контакта'!$G$2:$G$50),SUMPRODUCT(([1]Indoor!$A$2:$A$996=TEMPLATE!$E$22)*([1]Indoor!$B$2:$B$996=TEMPLATE!$E54)*[1]Indoor!$F$2:$F$996)*F54*G54))} -> 0 | N54: =M54*VLOOKUP(D54,'[1]Коэфы качество контакта'!$A$2:$E$22,3,FALSE)*VLOOKUP(D54,'[1]Коэфы качество контакта'!$A$2:$E$22,5,FALSE) -> 0 | O54: {=IFERROR(IF(I54>0,I54*G54,J54/SUMPRODUCT(([1]Indoor!$A$2:$A$996=TEMPLATE!$E$22)*([1]Indoor!$B$2:$B$996=TEMPLATE!$E54)*[1]Indoor!$G$2:$G$996)),0)} -> 0
D55: Indoor | J55: {=IF(H55>0,H55*G55,IF(I55>0,G55*I55*SUMPRODUCT(('[1]Коэфы качество контакта'!$A$2:$A$50=D55)*'[1]Коэфы качество контакта'!$G$2:$G$50),SUMPRODUCT(([1]Indoor!$A$2:$A$996=TEMPLATE!$E$22)*([1]Indoor!$B$2:$B$996=TEMPLATE!$E55)*[1]Indoor!$F$2:$F$996)*F55*G55))} -> 0 | N55: =M55*VLOOKUP(D55,'[1]Коэфы качество контакта'!$A$2:$E$22,3,FALSE)*VLOOKUP(D55,'[1]Коэфы качество контакта'!$A$2:$E$22,5,FALSE) -> 0 | O55: {=IFERROR(IF(I55>0,I55*G55,J55/SUMPRODUCT(([1]Indoor!$A$2:$A$996=TEMPLATE!$E$22)*([1]Indoor!$B$2:$B$996=TEMPLATE!$E55)*[1]Indoor!$G$2:$G$996)),0)} -> 0
D56: Indoor | J56: {=IF(H56>0,H56*G56,IF(I56>0,G56*I56*SUMPRODUCT(('[1]Коэфы качество контакта'!$A$2:$A$50=D56)*'[1]Коэфы качество контакта'!$G$2:$G$50),SUMPRODUCT(([1]Indoor!$A$2:$A$996=TEMPLATE!$E$22)*([1]Indoor!$B$2:$B$996=TEMPLATE!$E56)*[1]Indoor!$F$2:$F$996)*F56*G56))} -> 0 | N56: =M56*VLOOKUP(D56,'[1]Коэфы качество контакта'!$A$2:$E$22,3,FALSE)*VLOOKUP(D56,'[1]Коэфы качество контакта'!$A$2:$E$22,5,FALSE) -> 0 | O56: {=IFERROR(IF(I56>0,I56*G56,J56/SUMPRODUCT(([1]Indoor!$A$2:$A$996=TEMPLATE!$E$22)*([1]Indoor!$B$2:$B$996=TEMPLATE!$E56)*[1]Indoor!$G$2:$G$996)),0)} -> 0
... D60: Indoor | J60: {=IF(H60>0,H60*G60,IF(I60>0,G60*I60*SUMPRODUCT(('[1]Коэфы качество контакта'!$A$2:$A$50=D60)*'[1]Коэфы качество контакта'!$G$2:$G$50),SUMPRODUCT(([1]Indoor!$A$2:$A$996=TEMPLATE!$E$22)*([1]Indoor!$B$2:$B$996=TEMPLATE!$E60)*[1]Indoor!$F$2:$F$996)*F60*G60))} -> 0 | N60: =M60*VLOOKUP(D60,'[1]Коэфы качество контакта'!$A$2:$E$22,3,FALSE)*VLOOKUP(D60,'[1]Коэфы качество контакта'!$A$2:$E$22,5,FALSE) -> 0 | O60: {=IFERROR(IF(I60>0,I60*G60,J60/SUMPRODUCT(([1]Indoor!$A$2:$A$996=TEMPLATE!$E$22)*([1]Indoor!$B$2:$B$996=TEMPLATE!$E60)*[1]Indoor!$G$2:$G$996)),0)} -> 0
D61: Метро | J61: =SUM(J62:J66) -> 0 | K61: Количество выходов в день | L61: Количество веток | M61: Хронометраж | N61: Время взаимодействия с креативом | O61: =IF(J61>0,J61/VLOOKUP(D61,'[1]Коэфы качество контакта'!$A$2:$G$22,7,FALSE),(1-(1-(O62/$E$21*0.5))*(1-(O63/$E$21*0.5))*(1-(O64/$E$21*0.5))*(1-(O65/$E$21*0.5))*(1-(O66/$E$21*0.5)))*$E$21) -> #N/A
D62: Метро | E62: Digital Screen в вагонах | J62: {=IF(H62>0,H62*G62,IF(K62>0,SUMPRODUCT((([1]Метро!$A$2:$A$1000=TEMPLATE!$E$22)*[1]Метро!$E$2:$E$1000)/1000)*L62*F62*G62*SUMPRODUCT(([1]Метро!$F$2:$F$6=TEMPLATE!$E62)*[1]Метро!$G$2:$G$6)*K62,IF(I62>0,G62*I62*SUMPRODUCT(('[1]Коэфы качество контакта'!$A$2:$A$50=D62)*'[1]Коэфы качество контакта'!$G$2:$G$50),"")))} | N62: =M62*VLOOKUP(D62,'[1]Коэфы качество контакта'!$A$2:$E$22,3,FALSE)*VLOOKUP(D62,'[1]Коэфы качество контакта'!$A$2:$E$22,5,FALSE) -> 0 | O62: =IFERROR(IF(I62>0,I62*G62,J62/VLOOKUP(D62,'[1]Коэфы качество контакта'!$A$2:$G$22,7,FALSE)),) -> 0
D63: Метро | E63: DCF на ст.метро | J63: {=IF(H63>0,H63*G63,IF(K63>0,SUMPRODUCT((([1]Метро!$A$2:$A$1000=TEMPLATE!$E$22)*[1]Метро!$E$2:$E$1000)/1000)*L63*F63*G63*SUMPRODUCT(([1]Метро!$F$2:$F$6=TEMPLATE!$E63)*[1]Метро!$G$2:$G$6)*K63,IF(I63>0,G63*I63*SUMPRODUCT(('[1]Коэфы качество контакта'!$A$2:$A$50=D63)*'[1]Коэфы качество контакта'!$G$2:$G$50),"")))} | N63: =M63*VLOOKUP(D63,'[1]Коэфы качество контакта'!$A$2:$E$22,3,FALSE)*VLOOKUP(D63,'[1]Коэфы качество контакта'!$A$2:$E$22,5,FALSE) -> 0 | O63: =IFERROR(IF(I63>0,I63*G63,J63/VLOOKUP(D63,'[1]Коэфы качество контакта'!$A$2:$G$22,7,FALSE)),) -> 0
D64: Метро | E64: Digital Screen на ст.Савеловская | J64: {=IF(H64>0,H64*G64,IF(K64>0,SUMPRODUCT((([1]Метро!$A$2:$A$1000=TEMPLATE!$E$22)*[1]Метро!$E$2:$E$1000)/1000)*L64*F64*G64*SUMPRODUCT(([1]Метро!$F$2:$F$6=TEMPLATE!$E64)*[1]Метро!$G$2:$G$6)*K64,IF(I64>0,G64*I64*SUMPRODUCT(('[1]Коэфы качество контакта'!$A$2:$A$50=D64)*'[1]Коэфы качество контакта'!$G$2:$G$50),"")))} | N64: =M64*VLOOKUP(D64,'[1]Коэфы качество контакта'!$A$2:$E$22,3,FALSE)*VLOOKUP(D64,'[1]Коэфы качество контакта'!$A$2:$E$22,5,FALSE) -> 0 | O64: =IFERROR(IF(I64>0,I64*G64,J64/VLOOKUP(D64,'[1]Коэфы качество контакта'!$A$2:$G$22,7,FALSE)),) -> 0
D65: Метро | E65: Стикеры в вагонах А2 | J65: {=IF(H65>0,H65*G65,IF(K65>0,SUMPRODUCT((([1]Метро!$A$2:$A$1000=TEMPLATE!$E$22)*[1]Метро!$E$2:$E$1000)/1000)*L65*F65*G65*SUMPRODUCT(([1]Метро!$F$2:$F$6=TEMPLATE!$E65)*[1]Метро!$G$2:$G$6)*K65,IF(I65>0,G65*I65*SUMPRODUCT(('[1]Коэфы качество контакта'!$A$2:$A$50=D65)*'[1]Коэфы качество контакта'!$G$2:$G$50),"")))} | N65: =M65*VLOOKUP(D65,'[1]Коэфы качество контакта'!$A$2:$E$22,3,FALSE)*VLOOKUP(D65,'[1]Коэфы качество контакта'!$A$2:$E$22,5,FALSE) -> 0 | O65: =IFERROR(IF(I65>0,I65*G65,J65/VLOOKUP(D65,'[1]Коэфы качество контакта'!$A$2:$G$22,7,FALSE)),) -> 0
D66: Метро | E66: Стикеры в вагонах над дверью | J66: {=IF(H66>0,H66*G66,IF(K66>0,SUMPRODUCT((([1]Метро!$A$2:$A$1000=TEMPLATE!$E$22)*[1]Метро!$E$2:$E$1000)/1000)*L66*F66*G66*SUMPRODUCT(([1]Метро!$F$2:$F$6=TEMPLATE!$E66)*[1]Метро!$G$2:$G$6)*K66,IF(I66>0,G66*I66*SUMPRODUCT(('[1]Коэфы качество контакта'!$A$2:$A$50=D66)*'[1]Коэфы качество контакта'!$G$2:$G$50),"")))} | N66: =M66*VLOOKUP(D66,'[1]Коэфы качество контакта'!$A$2:$E$22,3,FALSE)*VLOOKUP(D66,'[1]Коэфы качество контакта'!$A$2:$E$22,5,FALSE) -> 0 | O66: =IFERROR(IF(I66>0,I66*G66,J66/VLOOKUP(D66,'[1]Коэфы качество контакта'!$A$2:$G$22,7,FALSE)),) -> 0
D67: Радио | J67: =SUM(J68:J69) -> 0 | K67: Количество выходов за весь период | L67: Радиостанции | M67: Хронометраж | N67: Время взаимодействия с креативом | O67: =IFERROR(IF(J67>0,J67/(VLOOKUP(D67,'[1]Коэфы качество контакта'!$A$2:$G$22,7,FALSE)*(MAX(F68:F69)/30.4)),(1-(1-(O68/$E$21*0.5))*(1-(O69/$E$21*0.5)))*$E$21),0) -> 0
D68: Радио | E68: Спонсорство | J68: {=IFERROR(IF(H68>0,H68*G68,IF(K68>0,SUM(OTSРадиоМосква)*G68*K68,IF(I68>0,G68*I68*SUMPRODUCT(('[1]Коэфы качество контакта'!$A$2:$A$50=D68)*'[1]Коэфы качество контакта'!$G$2:$G$50),""))),"")} | K68: =IFERROR(SUM(МинутыРадиоМосква),0) -> 0 | L68: Радиостанции из списка | N68: =M68*VLOOKUP(D68,'[1]Коэфы качество контакта'!$A$2:$E$22,3,FALSE)*VLOOKUP(D68,'[1]Коэфы качество контакта'!$A$2:$E$22,5,FALSE) -> 0 | O68: =IFERROR(IF(I68>0,I68*G68,J68/(VLOOKUP(D68,'[1]Коэфы качество контакта'!$A$2:$G$22,7,FALSE)*F68/30.4)),"") | P68: =_xlfn.CONCAT($E$22,E68) -> Спонсорство
D69: Радио | E69: Прямая Реклама | J69: {=IFERROR(IF(H69>0,H69*G69,IF(K69>0,SUM(OTSРадиоМосква)*G69*K69,IF(I69>0,G69*I69*SUMPRODUCT(('[1]Коэфы качество контакта'!$A$2:$A$50=D69)*'[1]Коэфы качество контакта'!$G$2:$G$50),""))),"")} | K69: =IFERROR(SUM(МинутыРадиоМосква),0) -> 0 | L69: Радиостанции из списка | N69: =M69*VLOOKUP(D69,'[1]Коэфы качество контакта'!$A$2:$E$22,3,FALSE)*VLOOKUP(D69,'[1]Коэфы качество контакта'!$A$2:$E$22,5,FALSE) -> 0 | O69: =IFERROR(IF(I69>0,I69*G69,J69/(VLOOKUP(D69,'[1]Коэфы качество контакта'!$A$2:$G$22,7,FALSE)*F69/30.4)),"") | P69: =_xlfn.CONCAT($E$22,E69) -> Прямая Реклама
D70: Digital | J70: =SUM(J71:J78) -> 0 | K70: Количество показов за весь период, тыс. | L70: Размер аудитории ресурса в тыс. (без продвижения) | M70: Хронометраж | N70: Время взаимодействия с креативом | O70: =IF((SUM(O71:O78)*0.6)<MAX(O71:O78),MAX(O71:O78),(SUM(O71:O78)*0.6)) -> 0
D71: Digital | E71: Видео без продвижения | J71: {=IFERROR(IF(H71>0,H71*G71,IF(K71>0,G71*K71,IF(L71>0,L71*G71*(1-SUMPRODUCT(([1]Списки!$F$2:$F$20=E71)*[1]Списки!$G$2:$G$20)),G71*I71*SUMPRODUCT(('[1]Коэфы качество контакта'!$A$2:$A$50=E71)*'[1]Коэфы качество контакта'!$G$2:$G$50)))),"")} -> 0 | N71: =IFERROR(M71*VLOOKUP(E71,'[1]Коэфы качество контакта'!$A$2:$E$50,3,FALSE)*VLOOKUP(E71,'[1]Коэфы качество контакта'!$A$2:$E$50,5,FALSE),"") -> 0 | O71: =IF(I70>0,I71*G71,IFERROR(J71/VLOOKUP(E71,'[1]Коэфы качество контакта'!$A$2:$G$50,7,FALSE),"")) -> 0
D72: Digital | E72: Промо-пост без продвижения | J72: {=IFERROR(IF(H72>0,H72*G72,IF(K72>0,G72*K72,IF(L72>0,L72*G72*(1-SUMPRODUCT(([1]Списки!$F$2:$F$20=E72)*[1]Списки!$G$2:$G$20)),G72*I72*SUMPRODUCT(('[1]Коэфы качество контакта'!$A$2:$A$50=E72)*'[1]Коэфы качество контакта'!$G$2:$G$50)))),"")} -> 0 | N72: =IFERROR(M72*VLOOKUP(E72,'[1]Коэфы качество контакта'!$A$2:$E$50,3,FALSE)*VLOOKUP(E72,'[1]Коэфы качество контакта'!$A$2:$E$50,5,FALSE),"") -> 0 | O72: =IF(I72>0,I72*G72,IFERROR(J72/VLOOKUP(E72,'[1]Коэфы качество контакта'!$A$2:$G$50,7,FALSE),"")) -> 0
D73: Digital | E73: Аудио | J73: {=IFERROR(IF(H73>0,H73*G73,IF(K73>0,G73*K73,IF(L73>0,L73*G73*(1-SUMPRODUCT(([1]Списки!$F$2:$F$20=E73)*[1]Списки!$G$2:$G$20)),G73*I73*SUMPRODUCT(('[1]Коэфы качество контакта'!$A$2:$A$50=E73)*'[1]Коэфы качество контакта'!$G$2:$G$50)))),"")} -> 0 | N73: =IFERROR(M73*VLOOKUP(E73,'[1]Коэфы качество контакта'!$A$2:$E$50,3,FALSE)*VLOOKUP(E73,'[1]Коэфы качество контакта'!$A$2:$E$50,5,FALSE),"") -> 0 | O73: =IF(I73>0,I73*G73,IFERROR(J73/VLOOKUP(E73,'[1]Коэфы качество контакта'!$A$2:$G$50,7,FALSE),"")) -> 0
D74: Digital | E74: Промо-пост | J74: {=IFERROR(IF(H74>0,H74*G74,IF(K74>0,G74*K74,IF(L74>0,L74*G74*(1-SUMPRODUCT(([1]Списки!$F$2:$F$20=E74)*[1]Списки!$G$2:$G$20)),G74*I74*SUMPRODUCT(('[1]Коэфы качество контакта'!$A$2:$A$50=E74)*'[1]Коэфы качество контакта'!$G$2:$G$50)))),"")} -> 0 | N74: =IFERROR(M74*VLOOKUP(E74,'[1]Коэфы качество контакта'!$A$2:$E$50,3,FALSE)*VLOOKUP(E74,'[1]Коэфы качество контакта'!$A$2:$E$50,5,FALSE),"") -> 0 | O74: =IF(I74>0,I74*G74,IFERROR(J74/VLOOKUP(E74,'[1]Коэфы качество контакта'!$A$2:$G$50,7,FALSE),"")) -> 0
D75: Digital | J75: {=IFERROR(IF(H75>0,H75*G75,IF(K75>0,G75*K75,IF(L75>0,L75*G75*(1-SUMPRODUCT(([1]Списки!$F$2:$F$20=E75)*[1]Списки!$G$2:$G$20)),G75*I75*SUMPRODUCT(('[1]Коэфы качество контакта'!$A$2:$A$50=E75)*'[1]Коэфы качество контакта'!$G$2:$G$50)))),"")} -> 0 | N75: =IFERROR(M75*VLOOKUP(E75,'[1]Коэфы качество контакта'!$A$2:$E$50,3,FALSE)*VLOOKUP(E75,'[1]Коэфы качество контакта'!$A$2:$E$50,5,FALSE),"") | O75: =IF(I75>0,I75*G75,IFERROR(J75/VLOOKUP(E75,'[1]Коэфы качество контакта'!$A$2:$G$50,7,FALSE),""))
D76: Digital | J76: {=IFERROR(IF(H76>0,H76*G76,IF(K76>0,G76*K76,IF(L76>0,L76*G76*(1-SUMPRODUCT(([1]Списки!$F$2:$F$20=E76)*[1]Списки!$G$2:$G$20)),G76*I76*SUMPRODUCT(('[1]Коэфы качество контакта'!$A$2:$A$50=E76)*'[1]Коэфы качество контакта'!$G$2:$G$50)))),"")} -> 0 | N76: =IFERROR(M76*VLOOKUP(E76,'[1]Коэфы качество контакта'!$A$2:$E$50,3,FALSE)*VLOOKUP(E76,'[1]Коэфы качество контакта'!$A$2:$E$50,5,FALSE),"") | O76: =IF(I76>0,I76*G76,IFERROR(J76/VLOOKUP(E76,'[1]Коэфы качество контакта'!$A$2:$G$50,7,FALSE),""))
D77: Digital | J77: {=IFERROR(IF(H77>0,H77*G77,IF(K77>0,G77*K77,IF(L77>0,L77*G77*(1-SUMPRODUCT(([1]Списки!$F$2:$F$20=E77)*[1]Списки!$G$2:$G$20)),G77*I77*SUMPRODUCT(('[1]Коэфы качество контакта'!$A$2:$A$50=E77)*'[1]Коэфы качество контакта'!$G$2:$G$50)))),"")} -> 0 | N77: =IFERROR(M77*VLOOKUP(E77,'[1]Коэфы качество контакта'!$A$2:$E$50,3,FALSE)*VLOOKUP(E77,'[1]Коэфы качество контакта'!$A$2:$E$50,5,FALSE),"") | O77: =IF(I77>0,I77*G77,IFERROR(J77/VLOOKUP(E77,'[1]Коэфы качество контакта'!$A$2:$G$50,7,FALSE),""))
D78: Digital | J78: {=IFERROR(IF(H78>0,H78*G78,IF(K78>0,G78*K78,IF(L78>0,L78*G78*(1-SUMPRODUCT(([1]Списки!$F$2:$F$20=E78)*[1]Списки!$G$2:$G$20)),G78*I78*SUMPRODUCT(('[1]Коэфы качество контакта'!$A$2:$A$50=E78)*'[1]Коэфы качество контакта'!$G$2:$G$50)))),"")} -> 0 | N78: =IFERROR(M78*VLOOKUP(E78,'[1]Коэфы качество контакта'!$A$2:$E$50,3,FALSE)*VLOOKUP(E78,'[1]Коэфы качество контакта'!$A$2:$E$50,5,FALSE),"") | O78: =IF(I78>0,I78*G78,IFERROR(J78/VLOOKUP(E78,'[1]Коэфы качество контакта'!$A$2:$G$50,7,FALSE),""))
D79: Айдентика Бренда партнера на сайте | J79: =SUM(J80:J85) -> 0 | K79: Посешаемость сайта за весь период, тыс. или заполнить сайт | L79: Сайт / размер аудитории | M79: Хронометраж | O79: =IF(J79>0,J79/1,IF((SUM(O80:O85)*0.6)>MAX(O80:O85),MAX(O80:O85),(SUM(O80:O85)*0.6))) -> 0
D80: Айдентика Бренда партнера на сайте | E80: Billboard в шапке сайта | J80: {=IF(I80>0,I80,IF(H80>0,H80*G80,IF(K80<>"",K80*G80,G80*SUMPRODUCT(([1]Списки!$S$2:$S$17=TEMPLATE!L80)*[1]Списки!$T$2:$T$17)/1000)))} -> 0 | O80: =IF(I80>0,I80*G80,J80/1) -> 0
D81: Айдентика Бренда партнера на сайте | E81: Баннер боковой в 1 экране | J81: {=IF(I81>0,I81,IF(H81>0,H81*G81,IF(K81<>"",K81*G81,G81*SUMPRODUCT(([1]Списки!$S$2:$S$17=TEMPLATE!L81)*[1]Списки!$T$2:$T$17)/1000)))} -> 0 | O81: =IF(I81>0,I81*G81,J81/1) -> 0
D82: Айдентика Бренда партнера на сайте | E82: Баннер боковой во 2м экране | J82: {=IF(I82>0,I82,IF(H82>0,H82*G82,IF(K82<>"",K82*G82,G82*SUMPRODUCT(([1]Списки!$S$2:$S$17=TEMPLATE!L82)*[1]Списки!$T$2:$T$17)/1000)))} -> 0 | O82: =IF(I82>0,I82*G82,J82/1) -> 0
D83: Айдентика Бренда партнера на сайте | J83: {=IF(I83>0,I83,IF(H83>0,H83*G83,IF(K83<>"",K83*G83,G83*SUMPRODUCT(([1]Списки!$S$2:$S$17=TEMPLATE!L83)*[1]Списки!$T$2:$T$17)/1000)))} -> 0 | O83: =IF(I83>0,I83*G83,J83/1) -> 0
D84: Айдентика Бренда партнера на сайте | J84: {=IF(I84>0,I84,IF(H84>0,H84*G84,IF(K84<>"",K84*G84,G84*SUMPRODUCT(([1]Списки!$S$2:$S$17=TEMPLATE!L84)*[1]Списки!$T$2:$T$17)/1000)))} -> 0 | O84: =IF(I84>0,I84*G84,J84/1) -> 0
D85: Айдентика Бренда партнера на сайте | J85: {=IF(I85>0,I85,IF(H85>0,H85*G85,IF(K85<>"",K85*G85,G85*SUMPRODUCT(([1]Списки!$S$2:$S$17=TEMPLATE!L85)*[1]Списки!$T$2:$T$17)/1000)))} -> 0 | O85: =IF(I85>0,I85*G85,J85/1) -> 0
D86: PR | J86: =SUM(J87:J92) -> 0 | K86: Количество просмотров статьи, тыс. или заполнить сайт | L86: Сайт / размер аудитории | M86: Хронометраж | O86: =IF(J86>0,J86/1.5,(1-(1-(O87/$E$21*0.5))*(1-(O88/$E$21*0.5))*(1-(O89/$E$21*0.5))*(1-(O90/$E$21*0.5))*(1-(O91/$E$21*0.5))*(1-(O92/$E$21*0.5)))*$E$21) -> #N/A
D87: PR | E87: Статьи о событии | J87: {=IF(I87>0,I87*1.5,IF(H87>0,H87*G87,IF(K87<>"",K87*G87,G87*SUMPRODUCT(([1]Списки!$S$2:$S$17=TEMPLATE!L87)*[1]Списки!$T$2:$T$17)/1000)*(1-SUMPRODUCT(([1]Списки!$I$2:$I$7=TEMPLATE!E87)*[1]Списки!$J$2:$J$7))))} -> 0 | O87: =IF(I87>0,I87*G87,J87/1.5) -> 0
D88: PR | E88: Статьи с упоминанием события | J88: {=IF(I88>0,I88*1.5,IF(H88>0,H88*G88,IF(K88<>"",K88*G88,G88*SUMPRODUCT(([1]Списки!$S$2:$S$17=TEMPLATE!L88)*[1]Списки!$T$2:$T$17)/1000)*(1-SUMPRODUCT(([1]Списки!$I$2:$I$7=TEMPLATE!E88)*[1]Списки!$J$2:$J$7))))} -> 0 | O88: =IF(I88>0,I88*G88,J88/1.5) -> 0
D89: PR | E89: Посев в TG | J89: {=IF(I89>0,I89*1.5,IF(H89>0,H89*G89,IF(K89<>"",K89*G89,G89*SUMPRODUCT(([1]Списки!$S$2:$S$17=TEMPLATE!L89)*[1]Списки!$T$2:$T$17)/1000)*(1-SUMPRODUCT(([1]Списки!$I$2:$I$7=TEMPLATE!E89)*[1]Списки!$J$2:$J$7))))} -> 0 | O89: =IF(I89>0,I89*G89,J89/1.5) -> 0
D90: PR | E90: Блогеры в TG | J90: {=IF(I90>0,I90*1.5,IF(H90>0,H90*G90,IF(K90<>"",K90*G90,G90*SUMPRODUCT(([1]Списки!$S$2:$S$17=TEMPLATE!L90)*[1]Списки!$T$2:$T$17)/1000)*(1-SUMPRODUCT(([1]Списки!$I$2:$I$7=TEMPLATE!E90)*[1]Списки!$J$2:$J$7))))} -> 0 | O90: =IF(I90>0,I90*G90,J90/1.5) -> 0
D91: PR | E91: Блогеры в VK | J91: {=IF(I91>0,I91*1.5,IF(H91>0,H91*G91,IF(K91<>"",K91*G91,G91*SUMPRODUCT(([1]Списки!$S$2:$S$17=TEMPLATE!L91)*[1]Списки!$T$2:$T$17)/1000)*(1-SUMPRODUCT(([1]Списки!$I$2:$I$7=TEMPLATE!E91)*[1]Списки!$J$2:$J$7))))} -> 0 | O91: =IF(I91>0,I91*G91,J91/1.5) -> 0
D92: PR | E92: Посев в VK | J92: {=IF(I92>0,I92*1.5,IF(H92>0,H92*G92,IF(K92<>"",K92*G92,G92*SUMPRODUCT(([1]Списки!$S$2:$S$17=TEMPLATE!L92)*[1]Списки!$T$2:$T$17)/1000)*(1-SUMPRODUCT(([1]Списки!$I$2:$I$7=TEMPLATE!E92)*[1]Списки!$J$2:$J$7))))} -> 0 | O92: =IF(I92>0,I92*G92,J92/1.5) -> 0
B93: 5 | C93: Тип активации: ПРОДВИЖЕНИЕ НА МЕРОПРИЯТИИ | D93: Видео | J93: =SUM(J94:J97) -> 0 | O93: =IF(IF(COUNTIF($O$94:$O$97,">0")>1,(1-(1-($O$94/$E$26))*(1-($O$95/$E$26))*(1-($O$96/$E$26))*(1-($O$97/$E$26)))*$E$26,SUM($O$94:$O$97))>$E$26,E26,IF(COUNTIF($O$94:$O$97,">0")>1,(1-(1-($O$94/$E$26))*(1-($O$95/$E$26))*(1-($O$96/$E$26))*(1-($O$97/$E$26)))*$E$26,SUM($O$94:$O$97))) -> 0
D94: Видео | E94: Экраны на сцене | J94: {=IF(H94>0,H94*G94,G94*SUMPRODUCT(('[1]Коэфы брендирование'!$P$2:$P$5=TEMPLATE!E94)*'[1]Коэфы брендирование'!$Q$2:$Q$5)*$E$26)} -> 0 | O94: {=IFERROR(IF(I94>0,I94*G94,J94/SUMPRODUCT(('[1]Коэфы брендирование'!$P$2:$P$996=TEMPLATE!$E94)*'[1]Коэфы брендирование'!$R$2:$R$996)),"-")} -> 0
D95: Видео | E95: Экраны в чаше локации/стадиона | J95: {=IF(H95>0,H95*G95,G95*SUMPRODUCT(('[1]Коэфы брендирование'!$P$2:$P$5=TEMPLATE!E95)*'[1]Коэфы брендирование'!$Q$2:$Q$5)*$E$26)} -> 0 | O95: {=IFERROR(IF(I95>0,I95*G95,J95/SUMPRODUCT(('[1]Коэфы брендирование'!$P$2:$P$996=TEMPLATE!$E95)*'[1]Коэфы брендирование'!$R$2:$R$996)),"-")} -> 0
D96: Видео | E96: Плазменные панели на територии локации/стадиона | J96: {=IF(H96>0,H96*G96,G96*SUMPRODUCT(('[1]Коэфы брендирование'!$P$2:$P$5=TEMPLATE!E96)*'[1]Коэфы брендирование'!$Q$2:$Q$5)*$E$26)} -> 0 | O96: {=IFERROR(IF(I96>0,I96*G96,J96/SUMPRODUCT(('[1]Коэфы брендирование'!$P$2:$P$996=TEMPLATE!$E96)*'[1]Коэфы брендирование'!$R$2:$R$996)),"-")} -> 0
D97: Видео | E97: Лого на входе | J97: {=IF(H97>0,H97*G97,G97*SUMPRODUCT(('[1]Коэфы брендирование'!$P$2:$P$5=TEMPLATE!E97)*'[1]Коэфы брендирование'!$Q$2:$Q$5)*$E$26)} -> 0 | O97: {=IFERROR(IF(I97>0,I97*G97,J97/SUMPRODUCT(('[1]Коэфы брендирование'!$P$2:$P$996=TEMPLATE!$E97)*'[1]Коэфы брендирование'!$R$2:$R$996)),"-")} -> 0
D98: Аудио | J98: =SUM(J99:J100) -> 0 | O98: =IF(IF(COUNTIF($O$99:$O$100,">0")>1,(1-(1-($O$99/$E$26))*(1-($O$100/$E$26)))*$E$26,SUM($O$99:$O$100))>$E$26,E26,IF(COUNTIF($O$99:$O$100,">0")>1,(1-(1-($O$99/$E$26))*(1-($O$100/$E$26))*(1-($O$99/$E$26))*(1-($O$100/$E$26)))*$E$26,SUM($O$99:$O$100))) -> 0
D99: Аудио | E99: Голосовое сообщение до старта мероприятия | J99: {=IF(H99>0,H99*G99,G99*SUMPRODUCT(('[1]Коэфы брендирование'!$A$2:$A$3=TEMPLATE!E99)*'[1]Коэфы брендирование'!$B$2:$B$3)*$E$26)} -> 0 | O99: {=IFERROR(IF(I99>0,I99*G99,J99/SUMPRODUCT(('[1]Коэфы брендирование'!$A$2:$A$996=TEMPLATE!$E99)*'[1]Коэфы брендирование'!$C$2:$C$996)),"-")} -> 0
D100: Аудио | E100: Голосовое сообщение во время мероприятия | J100: {=IF(H100>0,H100*G100,G100*SUMPRODUCT(('[1]Коэфы брендирование'!$A$2:$A$3=TEMPLATE!E100)*'[1]Коэфы брендирование'!$B$2:$B$3)*$E$26)} -> 0 | O100: {=IFERROR(IF(I100>0,I100*G100,J100/SUMPRODUCT(('[1]Коэфы брендирование'!$A$2:$A$996=TEMPLATE!$E100)*'[1]Коэфы брендирование'!$C$2:$C$996)),"-")} -> 0
D101: Брендирование | J101: =SUM(J102:J123) -> 0 | O101: =IF(IF(COUNTIF($O$102:$O$123,">0")>1,(1-(1-($O$102/$E$26))*(1-($O$103/$E$26))*(1-($O$104/$E$26))*(1-($O$105/$E$26))*(1-($O$106/$E$26))*(1-($O$107/$E$26))*(1-($O$108/$E$26))*(1-($O$109/$E$26))*(1-($O$110/$E$26))*(1-($O$111/$E$26))*(1-($O$112/$E$26))*(1-($O$113/$E$26))*(1-($O$114/$E$26))*(1-($O$115/$E$26))*(1-($O$116/$E$26))*(1-($O$117/$E$26))*(1-($O$118/$E$26))*(1-($O$119/$E$26))*(1-($O$120/$E$26))*(1-($O$121/$E$26))*(1-($O$122/$E$26))*(1-($O$123/$E$26)))*$E$26,SUM($O$102:$O$123))>$E$26,E26,IF(COUNTIF($O$102:$O$123,">0")>1,(1-(1-($O$102/$E$26))*(1-($O$103/$E$26))*(1-($O$104/$E$26))*(1-($O$105/$E$26))*(1-($O$106/$E$26))*(1-($O$107/$E$26))*(1-($O$108/$E$26))*(1-($O$109/$E$26))*(1-($O$110/$E$26))*(1-($O$111/$E$26))*(1-($O$112/$E$26))*(1-($O$113/$E$26))*(1-($O$114/$E$26))*(1-($O$115/$E$26))*(1-($O$116/$E$26))*(1-($O$117/$E$26))*(1-($O$118/$E$26))*(1-($O$119/$E$26))*(1-($O$120/$E$26))*(1-($O$121/$E$26))*(1-($O$122/$E$26))*(1-($O$123/$E$26)))*$E$26,SUM($O$102:$O$123))) -> 0
D102: Брендирование | E102: брендинг вип-зоны | J102: {=IF(H102>0,H102*G102,G102*SUMPRODUCT(('[1]Коэфы брендирование'!$D$2:$D$23=TEMPLATE!E102)*'[1]Коэфы брендирование'!$E$2:$E$23)*$E$26*(1-SUMPRODUCT(([1]Списки!$W$2:$W$5=TEMPLATE!$E$23)*[1]Списки!$X$2:$X$5)))} -> 0 | O102: {=IFERROR(IF(I102>0,I102*G102,J102/SUMPRODUCT(('[1]Коэфы брендирование'!$D$2:$D$993=TEMPLATE!$E102)*'[1]Коэфы брендирование'!$F$2:$F$993)),0)} -> 0
D103: Брендирование | E103: размещение арт-объекта | J103: {=IF(H103>0,H103*G103,G103*SUMPRODUCT(('[1]Коэфы брендирование'!$D$2:$D$23=TEMPLATE!E103)*'[1]Коэфы брендирование'!$E$2:$E$23)*$E$26*(1-SUMPRODUCT(([1]Списки!$W$2:$W$5=TEMPLATE!$E$23)*[1]Списки!$X$2:$X$5)))} -> 0 | O103: {=IFERROR(IF(I103>0,I103*G103,J103/SUMPRODUCT(('[1]Коэфы брендирование'!$D$2:$D$993=TEMPLATE!$E103)*'[1]Коэфы брендирование'!$F$2:$F$993)),0)} -> 0
D104: Брендирование | E104: бренд-зона/лаундж-зона | J104: {=IF(H104>0,H104*G104,G104*SUMPRODUCT(('[1]Коэфы брендирование'!$D$2:$D$23=TEMPLATE!E104)*'[1]Коэфы брендирование'!$E$2:$E$23)*$E$26*(1-SUMPRODUCT(([1]Списки!$W$2:$W$5=TEMPLATE!$E$23)*[1]Списки!$X$2:$X$5)))} -> 0 | O104: {=IFERROR(IF(I104>0,I104*G104,J104/SUMPRODUCT(('[1]Коэфы брендирование'!$D$2:$D$993=TEMPLATE!$E104)*'[1]Коэфы брендирование'!$F$2:$F$993)),0)} -> 0
D105: Брендирование | E105: брендинг браслетов | J105: {=IF(H105>0,H105*G105,G105*SUMPRODUCT(('[1]Коэфы брендирование'!$D$2:$D$23=TEMPLATE!E105)*'[1]Коэфы брендирование'!$E$2:$E$23)*$E$26*(1-SUMPRODUCT(([1]Списки!$W$2:$W$5=TEMPLATE!$E$23)*[1]Списки!$X$2:$X$5)))} -> 0 | O105: {=IFERROR(IF(I105>0,I105*G105,J105/SUMPRODUCT(('[1]Коэфы брендирование'!$D$2:$D$993=TEMPLATE!$E105)*'[1]Коэфы брендирование'!$F$2:$F$993)),0)} -> 0
D106: Брендирование | E106: брендинг одежды персонала (бармены, гардеробщики) | J106: {=IF(H106>0,H106*G106,G106*SUMPRODUCT(('[1]Коэфы брендирование'!$D$2:$D$23=TEMPLATE!E106)*'[1]Коэфы брендирование'!$E$2:$E$23)*$E$26*(1-SUMPRODUCT(([1]Списки!$W$2:$W$5=TEMPLATE!$E$23)*[1]Списки!$X$2:$X$5)))} -> 0 | O106: {=IFERROR(IF(I106>0,I106*G106,J106/SUMPRODUCT(('[1]Коэфы брендирование'!$D$2:$D$993=TEMPLATE!$E106)*'[1]Коэфы брендирование'!$F$2:$F$993)),0)} -> 0
D107: Брендирование | E107: брендированная раздатка (например, флешмоб с брендированными масками с лицом артиста) | J107: {=IF(H107>0,H107*G107,G107*SUMPRODUCT(('[1]Коэфы брендирование'!$D$2:$D$23=TEMPLATE!E107)*'[1]Коэфы брендирование'!$E$2:$E$23)*$E$26*(1-SUMPRODUCT(([1]Списки!$W$2:$W$5=TEMPLATE!$E$23)*[1]Списки!$X$2:$X$5)))} -> 0 | O107: {=IFERROR(IF(I107>0,I107*G107,J107/SUMPRODUCT(('[1]Коэфы брендирование'!$D$2:$D$993=TEMPLATE!$E107)*'[1]Коэфы брендирование'!$F$2:$F$993)),0)} -> 0
D108: Брендирование | E108: брендированная зона раздачи мерча | J108: {=IF(H108>0,H108*G108,G108*SUMPRODUCT(('[1]Коэфы брендирование'!$D$2:$D$23=TEMPLATE!E108)*'[1]Коэфы брендирование'!$E$2:$E$23)*$E$26*(1-SUMPRODUCT(([1]Списки!$W$2:$W$5=TEMPLATE!$E$23)*[1]Списки!$X$2:$X$5)))} -> 0 | O108: {=IFERROR(IF(I108>0,I108*G108,J108/SUMPRODUCT(('[1]Коэфы брендирование'!$D$2:$D$993=TEMPLATE!$E108)*'[1]Коэфы брендирование'!$F$2:$F$993)),0)} -> 0
D109: Брендирование | J109: {=IF(H109>0,H109*G109,G109*SUMPRODUCT(('[1]Коэфы брендирование'!$D$2:$D$23=TEMPLATE!E109)*'[1]Коэфы брендирование'!$E$2:$E$23)*$E$26*(1-SUMPRODUCT(([1]Списки!$W$2:$W$5=TEMPLATE!$E$23)*[1]Списки!$X$2:$X$5)))} -> 0 | O109: {=IFERROR(IF(I109>0,I109*G109,J109/SUMPRODUCT(('[1]Коэфы брендирование'!$D$2:$D$993=TEMPLATE!$E109)*'[1]Коэфы брендирование'!$F$2:$F$993)),0)} -> 0
D110: Брендирование | J110: {=IF(H110>0,H110*G110,G110*SUMPRODUCT(('[1]Коэфы брендирование'!$D$2:$D$23=TEMPLATE!E110)*'[1]Коэфы брендирование'!$E$2:$E$23)*$E$26*(1-SUMPRODUCT(([1]Списки!$W$2:$W$5=TEMPLATE!$E$23)*[1]Списки!$X$2:$X$5)))} -> 0 | O110: {=IFERROR(IF(I110>0,I110*G110,J110/SUMPRODUCT(('[1]Коэфы брендирование'!$D$2:$D$993=TEMPLATE!$E110)*'[1]Коэфы брендирование'!$F$2:$F$993)),0)} -> 0
D111: Брендирование | J111: {=IF(H111>0,H111*G111,G111*SUMPRODUCT(('[1]Коэфы брендирование'!$D$2:$D$23=TEMPLATE!E111)*'[1]Коэфы брендирование'!$E$2:$E$23)*$E$26*(1-SUMPRODUCT(([1]Списки!$W$2:$W$5=TEMPLATE!$E$23)*[1]Списки!$X$2:$X$5)))} -> 0 | O111: {=IFERROR(IF(I111>0,I111*G111,J111/SUMPRODUCT(('[1]Коэфы брендирование'!$D$2:$D$993=TEMPLATE!$E111)*'[1]Коэфы брендирование'!$F$2:$F$993)),0)} -> 0
D112: Брендирование | J112: {=IF(H112>0,H112*G112,G112*SUMPRODUCT(('[1]Коэфы брендирование'!$D$2:$D$23=TEMPLATE!E112)*'[1]Коэфы брендирование'!$E$2:$E$23)*$E$26*(1-SUMPRODUCT(([1]Списки!$W$2:$W$5=TEMPLATE!$E$23)*[1]Списки!$X$2:$X$5)))} -> 0 | O112: {=IFERROR(IF(I112>0,I112*G112,J112/SUMPRODUCT(('[1]Коэфы брендирование'!$D$2:$D$993=TEMPLATE!$E112)*'[1]Коэфы брендирование'!$F$2:$F$993)),0)} -> 0
...

Sheet ТВ Каналы
A1: Город | B1: Формат | C1: Город+Формат | D1: Канал | E1: Минуты в день | F1: OTS | M1: Источник: Mediascope
A2: Москва | B2: Прямая Реклама | C2: =_xlfn.CONCAT(A2,B2) -> МоскваПрямая Реклама | D2: ТНТ 4 | F2: {=SUMPRODUCT((ТВ!$A$2:$A$1000='ТВ Каналы'!A2)*(ТВ!$B$2:$B$1000='ТВ Каналы'!D2)*ТВ!$C$2:$C$1000)} -> 2395
A3: Москва | B3: Прямая Реклама | C3: =_xlfn.CONCAT(A3,B3) -> МоскваПрямая Реклама | D3: ПЯТНИЦА | F3: {=SUMPRODUCT((ТВ!$A$2:$A$1000='ТВ Каналы'!A3)*(ТВ!$B$2:$B$1000='ТВ Каналы'!D3)*ТВ!$C$2:$C$1000)} -> 33455
A4: Москва | B4: Спонсорство | C4: =_xlfn.CONCAT(A4,B4) -> МоскваСпонсорство | D4: Ю | F4: {=SUMPRODUCT((ТВ!$A$2:$A$1000='ТВ Каналы'!A4)*(ТВ!$B$2:$B$1000='ТВ Каналы'!D4)*ТВ!$C$2:$C$1000)} -> 6309
A5: Москва | B5: Спонсорство | C5: =_xlfn.CONCAT(A5,B5) -> МоскваСпонсорство | D5: СТС LOVE | F5: {=SUMPRODUCT((ТВ!$A$2:$A$1000='ТВ Каналы'!A5)*(ТВ!$B$2:$B$1000='ТВ Каналы'!D5)*ТВ!$C$2:$C$1000)} -> 8526
A6: Санкт-Петербург | B6: Спонсорство | C6: =_xlfn.CONCAT(A6,B6) -> Санкт-ПетербургСпонсорство | D6: РОССИЯ 24 | F6: {=SUMPRODUCT((ТВ!$A$2:$A$1000='ТВ Каналы'!A6)*(ТВ!$B$2:$B$1000='ТВ Каналы'!D6)*ТВ!$C$2:$C$1000)} -> 9044
A7: Санкт-Петербург | B7: Спонсорство | C7: =_xlfn.CONCAT(A7,B7) -> Санкт-ПетербургСпонсорство | D7: ТНТ | F7: {=SUMPRODUCT((ТВ!$A$2:$A$1000='ТВ Каналы'!A7)*(ТВ!$B$2:$B$1000='ТВ Каналы'!D7)*ТВ!$C$2:$C$1000)} -> 9146
A8: Санкт-Петербург | B8: Прямая Реклама | C8: =_xlfn.CONCAT(A8,B8) -> Санкт-ПетербургПрямая Реклама | D8: РОССИЯ 24 | F8: {=SUMPRODUCT((ТВ!$A$2:$A$1000='ТВ Каналы'!A8)*(ТВ!$B$2:$B$1000='ТВ Каналы'!D8)*ТВ!$C$2:$C$1000)} -> 9044
A9: Санкт-Петербург | B9: Прямая Реклама | C9: =_xlfn.CONCAT(A9,B9) -> Санкт-ПетербургПрямая Реклама | D9: СТС | F9: {=SUMPRODUCT((ТВ!$A$2:$A$1000='ТВ Каналы'!A9)*(ТВ!$B$2:$B$1000='ТВ Каналы'!D9)*ТВ!$C$2:$C$1000)} -> 16314
A10: Краснодар | B10: Спонсорство | D10: ТНТ | F10: {=SUMPRODUCT((ТВ!$A$2:$A$1000='ТВ Каналы'!A10)*(ТВ!$B$2:$B$1000='ТВ Каналы'!D10)*ТВ!$C$2:$C$1000)} -> 1232
A11: Краснодар | B11: Спонсорство | C11: =_xlfn.CONCAT(A11,B11) -> КраснодарСпонсорство | D11: РОССИЯ 1 | F11: {=SUMPRODUCT((ТВ!$A$2:$A$1000='ТВ Каналы'!A11)*(ТВ!$B$2:$B$1000='ТВ Каналы'!D11)*ТВ!$C$2:$C$1000)} -> 7386
A12: Воронеж | B12: Прямая Реклама | C12: =_xlfn.CONCAT(A12,B12) -> ВоронежПрямая Реклама | D12: ПЕРВЫЙ КАНАЛ | F12: {=SUMPRODUCT((ТВ!$A$2:$A$1000='ТВ Каналы'!A12)*(ТВ!$B$2:$B$1000='ТВ Каналы'!D12)*ТВ!$C$2:$C$1000)} -> 16491
C13: =_xlfn.CONCAT(A13,B13) | F13: {=SUMPRODUCT((ТВ!$A$2:$A$1000='ТВ Каналы'!A13)*(ТВ!$B$2:$B$1000='ТВ Каналы'!D13)*ТВ!$C$2:$C$1000)} -> 0
C14: =_xlfn.CONCAT(A14,B14) | F14: {=SUMPRODUCT((ТВ!$A$2:$A$1000='ТВ Каналы'!A14)*(ТВ!$B$2:$B$1000='ТВ Каналы'!D14)*ТВ!$C$2:$C$1000)} -> 0
C15: =_xlfn.CONCAT(A15,B15) | F15: {=SUMPRODUCT((ТВ!$A$2:$A$1000='ТВ Каналы'!A15)*(ТВ!$B$2:$B$1000='ТВ Каналы'!D15)*ТВ!$C$2:$C$1000)} -> 0
C16: =_xlfn.CONCAT(A16,B16) | F16: {=SUMPRODUCT((ТВ!$A$2:$A$1000='ТВ Каналы'!A16)*(ТВ!$B$2:$B$1000='ТВ Каналы'!D16)*ТВ!$C$2:$C$1000)} -> 0
C17: =_xlfn.CONCAT(A17,B17) | F17: {=SUMPRODUCT((ТВ!$A$2:$A$1000='ТВ Каналы'!A17)*(ТВ!$B$2:$B$1000='ТВ Каналы'!D17)*ТВ!$C$2:$C$1000)} -> 0
C18: =_xlfn.CONCAT(A18,B18) | F18: {=SUMPRODUCT((ТВ!$A$2:$A$1000='ТВ Каналы'!A18)*(ТВ!$B$2:$B$1000='ТВ Каналы'!D18)*ТВ!$C$2:$C$1000)} -> 0
C19: =_xlfn.CONCAT(A19,B19) | F19: {=SUMPRODUCT((ТВ!$A$2:$A$1000='ТВ Каналы'!A19)*(ТВ!$B$2:$B$1000='ТВ Каналы'!D19)*ТВ!$C$2:$C$1000)} -> 0
C20: =_xlfn.CONCAT(A20,B20) | F20: {=SUMPRODUCT((ТВ!$A$2:$A$1000='ТВ Каналы'!A20)*(ТВ!$B$2:$B$1000='ТВ Каналы'!D20)*ТВ!$C$2:$C$1000)} -> 0
C21: =_xlfn.CONCAT(A21,B21) | F21: {=SUMPRODUCT((ТВ!$A$2:$A$1000='ТВ Каналы'!A21)*(ТВ!$B$2:$B$1000='ТВ Каналы'!D21)*ТВ!$C$2:$C$1000)} -> 0
C22: =_xlfn.CONCAT(A22,B22) | F22: {=SUMPRODUCT((ТВ!$A$2:$A$1000='ТВ Каналы'!A22)*(ТВ!$B$2:$B$1000='ТВ Каналы'!D22)*ТВ!$C$2:$C$1000)} -> 0
C23: =_xlfn.CONCAT(A23,B23) | F23: {=SUMPRODUCT((ТВ!$A$2:$A$1000='ТВ Каналы'!A23)*(ТВ!$B$2:$B$1000='ТВ Каналы'!D23)*ТВ!$C$2:$C$1000)} -> 0
C24: =_xlfn.CONCAT(A24,B24) | F24: {=SUMPRODUCT((ТВ!$A$2:$A$1000='ТВ Каналы'!A24)*(ТВ!$B$2:$B$1000='ТВ Каналы'!D24)*ТВ!$C$2:$C$1000)} -> 0
... C995: =_xlfn.CONCAT(A995,B995) | F995: {=SUMPRODUCT((ТВ!$A$2:$A$1000='ТВ Каналы'!A995)*(ТВ!$B$2:$B$1000='ТВ Каналы'!D995)*ТВ!$C$2:$C$1000)} -> 0

Sheet Радиостанции
A1: Город | B1: Формат | C1: Город+Формат | D1: Радиостанция | E1: Количество выходов за весь период | F1: OTS | J1: Источник: Mediascope
A2: Москва | B2: Прямая Реклама | C2: =_xlfn.CONCAT(A2,B2) -> МоскваПрямая Реклама | D2: Авторадио | E2: 0 | F2: {=SUMPRODUCT((Radio!$A$2:$A$1000=Радиостанции!A2)*(Radio!$B$2:$B$1000=Радиостанции!D2)*Radio!$C$2:$C$1000)} -> 397.21429
A3: Москва | B3: Прямая Реклама | C3: =_xlfn.CONCAT(A3,B3) -> МоскваПрямая Реклама | D3: Like FM | E3: 0 | F3: {=SUMPRODUCT((Radio!$A$2:$A$1000=Радиостанции!A3)*(Radio!$B$2:$B$1000=Радиостанции!D3)*Radio!$C$2:$C$1000)} -> 137.32857
A4: Москва | B4: Прямая Реклама | C4: =_xlfn.CONCAT(A4,B4) -> МоскваПрямая Реклама | D4: Comedy Radio | E4: 0 | F4: {=SUMPRODUCT((Radio!$A$2:$A$1000=Радиостанции!A4)*(Radio!$B$2:$B$1000=Радиостанции!D4)*Radio!$C$2:$C$1000)} -> 221.9
A5: Москва | B5: Прямая Реклама | C5: =_xlfn.CONCAT(A5,B5) -> МоскваПрямая Реклама | D5: Юмор FM | E5: 0 | F5: {=SUMPRODUCT((Radio!$A$2:$A$1000=Радиостанции!A5)*(Radio!$B$2:$B$1000=Радиостанции!D5)*Radio!$C$2:$C$1000)} -> 232.98571
A6: Москва | B6: Прямая Реклама | C6: =_xlfn.CONCAT(A6,B6) -> МоскваПрямая Реклама | D6: Relax FM | E6: 0 | F6: {=SUMPRODUCT((Radio!$A$2:$A$1000=Радиостанции!A6)*(Radio!$B$2:$B$1000=Радиостанции!D6)*Radio!$C$2:$C$1000)} -> 222.78571
A7: Москва | B7: Спонсорство | C7: =_xlfn.CONCAT(A7,B7) -> МоскваСпонсорство | D7: Радио ENERGY | E7: 20 | F7: {=SUMPRODUCT((Radio!$A$2:$A$1000=Радиостанции!A7)*(Radio!$B$2:$B$1000=Радиостанции!D7)*Radio!$C$2:$C$1000)} -> 246.85714
A8: Москва | B8: Спонсорство | C8: =_xlfn.CONCAT(A8,B8) -> МоскваСпонсорство | D8: Comedy Radio | E8: 20 | F8: {=SUMPRODUCT((Radio!$A$2:$A$1000=Радиостанции!A8)*(Radio!$B$2:$B$1000=Радиостанции!D8)*Radio!$C$2:$C$1000)} -> 221.9
A9: Москва | B9: Спонсорство | C9: =_xlfn.CONCAT(A9,B9) -> МоскваСпонсорство | D9: Like FM | E9: 20 | F9: {=SUMPRODUCT((Radio!$A$2:$A$1000=Радиостанции!A9)*(Radio!$B$2:$B$1000=Радиостанции!D9)*Radio!$C$2:$C$1000)} -> 137.32857
A10: Санкт-Петербург | B10: Прямая Реклама | C10: =_xlfn.CONCAT(A10,B10) -> Санкт-ПетербургПрямая Реклама | D10: STUDIO 21 | E10: 200 | F10: {=SUMPRODUCT((Radio!$A$2:$A$1000=Радиостанции!A10)*(Radio!$B$2:$B$1000=Радиостанции!D10)*Radio!$C$2:$C$1000)} -> 26.185714
A11: Санкт-Петербург | B11: Прямая Реклама | C11: =_xlfn.CONCAT(A11,B11) -> Санкт-ПетербургПрямая Реклама | D11: Like FM | F11: {=SUMPRODUCT((Radio!$A$2:$A$1000=Радиостанции!A11)*(Radio!$B$2:$B$1000=Радиостанции!D11)*Radio!$C$2:$C$1000)} -> 27.214286
A12: Санкт-Петербург | B12: Спонсорство | C12: =_xlfn.CONCAT(A12,B12) -> Санкт-ПетербургСпонсорство | D12: Европа Плюс | F12: {=SUMPRODUCT((Radio!$A$2:$A$1000=Радиостанции!A12)*(Radio!$B$2:$B$1000=Радиостанции!D12)*Radio!$C$2:$C$1000)} -> 181.92857
A13: Краснодар | B13: Спонсорство | C13: =_xlfn.CONCAT(A13,B13) -> КраснодарСпонсорство | D13: Авторадио | F13: {=SUMPRODUCT((Radio!$A$2:$A$1000=Радиостанции!A13)*(Radio!$B$2:$B$1000=Радиостанции!D13)*Radio!$C$2:$C$1000)} -> 37.214286
A14: Краснодар | B14: Прямая Реклама | C14: =_xlfn.CONCAT(A14,B14) -> КраснодарПрямая Реклама | D14: Европа Плюс | F14: {=SUMPRODUCT((Radio!$A$2:$A$1000=Радиостанции!A14)*(Radio!$B$2:$B$1000=Радиостанции!D14)*Radio!$C$2:$C$1000)} -> 41.742857
A15: Екатеринбург | B15: Прямая Реклама | C15: =_xlfn.CONCAT(A15,B15) -> ЕкатеринбургПрямая Реклама | D15: Business FM | F15: {=SUMPRODUCT((Radio!$A$2:$A$1000=Радиостанции!A15)*(Radio!$B$2:$B$1000=Радиостанции!D15)*Radio!$C$2:$C$1000)} -> 23.857143
C16: =_xlfn.CONCAT(A16,B16) | F16: {=SUMPRODUCT((Radio!$A$2:$A$1000=Радиостанции!A16)*(Radio!$B$2:$B$1000=Радиостанции!D16)*Radio!$C$2:$C$1000)} -> 0
C17: =_xlfn.CONCAT(A17,B17) | F17: {=SUMPRODUCT((Radio!$A$2:$A$1000=Радиостанции!A17)*(Radio!$B$2:$B$1000=Радиостанции!D17)*Radio!$C$2:$C$1000)} -> 0
C18: =_xlfn.CONCAT(A18,B18) | F18: {=SUMPRODUCT((Radio!$A$2:$A$1000=Радиостанции!A18)*(Radio!$B$2:$B$1000=Радиостанции!D18)*Radio!$C$2:$C$1000)} -> 0
C19: =_xlfn.CONCAT(A19,B19) | F19: {=SUMPRODUCT((Radio!$A$2:$A$1000=Радиостанции!A19)*(Radio!$B$2:$B$1000=Радиостанции!D19)*Radio!$C$2:$C$1000)} -> 0
C20: =_xlfn.CONCAT(A20,B20) | F20: {=SUMPRODUCT((Radio!$A$2:$A$1000=Радиостанции!A20)*(Radio!$B$2:$B$1000=Радиостанции!D20)*Radio!$C$2:$C$1000)} -> 0
C21: =_xlfn.CONCAT(A21,B21) | F21: {=SUMPRODUCT((Radio!$A$2:$A$1000=Радиостанции!A21)*(Radio!$B$2:$B$1000=Радиостанции!D21)*Radio!$C$2:$C$1000)} -> 0
C22: =_xlfn.CONCAT(A22,B22) | F22: {=SUMPRODUCT((Radio!$A$2:$A$1000=Радиостанции!A22)*(Radio!$B$2:$B$1000=Радиостанции!D22)*Radio!$C$2:$C$1000)} -> 0
C23: =_xlfn.CONCAT(A23,B23) | F23: {=SUMPRODUCT((Radio!$A$2:$A$1000=Радиостанции!A23)*(Radio!$B$2:$B$1000=Радиостанции!D23)*Radio!$C$2:$C$1000)} -> 0
C24: =_xlfn.CONCAT(A24,B24) | F24: {=SUMPRODUCT((Radio!$A$2:$A$1000=Радиостанции!A24)*(Radio!$B$2:$B$1000=Радиостанции!D24)*Radio!$C$2:$C$1000)} -> 0
C25: =_xlfn.CONCAT(A25,B25) | F25: {=SUMPRODUCT((Radio!$A$2:$A$1000=Радиостанции!A25)*(Radio!$B$2:$B$1000=Радиостанции!D25)*Radio!$C$2:$C$1000)} -> 0
C26: =_xlfn.CONCAT(A26,B26) | F26: {=SUMPRODUCT((Radio!$A$2:$A$1000=Радиостанции!A26)*(Radio!$B$2:$B$1000=Радиостанции!D26)*Radio!$C$2:$C$1000)} -> 0
C27: =_xlfn.CONCAT(A27,B27) | F27: {=SUMPRODUCT((Radio!$A$2:$A$1000=Радиостанции!A27)*(Radio!$B$2:$B$1000=Радиостанции!D27)*Radio!$C$2:$C$1000)} -> 0
... C1028: =_xlfn.CONCAT(A1028,B1028) | F1028: {=SUMPRODUCT((Radio!$A$2:$A$1000=Радиостанции!A1028)*(Radio!$B$2:$B$1000=Радиостанции!D1028)*Radio!$C$2:$C$1000)} -> 0

Sheet Коэфы качество контакта
A1: Каналы | B1: Хроно креатива | C1: Доля/Время взаимодействия с креативом | D1: Время взаимодействия с креативойм | E1: Качество контакта | F1: Индекс Качества контакта | G1: Частота
A2: Специальные проекты (среднее время на проекте) | B2: 150 | C2: 1 | D2: 150 | E2: 1.5 | F2: 225 | G2: 2
A3: Креативные видео интеграции в шоу (VK, YT) | B3: 120 | C3: 0.85 | D3: 102 | E3: 1.3 | F3: 132.6 | G3: 2
A4: Нативные видео интеграции у блогеров (VK, YT) | B4: 90 | C4: 0.8 | D4: 72 | E4: 1.1 | F4: 79.2 | G4: 2
A5: Альт-роллы YT | B5: 20 | C5: 0.7 | D5: 14 | E5: 1.05 | F5: 14.7 | G5: 2
A6: ТВ | B6: 5 | C6: 0.8 | D6: 4 | E6: 1 | F6: 4 | G6: 12
A7: Видео | B7: 20 | C7: 0.77 | D7: 15.4 | E7: 0.9 | F7: 13.86 | G7: 4
A8: Smart ТВ | B8: 20 | C8: 0.8 | D8: 16 | E8: 0.95 | F8: 15.2 | G8: 3
A9: Rewarded Видео | B9: 15 | C9: 0.8 | D9: 12 | E9: 0.85 | F9: 10.2 | G9: 4
A10: Блогеры (посты в ленте) | B10: 0-60 | C10: 7 | D10: 7 | E10: 0.77 | F10: 5.38 | G10: 2
A11: Посев в группах (посты в ленте) | B11: 0-60 | C11: 5 | D11: 5 | E11: 0.7 | F11: 3.52 | G11: 3
A12: TG стикеры | B12: - | C12: 7 | D12: 7 | E12: 0.74 | F12: 5.15 | G12: 3
A13: Радио | B13: 15 | C13: 0.8 | D13: 12 | E13: 0.66 | F13: 7.92 | G13: 6
A14: Промо-пост | B14: 0-20 | C14: 1.5 | D14: 1.5 | E14: 0.64 | F14: 0.96 | G14: 5
A15: Telegram Ads | B15: 0-20 | C15: 1.5 | D15: 1.5 | E15: 0.67 | F15: 1.01 | G15: 4
A16: Баннеры | B16: 0-6 | C16: 2 | D16: 2 | E16: 0.58 | F16: 1.16 | G16: 5
A17: Маркетплейсы | B17: 0-6 | C17: 2 | D17: 4 | E17: 0.58 | F17: 2.32 | G17: 3
A18: Аудио | B18: 15 | C18: 0.8 | D18: 12 | E18: 0.59 | F18: 7.13 | G18: 2
A19: Метро | B19: 0-5, от 1 до 5 | C19: 5 | D19: 5 | E19: 0.6 | F19: 3 | G19: 10
A20: Кассы самообслуживания в супермаркетах | B20: 0-5 | C20: 1.5 | D20: 1.5 | E20: 0.64 | F20: 0.96 | G20: 4
A21: Indoor | B21: 0-5 | C21: 5 | D21: 5 | E21: 0.6 | F21: 3 | G21: 5
A22: ООН | B22: 0-5 | C22: 3 | D22: 3 | E22: 0.5 | F22: 1.5 | G22: 15
A23: Карусель | B23: 0-20 | C23: 1.5 | D23: 1.5 | E23: 0.64 | F23: 0.96 | G23: 5
A24: OLV - размещение в видео (in-stream) | B24: 20 | C24: 0.77 | D24: 15.4 | E24: 0.9 | F24: 13.86 | G24: 4
A25: HTML5 баннер | B25: 0-20 | C25: 1.5 | D25: 1.5 | E25: 0.64 | F25: 0.96 | G25: 5
A26: Билборд в ВК | B26: 0-20 | C26: 1.5 | D26: 1.5 | E26: 0.64 | F26: 0.96 | G26: 5
A27: Видео без продвижения | B27: 20 | C27: 0.77 | D27: 15.4 | E27: 0.9 | F27: 13.86 | G27: 4
A28: Промо-пост без продвижения | B28: 0-20 | C28: 1.5 | D28: 1.5 | E28: 0.64 | F28: 0.96 | G28: 5
A33: заменяемые параметры
A34: добавленная эстимация
A37: Источник: оценка агентства OMD
E39: =1-(1-(#REF!*0.5))*(1-(#REF!*0.5))*(1-(#REF!*0.5)) -> #REF!

Sheet ЦА по городам
A1: Город | B1: Численность, уники
A2: Москва | B2: 11062570
A3: Санкт-Петербург | B3: 4746408
A4: Екатеринбург | B4: 1228946.4
A5: Томск | B5: 436312.8
A6: Кемерово | B6: 435680
A7: Казань | B7: 1054883.2
A8: Новосибирск | B8: 1307080.8
A9: Краснодар | B9: 910923.2
A10: Сочи | B10: 355991.2
A11: Чебоксары | B11: 393864.8
A12: Нижний Новгород | B12: 970781.6
A13: Хабаровск | B13: 492456
... A16: Воронеж | B16: 866979.2

Sheet Коэфы брендирование
A1: Аудио | B1: Коэф | C1: Частота | D1: Брендирование | E1: Коэф | F1: Частота | G1: Промо-акции | H1: Коэф | I1: Частота | J1: Взаимодействие с артистом во время мероприятия | K1: Коэф | L1: Частота | M1: UGC | N1: Коэф | O1: Частота | P1: Видео | Q1: Коэф | R1: Частота | S1: Лого партнера | T1: Коэф | U1: Частота
A2: Голосовое сообщение до старта мероприятия | B2: 0.8 | C2: 1 | D2: персональные браслеты (фан зона/танц пол) | E2: 0.9 | F2: 5 | G2: Различные акции с участием промо-персонала | H2: 0.2 | I2: 1.5 | J2: Интеграция в шоу (например, сброс брендированных шаров, упоминания от артиста на сцене) | K2: 0.8 | L2: 1.5 | M2: AR-фотозона (с интерактивом) | N2: 0.1 | O2: 2 | P2: Экраны на сцене | Q2: 0.8 | R2: 3 | S2: Интеграция в фото и видео отчеты | T2: 0.2 | U2: 1
A3: Голосовое сообщение во время мероприятия | B3: 0.9 | C3: 1 | D3: бренд-зона/лаундж-зона | E3: 0.7 | F3: 1.5 | M3: Посты в социальных сетях, опубликованные посетителями мероприятия | N3: 0.05 | O3: 1 | P3: Экраны в чаше локации/стадиона | Q3: 0.8 | R3: 3 | S3: PR публикации | T3: 0.2 | U3: 1
D4: печатные баннеры/бегущие строки на трибунах | E4: 0.7 | F4: 3 | M4: Фотозона | N4: 0.2 | O4: 2 | P4: Плазменные панели на територии локации/стадиона | Q4: 0.8 | R4: 3 | S4: Интеграция в посты у артиста | T4: 0.3 | U4: 1
D5: брендинг вип-зоны | E5: 0.1 | F5: 3 | P5: Лого на входе | Q5: 0.8 | R5: 1
D6: брендинг кресел во всем зале | E6: 0.9 | F6: 3
D7: брендинг сидушек/пуфиков/шезлонгов в общих зонах | E7: 0.9 | F7: 2
D8: брендинг браслетов | E8: 0.9 | F8: 6
D9: флаги/штендеры/лайтбоксы/расклеенные печатные лого/тейбл-тенты на локации мероприятия | E9: 0.8 | F9: 1.5
D10: брендинг зоны бара | E10: 0.6 | F10: 1
D11: брендинг сцены/спортивной площадки (например, логотип на льду на хоккее) | E11: 0.9 | F11: 1
D12: брендинг меню | E12: 0.6 | F12: 4
D13: брендинг посуды в баре | E13: 0.6 | F13: 1
D14: брендинг гардероба | E14: 0.9 | F14: 2
D15: брендинг номерков | E15: 0.9 | F15: 2
D16: брендинг зоны туалета | E16: 0.9 | F16: 1
D17: брендированная зона раздачи мерча | E17: 0.7 | F17: 1
... D24: AR-фотозона (с интерактивом) | E24: 0.1 | F24: 2
A25: Источник: оценка агентства OMD | D25: Фотозона | E25: 0.2 | F25: 2

Sheet ТВ
A1: Регион | B1: Канал | C1: OTS | G1: Источник: Mediascope
A2: Воронеж | B2: МИР | C2: 395
A3: Воронеж | B3: КАРУСЕЛЬ | C3: 784
A4: Воронеж | B4: ПЕРВЫЙ КАНАЛ | C4: 16491
A5: Воронеж | B5: РОССИЯ 1 | C5: 8049
A6: Воронеж | B6: НТВ | C6: 13938
A7: Воронеж | B7: СТС | C7: 873
A8: Воронеж | B8: ТВ ЦЕНТР | C8: 3007
A9: Воронеж | B9: РЕН ТВ | C9: 4692
A10: Воронеж | B10: ТНТ | C10: 4075
A11: Воронеж | B11: ПЯТНИЦА | C11: 3695
A12: Воронеж | B12: ТВ-3 | C12: 1277
A13: Воронеж | B13: ДОМАШНИЙ | C13: 2634
... A464: Хабаровск | B464: МОСФИЛЬМ. ЗОЛОТАЯ КОЛЛЕКЦИЯ | C464: 199

Sheet OOH
A1: Город | B1: Формат | C1: Ср OTS тыс. dly на 1 поверхность | F1: Источник: AdMetrix
A2: Москва | B2: BB | C2: 61.45
A3: Москва | B3: DBB | C3: 74.49
A4: Москва | B4: SS | C4: 35.44
A5: Москва | B5: DSS | C5: 162.69
A6: Москва | B6: CF | C6: 27.55
A7: Москва | B7: DCF | C7: 20.63
A8: Москва | B8: Медиафасады | C8: 138.32
A9: Москва | B9: PL | C9: 37.33
A10: Санкт-Петербург | B10: BB | C10: 27.78
A11: Санкт-Петербург | B11: DBB | C11: 37.04
A12: Санкт-Петербург | B12: SS | C12: 88.38
A13: Санкт-Петербург | B13: DSS | C13: 60.53
A14: Санкт-Петербург | B14: CF | C14: 20.03
A15: Санкт-Петербург | B15: DCF
A16: Санкт-Петербург | B16: Медиафасад
A17: Санкт-Петербург | B17: PL | C17: 18.8
A18: Екатеринбург | B18: BB | C18: 26.75
A19: Екатеринбург | B19: DBB | C19: 22.08
A20: Екатеринбург | B20: SS | C20: 87.74
A21: Екатеринбург | B21: DSS | C21: 57.83
A22: Екатеринбург | B22: CF | C22: 15.48
A23: Екатеринбург | B23: DCF | C23: 15.86
A24: Екатеринбург | B24: Медиафасад | C24: 76.24
A25: Екатеринбург | B25: PL
A26: Томск | B26: BB | C26: 21.54
A27: Томск | B27: DBB | C27: 24.34
A28: Томск | B28: SS | C28: 20.21
A29: Томск | B29: DSS | C29: 25
A30: Томск | B30: CF | C30: 19.17
A31: Томск | B31: DCF
A32: Томск | B32: Медиафасад
A33: Томск | B33: PL | C33: 18.46
A34: Кемерово | B34: BB
A35: Кемерово | B35: DBB
A36: Кемерово | B36: SS
A37: Кемерово | B37: DSS
A38: Кемерово | B38: CF
A39: Кемерово | B39: DCF
A40: Кемерово | B40: Медиафасад
A41: Кемерово | B41: PL
A42: Казань | B42: BB | C42: 41.48
A43: Казань | B43: DBB | C43: 45.62
A44: Казань | B44: SS | C44: 82.87
A45: Казань | B45: DSS | C45: 76.37
A46: Казань | B46: CF | C46: 18.86
A47: Казань | B47: DCF | C47: 23.15
A48: Казань | B48: Медиафасад
A49: Казань | B49: PL | C49: 18.98
A50: Новосибирск | B50: BB | C50: 44.71
A51: Новосибирск | B51: DBB | C51: 42.42
A52: Новосибирск | B52: SS | C52: 112.11
A53: Новосибирск | B53: DSS | C53: 85.63
A54: Новосибирск | B54: CF | C54: 21.5
A55: Новосибирск | B55: DCF | C55: 16.37
A56: Новосибирск | B56: Медиафасад
A57: Новосибирск | B57: PL | C57: 24.32
A58: Краснодар | B58: BB | C58: 27.05
A59: Краснодар | B59: DBB | C59: 35.08
A60: Краснодар | B60: SS | C60: 88.22
A61: Краснодар | B61: DSS | C61: 62.86
A62: Краснодар | B62: CF | C62: 18.97
A63: Краснодар | B63: DCF
A64: Краснодар | B64: Медиафасад
A65: Краснодар | B65: PL | C65: 12.25
A66: Сочи | B66: BB | C66: 24.48
A67: Сочи | B67: DBB | C67: 24.93
A68: Сочи | B68: SS | C68: 73.29
A69: Сочи | B69: DSS | C69: 31.2
A70: Сочи | B70: CF | C70: 20.79
A71: Сочи | B71: DCF | C71: 27.22
A72: Сочи | B72: Медиафасад | C72: 37.71
A73: Сочи | B73: PL | C73: 12.25
A74: Чебоксары | B74: BB | C74: 28.74
A75: Чебоксары | B75: DBB | C75: 27.51
A76: Чебоксары | B76: SS | C76: 64.41
A77: Чебоксары | B77: DSS
A78: Чебоксары | B78: CF | C78: 12.28
A79: Чебоксары | B79: DCF
A80: Чебоксары | B80: Медиафасад
A81: Чебоксары | B81: PL
A82: Нижний Новгород | B82: BB | C82: 32.79
A83: Нижний Новгород | B83: DBB | C83: 37.04
A84: Нижний Новгород | B84: SS | C84: 66.2
A85: Нижний Новгород | B85: DSS | C85: 55.01
A86: Нижний Новгород | B86: CF | C86: 23.23
A87: Нижний Новгород | B87: DCF | C87: 11.73
A88: Нижний Новгород | B88: Медиафасад
A89: Нижний Новгород | B89: PL | C89: 24.82
A90: Хабаровск | B90: BB | C90: 27.95
A91: Хабаровск | B91: DBB | C91: 34.27
A92: Хабаровск | B92: SS | C92: 53.93
A93: Хабаровск | B93: DSS | C93: 27.56
A94: Хабаровск | B94: CF | C94: 19.42
A95: Хабаровск | B95: DCF
A96: Хабаровск | B96: Медиафасад
A97: Хабаровск | B97: PL | C97: 13.24
A98: Калининград | B98: BB
A99: Калининград | B99: DBB
A100: Калининград | B100: SS
...

Sheet Метро
A1: Город | B1: Средний пассажиропоток в день в метро | C1: Средний пассажиропоток в день в метро, 18+ | D1: Количество веток | E1: Пассажиров приходится в день на ветку | F1: Формат | G1: Коэф
A2: Москва | B2: 8000000 | C2: =IFERROR(B2*0.76,"") -> 6080000 | D2: 13 | E2: =C2/D2 -> 467692.31 | F2: Digital Screen в вагонах | G2: 0.1
A3: Санкт-Петербург | B3: 2000000 | C3: =IFERROR(B3*0.76,"") -> 1520000 | D3: 5 | E3: =C3/D3 -> 304000 | F3: DCF на ст.метро | G3: 0.4
A4: Екатеринбург | B4: 150000 | C4: =IFERROR(B4*0.76,"") -> 114000 | D4: 1 | E4: =C4/D4 -> 114000 | F4: Digital Screen на ст.Савеловская | G4: 0.03
A5: Томск | C5: =IFERROR(B5*0.76,"") -> 0 | F5: Стикеры в вагонах А2 | G5: 0.4
A6: Кемерово | C6: =IFERROR(B6*0.76,"") -> 0 | F6: Стикеры в вагонах над дверью | G6: 0.4
A7: Казань | B7: 130000 | C7: =IFERROR(B7*0.76,"") -> 98800 | D7: 1 | E7: =C7/D7 -> 98800
A8: Новосибирск | B8: 231000 | C8: =IFERROR(B8*0.76,"") -> 175560 | D8: 2 | E8: =C8/D8 -> 87780
A9: Краснодар | C9: =IFERROR(B9*0.76,"") -> 0
A10: Сочи | C10: =IFERROR(B10*0.76,"") -> 0
A11: Чебоксары | C11: =IFERROR(B11*0.76,"") -> 0
A12: Нижний Новгород | B12: 83000 | C12: =IFERROR(B12*0.76,"") -> 63080 | D12: 2 | E12: =C12/D12 -> 31540
A13: Хабаровск | C13: =IFERROR(B13*0.76,"") -> 0
A14: Калининград | C14: =IFERROR(B14*0.76,"") -> 0
A15: Омск | C15: =IFERROR(B15*0.76,"") -> 0
A16: Воронеж | C16: =IFERROR(B16*0.76,"") -> 0
A19: Источник: оценка агентства OMD

Sheet Radio
A1: Город | B1: Станция | C1: OTS | G1: Источник: Mediascope
A2: Москва | B2: Business FM | C2: 213.84286
A3: Москва | B3: Comedy Radio | C3: 221.9
A4: Москва | B4: DFM | C4: 131.65714
A5: Москва | B5: Like FM | C5: 137.32857
A6: Москва | B6: Love Radio | C6: 169.47143
A7: Москва | B7: Maximum | C7: 166.7
A8: Москва | B8: Relax FM | C8: 222.78571
A9: Москва | B9: Rock FM | C9: 156.01429
A10: Москва | B10: Royal Radio | C10: 0
A11: Москва | B11: STUDIO 21 | C11: 54.742857
A12: Москва | B12: Авторадио | C12: 397.21429
A13: Москва | B13: БИМ радио | C13: 0
... A639: Воронеж | B639: Юмор FM | C639: 26.742857

Sheet Indoor
A1: Город | B1: Канал | C1: Носитель | D1: Продолжительность | E1: OTS 18+ в месяц | F1: OTS тыс. 18+ в день | G1: Частота
A2: Анапа | B2: ТЦ Красная Площадь | C2: экраны | D2: 30 | E2: 600400 | F2: =(E2/D2)/1000 -> 20.013333 | G2: 5
A3: Красногорск | B3: ТЦ Vegas, Крокус сити | C3: экраны | D3: 30 | E3: 1106000 | F3: =(E3/D3)/1000 -> 36.866667 | G3: 5
A4: Краснодар | B4: ТЦ Красная Площадь | C4: экраны | D4: 30 | E4: 1820087.3 | F4: =(E4/D4)/1000 -> 60.669577 | G4: 5
A5: Москва | B5: Такси | C5: экраны | D5: 30 | E5: 28900000 | F5: =(E5/D5)/1000 -> 963.33333 | G5: 5
A6: Москва | B6: Авиапарк | C6: экраны | D6: 30 | E6: 12000000 | F6: =(E6/D6)/1000 -> 400 | G6: 5
A7: Москва | B7: Digital-мобиль | C7: автомобиль | D7: 30 | E7: 7061400 | F7: =(E7/D7)/1000 -> 235.38 | G7: 5
A8: Москва | B8: ПВЗ | C8: экраны | D8: 30 | E8: 21502857 | F8: =(E8/D8)/1000 -> 716.7619 | G8: 5
A9: Москва | B9: Аэроэкспрессы (Москва) | C9: экраны | D9: 30 | E9: 12880173 | F9: =(E9/D9)/1000 -> 429.3391 | G9: 5
A10: Москва | B10: Сапсаны | C10: экраны | D10: 30 | E10: 393207.72 | F10: =(E10/D10)/1000 -> 13.106924 | G10: 5
A11: Москва | B11: Ласточки | C11: экраны | D11: 30 | E11: 3447000 | F11: =(E11/D11)/1000 -> 114.9 | G11: 5
A12: Москва | B12: ТЦ Коламбус | C12: экраны | D12: 30 | E12: 2370000 | F12: =(E12/D12)/1000 -> 79 | G12: 5
A13: Москва | B13: ТЦ Охотный ряд | C13: экраны | D13: 30 | E13: 5688000 | F13: =(E13/D13)/1000 -> 189.6 | G13: 5
... A37: Химки | B37: ТЦ Мега, Химки | C37: экраны | D37: 30 | E37: 3950000 | F37: =(E37/D37)/1000 -> 131.66667 | G37: 5
A40: Источник: оценка агентства OMD

Sheet ТВ исходник
A1: Блок распространения | B1: Канал | C1: Регион | D1: OTS
A2: Локальный | B2: ЗВЕЗДА | C2: КРАСНОДАР | D2: 94
A3: Локальный | B3: МАТЧ ТВ | C3: ОМСК | D3: 34
A4: Локальный | B4: МАТЧ ТВ | C4: КРАСНОДАР | D4: 321
A5: Локальный | B5: МАТЧ ТВ | C5: ХАБАРОВСК | D5: 20
A6: Локальный | B6: МАТЧ ТВ | C6: КЕМЕРОВО | D6: 23
A7: Локальный | B7: МАТЧ ТВ | C7: ТОМСК | D7: 42
A8: Локальный | B8: ТНТ 4 | C8: МОСКВА | D8: 152
A9: Локальный | B9: ТНТ 4 | C9: САНКТ-ПЕТЕРБУРГ | D9: 355
A10: Локальный | B10: ТНТ 4 | C10: НИЖНИЙ НОВГОРОД | D10: 18
A11: Локальный | B11: ТНТ 4 | C11: КАЗАНЬ | D11: 48
A12: Локальный | B12: ПЯТНИЦА | C12: КРАСНОДАР | D12: 111
A13: Локальный | B13: ТНТ 4 | C13: ЕКАТЕРИНБУРГ | D13: 125
... A805: Орбитальный | B805: ЧЕ | C805: КРАСНОДАР | D805: 163

Sheet Радио
A1: Охват | B1: Станция | C1: Москва | D1: Спб | E1: ЕКБ | F1: Казань | G1: Новосибирск | H1: Краснодар | I1: Сочи | J1: Нижний Новгород | K1: Хабаровск | L1: Омск | M1: Воронеж
A2: 16+ | B2: Business FM | C2: 213.84286 | D2: 75.285714 | E2: 23.857143 | F2: 14.571429 | G2: 18.814286 | H2: - | I2: - | J2: 12.385714 | K2: - | L2: - | M2: -
B3: Comedy Radio | C3: 221.9 | D3: 75.114286 | E3: 26.457143 | F3: - | G3: 30.457143 | H3: - | I3: - | J3: 23.585714 | K3: 5.4 | L3: 17.385714 | M3: -
B4: DFM | C4: 131.65714 | D4: 64.614286 | E4: - | F4: 26.471429 | G4: 20.828571 | H4: 20.242857 | I4: - | J4: - | K4: - | L4: - | M4: 21.542857
B5: Like FM | C5: 137.32857 | D5: 27.214286 | E5: - | F5: - | G5: 7.8428571 | H5: - | I5: - | J5: - | K5: - | L5: - | M5: 19.8
B6: Love Radio | C6: 169.47143 | D6: 94.014286 | E6: - | F6: - | G6: 18.357143 | H6: - | I6: - | J6: 21.028571 | K6: - | L6: - | M6: -
B7: Maximum | C7: 166.7 | D7: 75.542857 | E7: - | F7: - | G7: - | H7: - | I7: - | J7: - | K7: - | L7: 12.842857 | M7: -
B8: Relax FM | C8: 222.78571 | D8: - | E8: - | F8: 27.585714 | G8: 12.628571 | H8: - | I8: - | J8: 11.242857 | K8: - | L8: - | M8: 19.671429
B9: Rock FM | C9: 156.01429 | D9: 53.757143 | E9: - | F9: - | G9: - | H9: - | I9: - | J9: - | K9: - | L9: - | M9: -
B10: Royal Radio | C10: - | D10: 23.1 | E10: - | F10: - | G10: - | H10: - | I10: - | J10: - | K10: - | L10: - | M10: -
B11: STUDIO 21 | C11: 54.742857 | D11: 26.185714 | E11: 9.1285714 | F11: 8.4857143 | G11: - | H11: - | I11: - | J11: - | K11: 3.0571429 | L11: - | M11: -
B12: Авторадио | C12: 397.21429 | D12: 170.21429 | E12: 49.414286 | F12: 45.214286 | G12: 61.2 | H12: 37.214286 | I12: 16.928571 | J12: 42.985714 | K12: 27.928571 | L12: 45.142857 | M12: 50.657143
B13: БИМ радио | C13: - | D13: - | E13: - | F13: 42.414286 | G13: - | H13: - | I13: - | J13: - | K13: - | L13: - | M13: -
B14: Вести FM | C14: 274.08571 | D14: 110.5 | E14: - | F14: - | G14: - | H14: - | I14: - | J14: 29.8 | K14: - | L14: - | M14: -
B15: Восток FM | C15: 69.028571 | D15: - | E15: - | F15: - | G15: - | H15: - | I15: - | J15: - | K15: - | L15: - | M15: -
B16: Говорит Москва | C16: 124.17143 | D16: - | E16: - | F16: - | G16: - | H16: - | I16: - | J16: - | K16: - | L16: - | M16: -
B17: Детское Радио | C17: 131.78571 | D17: 48.542857 | E17: 18.271429 | F17: 13.985714 | G17: 16.071429 | H17: 7.7 | I17: - | J17: 11.757143 | K17: - | L17: 11.414286 | M17: 11.157143
B18: Дорожное радио | C18: 332.5 | D18: 232.94286 | E18: 43.4 | F18: 39.985714 | G18: 49.528571 | H18: 31.7 | I18: 16.314286 | J18: 41.028571 | K18: 21.885714 | L18: 47.585714 | M18: 53.2
B19: Джем FM | C19: - | D19: - | E19: 31.285714 | F19: - | G19: - | H19: - | I19: - | J19: - | K19: - | L19: - | M19: -
B20: Другое | C20: 496.42857 | D20: 115.1 | E20: 88.242857 | F20: 85.142857 | G20: 103.18571 | H20: 68.214286 | I20: 34.485714 | J20: 79.385714 | K20: 40.471429 | L20: 79.657143 | M20: 84
B21: Европа Плюс | C21: 316.98571 | D21: 181.92857 | E21: 52.014286 | F21: 46.285714 | G21: 47.7 | H21: 41.742857 | I21: 17.942857 | J21: 50.257143 | K21: 25.114286 | L21: 45.7 | M21: 41.671429
B22: Казак FM | C22: - | D22: - | E22: - | F22: - | G22: - | H22: 27.542857 | I22: - | J22: - | K22: - | L22: - | M22: -
B23: КоммерсантъFM | C23: 130.47143 | D23: - | E23: - | F23: - | G23: - | H23: - | I23: - | J23: - | K23: - | L23: - | M23: -
B24: Маяк | C24: 195.32857 | D24: 86.071429 | E24: - | F24: - | G24: - | H24: - | I24: - | J24: - | K24: - | L24: - | M24: -
B25: Москва FM | C25: 119.94286 | D25: - | E25: - | F25: - | G25: - | H25: - | I25: - | J25: - | K25: - | L25: - | M25: -
B26: Наше Радио | C26: 228.28571 | D26: 110.07143 | E26: - | F26: - | G26: - | H26: - | I26: - | J26: - | K26: - | L26: - | M26: -
B27: Новое Радио | C27: 100.58571 | D27: 51.985714 | E27: 19.514286 | F27: 17.328571 | G27: 18.485714 | H27: 10.4 | I27: - | J27: 11.885714 | K27: 6.7714286 | L27: 20.442857 | M27: 15.685714
B28: Орфей | C28: 91.014286 | D28: - | E28: - | F28: - | G28: - | H28: - | I28: - | J28: - | K28: - | L28: - | M28: -
B29: Питер FM | C29: - | D29: 138.34286 | E29: - | F29: - | G29: - | H29: - | I29: - | J29: - | K29: - | L29: - | M29: -
B30: Радио 107 | C30: - | D30: - | E30: - | F30: - | G30: - | H30: 16.842857 | I30: - | J30: - | K30: - | L30: - | M30: -
B31: Радио 7 на семи холмах | C31: 211.98571 | D31: - | E31: - | F31: - | G31: 23.4 | H31: - | I31: - | J31: 23.242857 | K31: - | L31: 7 | M31: 29.128571
B32: Радио ENERGY | C32: 246.85714 | D32: 78.914286 | E32: 25.057143 | F32: 31.057143 | G32: 30.914286 | H32: 17.5 | I32: - | J32: 22.928571 | K32: 10.628571 | L32: 16.657143 | M32: 20.3
B33: Радио Romantika | C33: 124.42857 | D33: - | E33: - | F33: - | G33: - | H33: - | I33: - | J33: - | K33: - | L33: - | M33: -
B34: Радио Metro | C34: - | D34: 31.228571 | E34: - | F34: - | G34: - | H34: - | I34: - | J34: - | K34: - | L34: - | M34: -
B35: Радио Sputnik | C35: 77.057143 | D35: 40.314286 | E35: - | F35: - | G35: - | H35: - | I35: - | J35: - | K35: - | L35: - | M35: -
B36: Радио Ваня | C36: - | D36: 100.94286 | E36: - | F36: - | G36: - | H36: - | I36: - | J36: - | K36: - | L36: 27.914286 | M36: -
B37: Радио Дача | C37: 264.52857 | D37: 111.21429 | E37: 42.671429 | F37: 34.6 | G37: 52.557143 | H37: 27.057143 | I37: - | J37: 42.457143 | K37: - | L37: 43.985714 | M37: -
B38: Радио Джаз | C38: 179.65714 | D38: - | E38: - | F38: - | G38: - | H38: - | I38: - | J38: - | K38: - | L38: - | M38: -
B39: Радио Звезда | C39: 158.05714 | D39: 38.842857 | E39: 15.342857 | F39: - | G39: - | H39: 11.157143 | I39: - | J39: - | K39: - | L39: - | M39: -
B40: Радио Комсомольская правда / Радио КП | C40: 140.85714 | D40: 39.971429 | E40: 15.985714 | F40: 12.671429 | G40: 15.342857 | H40: 10.885714 | I40: - | J40: - | K40: 7.8714286 | L40: - | M40: 14.228571
B41: Радио Культура | C41: 99.885714 | D41: - | E41: - | F41: - | G41: - | H41: - | I41: - | J41: - | K41: - | L41: - | M41: -
B42: Радио Монте-Карло | C42: 265.54286 | D42: 95.214286 | E42: 25.814286 | F42: 19.185714 | G42: - | H42: - | I42: - | J42: 24.714286 | K42: 11.614286 | L42: 21.5 | M42: 8.6285714
B43: Радио Петербург | C43: - | D43: 66.414286 | E43: - | F43: - | G43: - | H43: - | I43: - | J43: - | K43: - | L43: - | M43: -
B44: Радио Пилот | C44: - | D44: - | E44: 39.914286 | F44: - | G44: - | H44: - | I44: - | J44: - | K44: - | L44: - | M44: -
B45: Радио Рекорд | C45: - | D45: 102.17143 | E45: 21.842857 | F45: 25.171429 | G45: - | H45: - | I45: - | J45: 21.785714 | K45: - | L45: 27.071429 | M45: -
B46: Радио России | C46: 124.95714 | D46: 78.714286 | E46: - | F46: - | G46: - | H46: - | I46: - | J46: - | K46: - | L46: - | M46: -
B47: Радио Русский Хит | C47: 122.58571 | D47: - | E47: - | F47: - | G47: - | H47: - | I47: - | J47: - | K47: - | L47: - | M47: -
B48: Радио СИ | C48: - | D48: - | E48: 43.828571 | F48: - | G48: - | H48: - | I48: - | J48: - | K48: - | L48: - | M48: -
B49: Радио Сибирь | C49: - | D49: - | E49: - | F49: - | G49: - | H49: - | I49: - | J49: - | K49: - | L49: 23.485714 | M49: -
B50: Радио Шансон | C50: 269.47143 | D50: 102.05714 | E50: 36.242857 | F50: 30.628571 | G50: - | H50: - | I50: - | J50: 33.114286 | K50: - | L50: - | M50: -
B51: Радио Шоколад | C51: 147.68571 | D51: - | E51: - | F51: - | G51: - | H51: - | I51: - | J51: - | K51: - | L51: - | M51: -
B52: Радио Эрмитаж | C52: - | D52: 95.314286 | E52: - | F52: - | G52: - | H52: - | I52: - | J52: - | K52: - | L52: - | M52: -
B53: Радио Юнитон | C53: - | D53: - | E53: - | F53: - | G53: 33.357143 | H53: - | I53: - | J53: - | K53: - | L53: - | M53: -
B54: Ретро FM | C54: 350.67143 | D54: 156.95714 | E54: 44.914286 | F54: 42.142857 | G54: 47.157143 | H54: 37.114286 | I54: 14.6 | J54: 37.885714 | K54: 21.142857 | L54: 38.485714 | M54: 32.642857
B55: Русское Радио | C55: 326.54286 | D55: 128.67143 | E55: 42.9 | F55: 36.842857 | G55: 40.614286 | H55: 36.542857 | I55: 15.3 | J55: 44.242857 | K55: 20.714286 | L55: 34.471429 | M55: 39.985714
B56: Такси FM | C56: 96.685714 | D56: - | E56: - | F56: - | G56: - | H56: - | I56: - | J56: - | K56: - | L56: - | M56: -
B57: Хит FM | C57: 212.64286 | D57: 58.314286 | E57: 28.171429 | F57: - | G57: 23.371429 | H57: 22.971429 | I57: - | J57: 29 | K57: - | L57: - | M57: -
B58: Эльдорадио | C58: - | D58: 124.78571 | E58: - | F58: - | G58: - | H58: - | I58: - | J58: - | K58: - | L58: - | M58: -
B59: Юмор FM | C59: 232.98571 | D59: 91.985714 | E59: 40.157143 | F59: 29.542857 | G59: 40.028571 | H59: - | I59: - | J59: 26.142857 | K59: 7.7142857 | L59: - | M59: 26.742857
